Workbook
Name Slicer_Year: #N/A

Sheet pivot table
A3: Row Labels | B3: Sum of Net Sales | D3: Row Labels | E3: Sum of Net Sales | G3: Row Labels | H3: Sum of Profit/loss | J3: Row Labels | K3: Sum of Net Sales | M3: Row Labels | N3: Sum of OrderQuantity | P3: Row Labels | Q3: Count of Feedback Category
A4: 2026 | B4: 372154.52 | D4: Africa | E4: 241857.84 | G4: Asia | H4: 112686.62 | J4: Liam Chen | K4: 44339.168 | M4: Smartwatch | N4: 723 | P4: Negative | Q4: 36
A5: 2025 | B5: 297186.69 | D5: Europe | E5: 252958.85 | G5: North America | H5: 98944.172 | J5: Carlos Rodriguez | K5: 78765.721 | M5: Laptop | N5: 679 | P5: Neutral | Q5: 127
A6: 2024 | B6: 301306.01 | D6: North America | E6: 253644.17 | G6: Africa | H6: 93057.838 | J6: Emma Dubois | K6: 96946.052 | M6: Headphones | N6: 662 | P6: Postive | Q6: 271
A7: 2023 | B7: 361224.4 | D7: South America | E7: 274724.13 | G7: South America | H7: 85674.126 | J7: Olivia Patel | K7: 97540.157 | M7: Tablet | N7: 650 | P7: Grand Total | Q7: 434
A8: Grand Total | B8: 1331871.6 | D8: Asia | E8: 308686.62 | G8: Europe | H8: 74158.853 | J8: Noah Kim | K8: 98415.381 | M8: Smartphone | N8: 628
D9: Grand Total | E9: 1331871.6 | G9: Grand Total | H9: 464521.61 | J9: Ahmed Khan | K9: 194539.21 | M9: Grand Total | N9: 3342
J10: Fatima Adebayo | K10: 199117.3
J11: Maria Garcia | K11: 246447.65
J12: Sophie Lee | K12: 275760.96
J13: Grand Total | K13: 1331871.6

Sheet Sales Dataset
A1: OrderID | B1: CustomerID | C1: SalesRepID | D1: SalesRepName | E1: Date | F1: Year | G1: Month | H1: Day | I1: Time | J1: Hour | K1: Minute | L1: Product | M1: Product cat | N1: OrderQuantity | O1: UnitPrice | P1: Unit Cost | Q1: Region | R1: SalesRepEmail | S1: Feedback | T1: Feedback Category | U1: Gross Revenue | V1: Total Cost | W1: Tax Rate | X1: Tax Amount | Y1: Discount Rate | Z1: Discount Amount | AA1: Net Sales | AB1: Profit/loss
A2: ORD-00001 | B2: CUST-754 | C2: REP-13 | D2: Ahmed Khan | E2: 45490 | F2: =YEAR(E2) -> 2024 | G2: =TEXT(E2,"mmmm") -> July | H2: =TEXT(E2, "dddd") -> Wednesday | I2: 0.46443287 | J2: =HOUR(I2) -> 11 | K2: =MINUTE(I2) -> 8 | L2: Laptop | M2: Computers | N2: 15 | O2: 1095.25 | P2: =VLOOKUP(L2,'Product-cost'!A:B,2,FALSE) -> 600 | Q2: North America | R2: ahmedkhan@tg.inc | S2: Excellent quality | T2: Postive | U2: =O2*N2 -> 16428.75 | V2: =P2*N2 -> 9000 | W2: =VLOOKUP(Q2,Taxrate!A:B,2,FALSE) -> 0.07 | X2: =U2*W2 -> 1150.0125 | Y2: =VLOOKUP(L2,'Discount Rate'!A:B,2,FALSE) -> 0.05 | Z2: =Y2*U2 -> 821.4375 | AA2: =U2-X2-Z2 -> 14457.3 | AB2: =AA2-V2 -> 5457.3
A3: ORD-00002 | B3: CUST-529 | C3: REP-17 | D3: Maria Garcia | E3: 46133 | F3: =YEAR(E3) -> 2026 | G3: =TEXT(E3,"mmmm") -> April | H3: =TEXT(E3, "dddd") -> Tuesday | I3: 0.87152778 | J3: =HOUR(I3) -> 20 | K3: =MINUTE(I3) -> 55 | L3: Smartphone | M3: Mobile Devices | N3: 6 | O3: 544.59 | P3: =VLOOKUP(L3,'Product-cost'!A:B,2,FALSE) -> 300 | Q3: Asia | R3: mariagarcia@tg.inc | S3: Fast delivery | T3: Postive | U3: =O3*N3 -> 3267.54 | V3: =P3*N3 -> 1800 | W3: =VLOOKUP(Q3,Taxrate!A:B,2,FALSE) -> 0.1 | X3: =U3*W3 -> 326.754 | Y3: =VLOOKUP(L3,'Discount Rate'!A:B,2,FALSE) -> 0.1 | Z3: =Y3*U3 -> 326.754 | AA3: =U3-X3-Z3 -> 2614.032 | AB3: =AA3-V3 -> 814.032
A4: ORD-00003 | B4: CUST-649 | C4: REP-13 | D4: Ahmed Khan | E4: 45236 | F4: =YEAR(E4) -> 2023 | G4: =TEXT(E4,"mmmm") -> November | H4: =TEXT(E4, "dddd") -> Monday | I4: 0.90322917 | J4: =HOUR(I4) -> 21 | K4: =MINUTE(I4) -> 40 | L4: Tablet | M4: Tablets | N4: 12 | O4: 500 | P4: =VLOOKUP(L4,'Product-cost'!A:B,2,FALSE) -> 200 | Q4: Europe | R4: ahmedkhan@sales.techg.com | S4: Good value for money | T4: Postive | U4: =O4*N4 -> 6000 | V4: =P4*N4 -> 2400 | W4: =VLOOKUP(Q4,Taxrate!A:B,2,FALSE) -> 0.2 | X4: =U4*W4 -> 1200 | Y4: =VLOOKUP(L4,'Discount Rate'!A:B,2,FALSE) -> 0.08 | Z4: =Y4*U4 -> 480 | AA4: =U4-X4-Z4 -> 4320 | AB4: =AA4-V4 -> 1920
A5: ORD-00004 | B5: CUST-266 | C5: REP-22 | D5: Fatima Adebayo | E5: 45415 | F5: =YEAR(E5) -> 2024 | G5: =TEXT(E5,"mmmm") -> May | H5: =TEXT(E5, "dddd") -> Friday | I5: 0.83313657 | J5: =HOUR(I5) -> 19 | K5: =MINUTE(I5) -> 59 | L5: Laptop | M5: Computers | N5: 3 | O5: 922.41 | P5: =VLOOKUP(L5,'Product-cost'!A:B,2,FALSE) -> 600 | Q5: South America | R5: fatimaadebayo@sales.techg.com | S5: Very satisfied | T5: Postive | U5: =O5*N5 -> 2767.23 | V5: =P5*N5 -> 1800 | W5: =VLOOKUP(Q5,Taxrate!A:B,2,FALSE) -> 0.15 | X5: =U5*W5 -> 415.0845 | Y5: =VLOOKUP(L5,'Discount Rate'!A:B,2,FALSE) -> 0.05 | Z5: =Y5*U5 -> 138.3615 | AA5: =U5-X5-Z5 -> 2213.784 | AB5: =AA5-V5 -> 413.784
A6: ORD-00005 | B6: CUST-334 | C6: REP-11 | D6: Emma Dubois | E6: 45661 | F6: =YEAR(E6) -> 2025 | G6: =TEXT(E6,"mmmm") -> January | H6: =TEXT(E6, "dddd") -> Saturday | I6: 0.38469907 | J6: =HOUR(I6) -> 9 | K6: =MINUTE(I6) -> 13 | L6: Smartwatch | M6: Wearables | N6: 6 | O6: 230.92 | P6: =VLOOKUP(L6,'Product-cost'!A:B,2,FALSE) -> 150 | Q6: South America | R6: emmadubois@techgadgetsco.com | T6: Neutral | U6: =O6*N6 -> 1385.52 | V6: =P6*N6 -> 900 | W6: =VLOOKUP(Q6,Taxrate!A:B,2,FALSE) -> 0.15 | X6: =U6*W6 -> 207.828 | Y6: =VLOOKUP(L6,'Discount Rate'!A:B,2,FALSE) -> 0.07 | Z6: =Y6*U6 -> 96.9864 | AA6: =U6-X6-Z6 -> 1080.7056 | AB6: =AA6-V6 -> 180.7056
A7: ORD-00006 | B7: CUST-470 | C7: REP-17 | D7: Maria Garcia | E7: 45911 | F7: =YEAR(E7) -> 2025 | G7: =TEXT(E7,"mmmm") -> September | H7: =TEXT(E7, "dddd") -> Thursday | I7: 0.40836806 | J7: =HOUR(I7) -> 9 | K7: =MINUTE(I7) -> 48 | L7: Laptop | M7: Computers | N7: 3 | O7: 1011.08 | P7: =VLOOKUP(L7,'Product-cost'!A:B,2,FALSE) -> 600 | Q7: North America | R7: mariagarcia@techgadgetsco.com | T7: Neutral | U7: =O7*N7 -> 3033.24 | V7: =P7*N7 -> 1800 | W7: =VLOOKUP(Q7,Taxrate!A:B,2,FALSE) -> 0.07 | X7: =U7*W7 -> 212.3268 | Y7: =VLOOKUP(L7,'Discount Rate'!A:B,2,FALSE) -> 0.05 | Z7: =Y7*U7 -> 151.662 | AA7: =U7-X7-Z7 -> 2669.2512 | AB7: =AA7-V7 -> 869.2512
A8: ORD-00007 | B8: CUST-838 | C8: REP-13 | D8: Ahmed Khan | E8: 46150 | F8: =YEAR(E8) -> 2026 | G8: =TEXT(E8,"mmmm") -> May | H8: =TEXT(E8, "dddd") -> Friday | I8: 0.3878125 | J8: =HOUR(I8) -> 9 | K8: =MINUTE(I8) -> 18 | L8: Smartphone | M8: Mobile Devices | N8: 12 | O8: 559.02 | P8: =VLOOKUP(L8,'Product-cost'!A:B,2,FALSE) -> 300 | Q8: Africa | R8: ahmedkhan@sales.techg.com | T8: Neutral | U8: =O8*N8 -> 6708.24 | V8: =P8*N8 -> 3600 | W8: =VLOOKUP(Q8,Taxrate!A:B,2,FALSE) -> 0.12 | X8: =U8*W8 -> 804.9888 | Y8: =VLOOKUP(L8,'Discount Rate'!A:B,2,FALSE) -> 0.1 | Z8: =Y8*U8 -> 670.824 | AA8: =U8-X8-Z8 -> 5232.4272 | AB8: =AA8-V8 -> 1632.4272
A9: ORD-00008 | B9: CUST-482 | C9: REP-15 | D9: Sophie Lee | E9: 46013 | F9: =YEAR(E9) -> 2025 | G9: =TEXT(E9,"mmmm") -> December | H9: =TEXT(E9, "dddd") -> Monday | I9: 0.72258102 | J9: =HOUR(I9) -> 17 | K9: =MINUTE(I9) -> 20 | L9: Laptop | M9: Computers | N9: 6 | O9: 1215.83 | P9: =VLOOKUP(L9,'Product-cost'!A:B,2,FALSE) -> 600 | Q9: Asia | R9: sophielee@sales.techg.com | T9: Neutral | U9: =O9*N9 -> 7294.98 | V9: =P9*N9 -> 3600 | W9: =VLOOKUP(Q9,Taxrate!A:B,2,FALSE) -> 0.1 | X9: =U9*W9 -> 729.498 | Y9: =VLOOKUP(L9,'Discount Rate'!A:B,2,FALSE) -> 0.05 | Z9: =Y9*U9 -> 364.749 | AA9: =U9-X9-Z9 -> 6200.733 | AB9: =AA9-V9 -> 2600.733
A10: ORD-00009 | B10: CUST-878 | C10: REP-33 | D10: Ahmed Khan | E10: 45189 | F10: =YEAR(E10) -> 2023 | G10: =TEXT(E10,"mmmm") -> September | H10: =TEXT(E10, "dddd") -> Wednesday | I10: 0.6737963 | J10: =HOUR(I10) -> 16 | K10: =MINUTE(I10) -> 10 | L10: Smartwatch | M10: Wearables | N10: 7 | O10: 278.18 | P10: =VLOOKUP(L10,'Product-cost'!A:B,2,FALSE) -> 150 | Q10: Europe | R10: ahmedkhan@sales.techg.com | S10: Fast delivery | T10: Postive | U10: =O10*N10 -> 1947.26 | V10: =P10*N10 -> 1050 | W10: =VLOOKUP(Q10,Taxrate!A:B,2,FALSE) -> 0.2 | X10: =U10*W10 -> 389.452 | Y10: =VLOOKUP(L10,'Discount Rate'!A:B,2,FALSE) -> 0.07 | Z10: =Y10*U10 -> 136.3082 | AA10: =U10-X10-Z10 -> 1421.4998 | AB10: =AA10-V10 -> 371.4998
A11: ORD-00010 | B11: CUST-330 | C11: REP-12 | D11: Olivia Patel | E11: 44970 | F11: =YEAR(E11) -> 2023 | G11: =TEXT(E11,"mmmm") -> February | H11: =TEXT(E11, "dddd") -> Monday | I11: 0.71805556 | J11: =HOUR(I11) -> 17 | K11: =MINUTE(I11) -> 14 | L11: Laptop | M11: Computers | N11: 1 | O11: 1252.71 | P11: =VLOOKUP(L11,'Product-cost'!A:B,2,FALSE) -> 600 | Q11: Asia | R11: oliviapatel@tg.inc | S11: Packaging was damaged | T11: Negative | U11: =O11*N11 -> 1252.71 | V11: =P11*N11 -> 600 | W11: =VLOOKUP(Q11,Taxrate!A:B,2,FALSE) -> 0.1 | X11: =U11*W11 -> 125.271 | Y11: =VLOOKUP(L11,'Discount Rate'!A:B,2,FALSE) -> 0.05 | Z11: =Y11*U11 -> 62.6355 | AA11: =U11-X11-Z11 -> 1064.8035 | AB11: =AA11-V11 -> 464.8035
A12: ORD-00011 | B12: CUST-690 | C12: REP-29 | D12: Sophie Lee | E12: 45895 | F12: =YEAR(E12) -> 2025 | G12: =TEXT(E12,"mmmm") -> August | H12: =TEXT(E12, "dddd") -> Tuesday | I12: 0.46256944 | J12: =HOUR(I12) -> 11 | K12: =MINUTE(I12) -> 6 | L12: Headphones | M12: Audio | N12: 7 | O12: 174.68 | P12: =VLOOKUP(L12,'Product-cost'!A:B,2,FALSE) -> 50 | Q12: North America | R12: sophielee@tg.inc | S12: Good value for money | T12: Postive | U12: =O12*N12 -> 1222.76 | V12: =P12*N12 -> 350 | W12: =VLOOKUP(Q12,Taxrate!A:B,2,FALSE) -> 0.07 | X12: =U12*W12 -> 85.5932 | Y12: =VLOOKUP(L12,'Discount Rate'!A:B,2,FALSE) -> 0.03 | Z12: =Y12*U12 -> 36.6828 | AA12: =U12-X12-Z12 -> 1100.484 | AB12: =AA12-V12 -> 750.484
A13: ORD-00012 | B13: CUST-532 | C13: REP-15 | D13: Sophie Lee | E13: 45785 | F13: =YEAR(E13) -> 2025 | G13: =TEXT(E13,"mmmm") -> May | H13: =TEXT(E13, "dddd") -> Thursday | I13: 0.91601852 | J13: =HOUR(I13) -> 21 | K13: =MINUTE(I13) -> 59 | L13: Headphones | M13: Audio | N13: 14 | O13: 123.79 | P13: =VLOOKUP(L13,'Product-cost'!A:B,2,FALSE) -> 50 | Q13: Africa | R13: sophielee@tg.inc | S13: Very satisfied | T13: Postive | U13: =O13*N13 -> 1733.06 | V13: =P13*N13 -> 700 | W13: =VLOOKUP(Q13,Taxrate!A:B,2,FALSE) -> 0.12 | X13: =U13*W13 -> 207.9672 | Y13: =VLOOKUP(L13,'Discount Rate'!A:B,2,FALSE) -> 0.03 | Z13: =Y13*U13 -> 51.9918 | AA13: =U13-X13-Z13 -> 1473.101 | AB13: =AA13-V13 -> 773.101
A14: ORD-00013 | B14: CUST-510 | C14: REP-11 | D14: Emma Dubois | E14: 45703 | F14: =YEAR(E14) -> 2025 | G14: =TEXT(E14,"mmmm") -> February | H14: =TEXT(E14, "dddd") -> Saturday | I14: 0.59512731 | J14: =HOUR(I14) -> 14 | K14: =MINUTE(I14) -> 16 | L14: Headphones | M14: Audio | N14: 12 | O14: 194.66 | P14: =VLOOKUP(L14,'Product-cost'!A:B,2,FALSE) -> 50 | Q14: Africa | R14: emmadubois@tg.inc | S14: Packaging was damaged | T14: Negative | U14: =O14*N14 -> 2335.92 | V14: =P14*N14 -> 600 | W14: =VLOOKUP(Q14,Taxrate!A:B,2,FALSE) -> 0.12 | X14: =U14*W14 -> 280.3104 | Y14: =VLOOKUP(L14,'Discount Rate'!A:B,2,FALSE) -> 0.03 | Z14: =Y14*U14 -> 70.0776 | AA14: =U14-X14-Z14 -> 1985.532 | AB14: =AA14-V14 -> 1385.532
A15: ORD-00014 | B15: CUST-865 | C15: REP-21 | D15: Fatima Adebayo | E15: 45029 | F15: =YEAR(E15) -> 2023 | G15: =TEXT(E15,"mmmm") -> April | H15: =TEXT(E15, "dddd") -> Thursday | I15: 0.70756944 | J15: =HOUR(I15) -> 16 | K15: =MINUTE(I15) -> 58 | L15: Smartwatch | M15: Wearables | N15: 9 | O15: 500 | P15: =VLOOKUP(L15,'Product-cost'!A:B,2,FALSE) -> 150 | Q15: Europe | R15: fatimaadebayo@tg.inc | T15: Neutral | U15: =O15*N15 -> 4500 | V15: =P15*N15 -> 1350 | W15: =VLOOKUP(Q15,Taxrate!A:B,2,FALSE) -> 0.2 | X15: =U15*W15 -> 900 | Y15: =VLOOKUP(L15,'Discount Rate'!A:B,2,FALSE) -> 0.07 | Z15: =Y15*U15 -> 315 | AA15: =U15-X15-Z15 -> 3285 | AB15: =AA15-V15 -> 1935
A16: ORD-00015 | B16: CUST-708 | C16: REP-11 | D16: Emma Dubois | E16: 45094 | F16: =YEAR(E16) -> 2023 | G16: =TEXT(E16,"mmmm") -> June | H16: =TEXT(E16, "dddd") -> Saturday | I16: 0.77611111 | J16: =HOUR(I16) -> 18 | K16: =MINUTE(I16) -> 37 | L16: Smartwatch | M16: Wearables | N16: 5 | O16: 254.78 | P16: =VLOOKUP(L16,'Product-cost'!A:B,2,FALSE) -> 150 | Q16: Europe | R16: emmadubois@sales.techg.com | S16: Perfect fit | T16: Postive | U16: =O16*N16 -> 1273.9 | V16: =P16*N16 -> 750 | W16: =VLOOKUP(Q16,Taxrate!A:B,2,FALSE) -> 0.2 | X16: =U16*W16 -> 254.78 | Y16: =VLOOKUP(L16,'Discount Rate'!A:B,2,FALSE) -> 0.07 | Z16: =Y16*U16 -> 89.173 | AA16: =U16-X16-Z16 -> 929.947 | AB16: =AA16-V16 -> 179.947
A17: ORD-00016 | B17: CUST-569 | C17: REP-35 | D17: Carlos Rodriguez | E17: 45131 | F17: =YEAR(E17) -> 2023 | G17: =TEXT(E17,"mmmm") -> July | H17: =TEXT(E17, "dddd") -> Monday | I17: 0.67606481 | J17: =HOUR(I17) -> 16 | K17: =MINUTE(I17) -> 13 | L17: Tablet | M17: Tablets | N17: 6 | O17: 495.85 | P17: =VLOOKUP(L17,'Product-cost'!A:B,2,FALSE) -> 200 | Q17: Asia | R17: carlosrodriguez@tg.inc | T17: Neutral | U17: =O17*N17 -> 2975.1 | V17: =P17*N17 -> 1200 | W17: =VLOOKUP(Q17,Taxrate!A:B,2,FALSE) -> 0.1 | X17: =U17*W17 -> 297.51 | Y17: =VLOOKUP(L17,'Discount Rate'!A:B,2,FALSE) -> 0.08 | Z17: =Y17*U17 -> 238.008 | AA17: =U17-X17-Z17 -> 2439.582 | AB17: =AA17-V17 -> 1239.582
A18: ORD-00017 | B18: CUST-108 | C18: REP-33 | D18: Ahmed Khan | E18: 46285 | F18: =YEAR(E18) -> 2026 | G18: =TEXT(E18,"mmmm") -> September | H18: =TEXT(E18, "dddd") -> Sunday | I18: 0.4278588 | J18: =HOUR(I18) -> 10 | K18: =MINUTE(I18) -> 16 | L18: Laptop | M18: Computers | N18: 3 | O18: 1102.41 | P18: =VLOOKUP(L18,'Product-cost'!A:B,2,FALSE) -> 600 | Q18: Asia | R18: ahmedkhan@tg.inc | S18: Battery life amazing | T18: Postive | U18: =O18*N18 -> 3307.23 | V18: =P18*N18 -> 1800 | W18: =VLOOKUP(Q18,Taxrate!A:B,2,FALSE) -> 0.1 | X18: =U18*W18 -> 330.723 | Y18: =VLOOKUP(L18,'Discount Rate'!A:B,2,FALSE) -> 0.05 | Z18: =Y18*U18 -> 165.3615 | AA18: =U18-X18-Z18 -> 2811.1455 | AB18: =AA18-V18 -> 1011.1455
A19: ORD-00018 | B19: CUST-749 | C19: REP-24 | D19: Liam Chen | E19: 44930 | F19: =YEAR(E19) -> 2023 | G19: =TEXT(E19,"mmmm") -> January | H19: =TEXT(E19, "dddd") -> Wednesday | I19: 0.57578704 | J19: =HOUR(I19) -> 13 | K19: =MINUTE(I19) -> 49 | L19: Tablet | M19: Tablets | N19: 8 | O19: 405.54 | P19: =VLOOKUP(L19,'Product-cost'!A:B,2,FALSE) -> 200 | Q19: North America | R19: liamchen@sales.techg.com | S19: A bit expensive but worth it | T19: Neutral | U19: =O19*N19 -> 3244.32 | V19: =P19*N19 -> 1600 | W19: =VLOOKUP(Q19,Taxrate!A:B,2,FALSE) -> 0.07 | X19: =U19*W19 -> 227.1024 | Y19: =VLOOKUP(L19,'Discount Rate'!A:B,2,FALSE) -> 0.08 | Z19: =Y19*U19 -> 259.5456 | AA19: =U19-X19-Z19 -> 2757.672 | AB19: =AA19-V19 -> 1157.672
A20: ORD-00019 | B20: CUST-251 | C20: REP-24 | D20: Liam Chen | E20: 45012 | F20: =YEAR(E20) -> 2023 | G20: =TEXT(E20,"mmmm") -> March | H20: =TEXT(E20, "dddd") -> Monday | I20: 0.58193287 | J20: =HOUR(I20) -> 13 | K20: =MINUTE(I20) -> 57 | L20: Laptop | M20: Computers | N20: 4 | O20: 1133.47 | P20: =VLOOKUP(L20,'Product-cost'!A:B,2,FALSE) -> 600 | Q20: Asia | R20: liamchen@techgadgetsco.com | S20: A bit expensive but worth it | T20: Neutral | U20: =O20*N20 -> 4533.88 | V20: =P20*N20 -> 2400 | W20: =VLOOKUP(Q20,Taxrate!A:B,2,FALSE) -> 0.1 | X20: =U20*W20 -> 453.388 | Y20: =VLOOKUP(L20,'Discount Rate'!A:B,2,FALSE) -> 0.05 | Z20: =Y20*U20 -> 226.694 | AA20: =U20-X20-Z20 -> 3853.798 | AB20: =AA20-V20 -> 1453.798
A21: ORD-00020 | B21: CUST-919 | C21: REP-15 | D21: Sophie Lee | E21: 44977 | F21: =YEAR(E21) -> 2023 | G21: =TEXT(E21,"mmmm") -> February | H21: =TEXT(E21, "dddd") -> Monday | I21: 0.83288194 | J21: =HOUR(I21) -> 19 | K21: =MINUTE(I21) -> 59 | L21: Headphones | M21: Audio | N21: 14 | O21: 138.61 | P21: =VLOOKUP(L21,'Product-cost'!A:B,2,FALSE) -> 50 | Q21: Europe | R21: sophielee@tg.inc | S21: Battery life amazing | T21: Postive | U21: =O21*N21 -> 1940.54 | V21: =P21*N21 -> 700 | W21: =VLOOKUP(Q21,Taxrate!A:B,2,FALSE) -> 0.2 | X21: =U21*W21 -> 388.108 | Y21: =VLOOKUP(L21,'Discount Rate'!A:B,2,FALSE) -> 0.03 | Z21: =Y21*U21 -> 58.2162 | AA21: =U21-X21-Z21 -> 1494.2158 | AB21: =AA21-V21 -> 794.2158
A22: ORD-00021 | B22: CUST-412 | C22: REP-17 | D22: Maria Garcia | E22: 44975 | F22: =YEAR(E22) -> 2023 | G22: =TEXT(E22,"mmmm") -> February | H22: =TEXT(E22, "dddd") -> Saturday | I22: 0.59811343 | J22: =HOUR(I22) -> 14 | K22: =MINUTE(I22) -> 21 | L22: Laptop | M22: Computers | N22: 5 | O22: 1054.7 | P22: =VLOOKUP(L22,'Product-cost'!A:B,2,FALSE) -> 600 | Q22: Africa | R22: mariagarcia@techgadgetsco.com | T22: Neutral | U22: =O22*N22 -> 5273.5 | V22: =P22*N22 -> 3000 | W22: =VLOOKUP(Q22,Taxrate!A:B,2,FALSE) -> 0.12 | X22: =U22*W22 -> 632.82 | Y22: =VLOOKUP(L22,'Discount Rate'!A:B,2,FALSE) -> 0.05 | Z22: =Y22*U22 -> 263.675 | AA22: =U22-X22-Z22 -> 4377.005 | AB22: =AA22-V22 -> 1377.005
A23: ORD-00022 | B23: CUST-211 | C23: REP-35 | D23: Carlos Rodriguez | E23: 45516 | F23: =YEAR(E23) -> 2024 | G23: =TEXT(E23,"mmmm") -> August | H23: =TEXT(E23, "dddd") -> Monday | I23: 0.61009259 | J23: =HOUR(I23) -> 14 | K23: =MINUTE(I23) -> 38 | L23: Laptop | M23: Computers | N23: 10 | O23: 822.19 | P23: =VLOOKUP(L23,'Product-cost'!A:B,2,FALSE) -> 600 | Q23: South America | R23: carlosrodriguez@techgadgetsco.com | S23: Packaging was damaged | T23: Negative | U23: =O23*N23 -> 8221.9 | V23: =P23*N23 -> 6000 | W23: =VLOOKUP(Q23,Taxrate!A:B,2,FALSE) -> 0.15 | X23: =U23*W23 -> 1233.285 | Y23: =VLOOKUP(L23,'Discount Rate'!A:B,2,FALSE) -> 0.05 | Z23: =Y23*U23 -> 411.095 | AA23: =U23-X23-Z23 -> 6577.52 | AB23: =AA23-V23 -> 577.52
A24: ORD-00023 | B24: CUST-438 | C24: REP-35 | D24: Carlos Rodriguez | E24: 46285 | F24: =YEAR(E24) -> 2026 | G24: =TEXT(E24,"mmmm") -> September | H24: =TEXT(E24, "dddd") -> Sunday | I24: 0.83146991 | J24: =HOUR(I24) -> 19 | K24: =MINUTE(I24) -> 57 | L24: Smartwatch | M24: Wearables | N24: 7 | O24: 252.69 | P24: =VLOOKUP(L24,'Product-cost'!A:B,2,FALSE) -> 150 | Q24: Africa | R24: carlosrodriguez@techgadgetsco.com | S24: Fantastic customer service | T24: Postive | U24: =O24*N24 -> 1768.83 | V24: =P24*N24 -> 1050 | W24: =VLOOKUP(Q24,Taxrate!A:B,2,FALSE) -> 0.12 | X24: =U24*W24 -> 212.2596 | Y24: =VLOOKUP(L24,'Discount Rate'!A:B,2,FALSE) -> 0.07 | Z24: =Y24*U24 -> 123.8181 | AA24: =U24-X24-Z24 -> 1432.7523 | AB24: =AA24-V24 -> 382.7523
A25: ORD-00024 | B25: CUST-100 | C25: REP-20 | D25: Sophie Lee | E25: 45446 | F25: =YEAR(E25) -> 2024 | G25: =TEXT(E25,"mmmm") -> June | H25: =TEXT(E25, "dddd") -> Monday | I25: 0.85946759 | J25: =HOUR(I25) -> 20 | K25: =MINUTE(I25) -> 37 | L25: Tablet | M25: Tablets | N25: 8 | O25: 422.23 | P25: =VLOOKUP(L25,'Product-cost'!A:B,2,FALSE) -> 200 | Q25: Europe | R25: sophielee@sales.techg.com | T25: Neutral | U25: =O25*N25 -> 3377.84 | V25: =P25*N25 -> 1600 | W25: =VLOOKUP(Q25,Taxrate!A:B,2,FALSE) -> 0.2 | X25: =U25*W25 -> 675.568 | Y25: =VLOOKUP(L25,'Discount Rate'!A:B,2,FALSE) -> 0.08 | Z25: =Y25*U25 -> 270.2272 | AA25: =U25-X25-Z25 -> 2432.0448 | AB25: =AA25-V25 -> 832.0448
A26: ORD-00025 | B26: CUST-417 | C26: REP-17 | D26: Maria Garcia | E26: 45228 | F26: =YEAR(E26) -> 2023 | G26: =TEXT(E26,"mmmm") -> October | H26: =TEXT(E26, "dddd") -> Sunday | I26: 0.34409722 | J26: =HOUR(I26) -> 8 | K26: =MINUTE(I26) -> 15 | L26: Smartwatch | M26: Wearables | N26: 2 | O26: 273.48 | P26: =VLOOKUP(L26,'Product-cost'!A:B,2,FALSE) -> 150 | Q26: Africa | R26: mariagarcia@techgadgetsco.com | T26: Neutral | U26: =O26*N26 -> 546.96 | V26: =P26*N26 -> 300 | W26: =VLOOKUP(Q26,Taxrate!A:B,2,FALSE) -> 0.12 | X26: =U26*W26 -> 65.6352 | Y26: =VLOOKUP(L26,'Discount Rate'!A:B,2,FALSE) -> 0.07 | Z26: =Y26*U26 -> 38.2872 | AA26: =U26-X26-Z26 -> 443.0376 | AB26: =AA26-V26 -> 143.0376
A27: ORD-00026 | B27: CUST-981 | C27: REP-13 | D27: Ahmed Khan | E27: 45375 | F27: =YEAR(E27) -> 2024 | G27: =TEXT(E27,"mmmm") -> March | H27: =TEXT(E27, "dddd") -> Sunday | I27: 0.86427083 | J27: =HOUR(I27) -> 20 | K27: =MINUTE(I27) -> 44 | L27: Headphones | M27: Audio | N27: 7 | O27: 183.63 | P27: =VLOOKUP(L27,'Product-cost'!A:B,2,FALSE) -> 50 | Q27: South America | R27: ahmedkhan@sales.techg.com | S27: Great product | T27: Postive | U27: =O27*N27 -> 1285.41 | V27: =P27*N27 -> 350 | W27: =VLOOKUP(Q27,Taxrate!A:B,2,FALSE) -> 0.15 | X27: =U27*W27 -> 192.8115 | Y27: =VLOOKUP(L27,'Discount Rate'!A:B,2,FALSE) -> 0.03 | Z27: =Y27*U27 -> 38.5623 | AA27: =U27-X27-Z27 -> 1054.0362 | AB27: =AA27-V27 -> 704.0362
A28: ORD-00027 | B28: CUST-836 | C28: REP-32 | D28: Maria Garcia | E28: 46049 | F28: =YEAR(E28) -> 2026 | G28: =TEXT(E28,"mmmm") -> January | H28: =TEXT(E28, "dddd") -> Tuesday | I28: 0.44994213 | J28: =HOUR(I28) -> 10 | K28: =MINUTE(I28) -> 47 | L28: Headphones | M28: Audio | N28: 13 | O28: 167.82 | P28: =VLOOKUP(L28,'Product-cost'!A:B,2,FALSE) -> 50 | Q28: Africa | R28: mariagarcia@techgadgetsco.com | T28: Neutral | U28: =O28*N28 -> 2181.66 | V28: =P28*N28 -> 650 | W28: =VLOOKUP(Q28,Taxrate!A:B,2,FALSE) -> 0.12 | X28: =U28*W28 -> 261.7992 | Y28: =VLOOKUP(L28,'Discount Rate'!A:B,2,FALSE) -> 0.03 | Z28: =Y28*U28 -> 65.4498 | AA28: =U28-X28-Z28 -> 1854.411 | AB28: =AA28-V28 -> 1204.411
A29: ORD-00028 | B29: CUST-182 | C29: REP-14 | D29: Maria Garcia | E29: 45400 | F29: =YEAR(E29) -> 2024 | G29: =TEXT(E29,"mmmm") -> April | H29: =TEXT(E29, "dddd") -> Thursday | I29: 0.7984375 | J29: =HOUR(I29) -> 19 | K29: =MINUTE(I29) -> 9 | L29: Smartphone | M29: Mobile Devices | N29: 7 | O29: 642.78 | P29: =VLOOKUP(L29,'Product-cost'!A:B,2,FALSE) -> 300 | Q29: South America | R29: mariagarcia@techgadgetsco.com | S29: Excellent quality | T29: Postive | U29: =O29*N29 -> 4499.46 | V29: =P29*N29 -> 2100 | W29: =VLOOKUP(Q29,Taxrate!A:B,2,FALSE) -> 0.15 | X29: =U29*W29 -> 674.919 | Y29: =VLOOKUP(L29,'Discount Rate'!A:B,2,FALSE) -> 0.1 | Z29: =Y29*U29 -> 449.946 | AA29: =U29-X29-Z29 -> 3374.595 | AB29: =AA29-V29 -> 1274.595
A30: ORD-00029 | B30: CUST-106 | C30: REP-22 | D30: Fatima Adebayo | E30: 45903 | F30: =YEAR(E30) -> 2025 | G30: =TEXT(E30,"mmmm") -> September | H30: =TEXT(E30, "dddd") -> Wednesday | I30: 0.69984954 | J30: =HOUR(I30) -> 16 | K30: =MINUTE(I30) -> 47 | L30: Smartwatch | M30: Wearables | N30: 15 | O30: 200.14 | P30: =VLOOKUP(L30,'Product-cost'!A:B,2,FALSE) -> 150 | Q30: South America | R30: fatimaadebayo@sales.techg.com | S30: Highly recommend | T30: Postive | U30: =O30*N30 -> 3002.1 | V30: =P30*N30 -> 2250 | W30: =VLOOKUP(Q30,Taxrate!A:B,2,FALSE) -> 0.15 | X30: =U30*W30 -> 450.315 | Y30: =VLOOKUP(L30,'Discount Rate'!A:B,2,FALSE) -> 0.07 | Z30: =Y30*U30 -> 210.147 | AA30: =U30-X30-Z30 -> 2341.638 | AB30: =AA30-V30 -> 91.638
A31: ORD-00030 | B31: CUST-737 | C31: REP-33 | D31: Ahmed Khan | E31: 45733 | F31: =YEAR(E31) -> 2025 | G31: =TEXT(E31,"mmmm") -> March | H31: =TEXT(E31, "dddd") -> Monday | I31: 0.40378472 | J31: =HOUR(I31) -> 9 | K31: =MINUTE(I31) -> 41 | L31: Smartphone | M31: Mobile Devices | N31: 3 | O31: 500 | P31: =VLOOKUP(L31,'Product-cost'!A:B,2,FALSE) -> 300 | Q31: South America | R31: ahmedkhan@sales.techg.com | S31: Highly recommend | T31: Postive | U31: =O31*N31 -> 1500 | V31: =P31*N31 -> 900 | W31: =VLOOKUP(Q31,Taxrate!A:B,2,FALSE) -> 0.15 | X31: =U31*W31 -> 225 | Y31: =VLOOKUP(L31,'Discount Rate'!A:B,2,FALSE) -> 0.1 | Z31: =Y31*U31 -> 150 | AA31: =U31-X31-Z31 -> 1125 | AB31: =AA31-V31 -> 225
A32: ORD-00031 | B32: CUST-954 | C32: REP-12 | D32: Olivia Patel | E32: 45171 | F32: =YEAR(E32) -> 2023 | G32: =TEXT(E32,"mmmm") -> September | H32: =TEXT(E32, "dddd") -> Saturday | I32: 0.55186343 | J32: =HOUR(I32) -> 13 | K32: =MINUTE(I32) -> 14 | L32: Laptop | M32: Computers | N32: 11 | O32: 500 | P32: =VLOOKUP(L32,'Product-cost'!A:B,2,FALSE) -> 600 | Q32: North America | R32: oliviapatel@tg.inc | S32: A bit expensive but worth it | T32: Neutral | U32: =O32*N32 -> 5500 | V32: =P32*N32 -> 6600 | W32: =VLOOKUP(Q32,Taxrate!A:B,2,FALSE) -> 0.07 | X32: =U32*W32 -> 385 | Y32: =VLOOKUP(L32,'Discount Rate'!A:B,2,FALSE) -> 0.05 | Z32: =Y32*U32 -> 275 | AA32: =U32-X32-Z32 -> 4840 | AB32: =AA32-V32 -> -1760
A33: ORD-00032 | B33: CUST-323 | C33: REP-28 | D33: Maria Garcia | E33: 45682 | F33: =YEAR(E33) -> 2025 | G33: =TEXT(E33,"mmmm") -> January | H33: =TEXT(E33, "dddd") -> Saturday | I33: 0.7352662 | J33: =HOUR(I33) -> 17 | K33: =MINUTE(I33) -> 38 | L33: Laptop | M33: Computers | N33: 3 | O33: 854.05 | P33: =VLOOKUP(L33,'Product-cost'!A:B,2,FALSE) -> 600 | Q33: North America | R33: mariagarcia@tg.inc | S33: Highly recommend | T33: Postive | U33: =O33*N33 -> 2562.15 | V33: =P33*N33 -> 1800 | W33: =VLOOKUP(Q33,Taxrate!A:B,2,FALSE) -> 0.07 | X33: =U33*W33 -> 179.3505 | Y33: =VLOOKUP(L33,'Discount Rate'!A:B,2,FALSE) -> 0.05 | Z33: =Y33*U33 -> 128.1075 | AA33: =U33-X33-Z33 -> 2254.692 | AB33: =AA33-V33 -> 454.692
A34: ORD-00033 | B34: CUST-807 | C34: REP-17 | D34: Maria Garcia | E34: 46354 | F34: =YEAR(E34) -> 2026 | G34: =TEXT(E34,"mmmm") -> November | H34: =TEXT(E34, "dddd") -> Saturday | I34: 0.90530093 | J34: =HOUR(I34) -> 21 | K34: =MINUTE(I34) -> 43 | L34: Laptop | M34: Computers | N34: 10 | O34: 973.6 | P34: =VLOOKUP(L34,'Product-cost'!A:B,2,FALSE) -> 600 | Q34: South America | R34: mariagarcia@techgadgetsco.com | S34: Excellent quality | T34: Postive | U34: =O34*N34 -> 9736 | V34: =P34*N34 -> 6000 | W34: =VLOOKUP(Q34,Taxrate!A:B,2,FALSE) -> 0.15 | X34: =U34*W34 -> 1460.4 | Y34: =VLOOKUP(L34,'Discount Rate'!A:B,2,FALSE) -> 0.05 | Z34: =Y34*U34 -> 486.8 | AA34: =U34-X34-Z34 -> 7788.8 | AB34: =AA34-V34 -> 1788.8
A35: ORD-00034 | B35: CUST-470 | C35: REP-28 | D35: Maria Garcia | E35: 45936 | F35: =YEAR(E35) -> 2025 | G35: =TEXT(E35,"mmmm") -> October | H35: =TEXT(E35, "dddd") -> Monday | I35: 0.81505787 | J35: =HOUR(I35) -> 19 | K35: =MINUTE(I35) -> 33 | L35: Tablet | M35: Tablets | N35: 15 | O35: 416.7 | P35: =VLOOKUP(L35,'Product-cost'!A:B,2,FALSE) -> 200 | Q35: South America | R35: mariagarcia@sales.techg.com | S35: Very satisfied | T35: Postive | U35: =O35*N35 -> 6250.5 | V35: =P35*N35 -> 3000 | W35: =VLOOKUP(Q35,Taxrate!A:B,2,FALSE) -> 0.15 | X35: =U35*W35 -> 937.575 | Y35: =VLOOKUP(L35,'Discount Rate'!A:B,2,FALSE) -> 0.08 | Z35: =Y35*U35 -> 500.04 | AA35: =U35-X35-Z35 -> 4812.885 | AB35: =AA35-V35 -> 1812.885
A36: ORD-00035 | B36: CUST-349 | C36: REP-28 | D36: Maria Garcia | E36: 45615 | F36: =YEAR(E36) -> 2024 | G36: =TEXT(E36,"mmmm") -> November | H36: =TEXT(E36, "dddd") -> Tuesday | I36: 0.66273148 | J36: =HOUR(I36) -> 15 | K36: =MINUTE(I36) -> 54 | L36: Smartphone | M36: Mobile Devices | N36: 6 | O36: 582.1 | P36: =VLOOKUP(L36,'Product-cost'!A:B,2,FALSE) -> 300 | Q36: Africa | R36: mariagarcia@tg.inc | T36: Neutral | U36: =O36*N36 -> 3492.6 | V36: =P36*N36 -> 1800 | W36: =VLOOKUP(Q36,Taxrate!A:B,2,FALSE) -> 0.12 | X36: =U36*W36 -> 419.112 | Y36: =VLOOKUP(L36,'Discount Rate'!A:B,2,FALSE) -> 0.1 | Z36: =Y36*U36 -> 349.26 | AA36: =U36-X36-Z36 -> 2724.228 | AB36: =AA36-V36 -> 924.228
A37: ORD-00036 | B37: CUST-876 | C37: REP-17 | D37: Maria Garcia | E37: 46249 | F37: =YEAR(E37) -> 2026 | G37: =TEXT(E37,"mmmm") -> August | H37: =TEXT(E37, "dddd") -> Saturday | I37: 0.6597338 | J37: =HOUR(I37) -> 15 | K37: =MINUTE(I37) -> 50 | L37: Laptop | M37: Computers | N37: 7 | O37: 953.1 | P37: =VLOOKUP(L37,'Product-cost'!A:B,2,FALSE) -> 600 | Q37: Africa | R37: mariagarcia@tg.inc | S37: Great product | T37: Postive | U37: =O37*N37 -> 6671.7 | V37: =P37*N37 -> 4200 | W37: =VLOOKUP(Q37,Taxrate!A:B,2,FALSE) -> 0.12 | X37: =U37*W37 -> 800.604 | Y37: =VLOOKUP(L37,'Discount Rate'!A:B,2,FALSE) -> 0.05 | Z37: =Y37*U37 -> 333.585 | AA37: =U37-X37-Z37 -> 5537.511 | AB37: =AA37-V37 -> 1337.511
A38: ORD-00037 | B38: CUST-336 | C38: REP-13 | D38: Ahmed Khan | E38: 45514 | F38: =YEAR(E38) -> 2024 | G38: =TEXT(E38,"mmmm") -> August | H38: =TEXT(E38, "dddd") -> Saturday | I38: 0.81583333 | J38: =HOUR(I38) -> 19 | K38: =MINUTE(I38) -> 34 | L38: Smartphone | M38: Mobile Devices | N38: 12 | O38: 697.38 | P38: =VLOOKUP(L38,'Product-cost'!A:B,2,FALSE) -> 300 | Q38: Africa | R38: ahmedkhan@tg.inc | T38: Neutral | U38: =O38*N38 -> 8368.56 | V38: =P38*N38 -> 3600 | W38: =VLOOKUP(Q38,Taxrate!A:B,2,FALSE) -> 0.12 | X38: =U38*W38 -> 1004.2272 | Y38: =VLOOKUP(L38,'Discount Rate'!A:B,2,FALSE) -> 0.1 | Z38: =Y38*U38 -> 836.856 | AA38: =U38-X38-Z38 -> 6527.4768 | AB38: =AA38-V38 -> 2927.4768
A39: ORD-00038 | B39: CUST-646 | C39: REP-14 | D39: Maria Garcia | E39: 45020 | F39: =YEAR(E39) -> 2023 | G39: =TEXT(E39,"mmmm") -> April | H39: =TEXT(E39, "dddd") -> Tuesday | I39: 0.67967593 | J39: =HOUR(I39) -> 16 | K39: =MINUTE(I39) -> 18 | L39: Smartphone | M39: Mobile Devices | N39: 13 | O39: 741.82 | P39: =VLOOKUP(L39,'Product-cost'!A:B,2,FALSE) -> 300 | Q39: Africa | R39: mariagarcia@sales.techg.com | S39: Quick shipping | T39: Postive | U39: =O39*N39 -> 9643.66 | V39: =P39*N39 -> 3900 | W39: =VLOOKUP(Q39,Taxrate!A:B,2,FALSE) -> 0.12 | X39: =U39*W39 -> 1157.2392 | Y39: =VLOOKUP(L39,'Discount Rate'!A:B,2,FALSE) -> 0.1 | Z39: =Y39*U39 -> 964.366 | AA39: =U39-X39-Z39 -> 7522.0548 | AB39: =AA39-V39 -> 3622.0548
A40: ORD-00039 | B40: CUST-166 | C40: REP-23 | D40: Noah Kim | E40: 44932 | F40: =YEAR(E40) -> 2023 | G40: =TEXT(E40,"mmmm") -> January | H40: =TEXT(E40, "dddd") -> Friday | I40: 0.42350694 | J40: =HOUR(I40) -> 10 | K40: =MINUTE(I40) -> 9 | L40: Smartwatch | M40: Wearables | N40: 2 | O40: 189.03 | P40: =VLOOKUP(L40,'Product-cost'!A:B,2,FALSE) -> 150 | Q40: South America | R40: noahkim@sales.techg.com | S40: Love the design | T40: Postive | U40: =O40*N40 -> 378.06 | V40: =P40*N40 -> 300 | W40: =VLOOKUP(Q40,Taxrate!A:B,2,FALSE) -> 0.15 | X40: =U40*W40 -> 56.709 | Y40: =VLOOKUP(L40,'Discount Rate'!A:B,2,FALSE) -> 0.07 | Z40: =Y40*U40 -> 26.4642 | AA40: =U40-X40-Z40 -> 294.8868 | AB40: =AA40-V40 -> -5.1132
A41: ORD-00040 | B41: CUST-702 | C41: REP-24 | D41: Liam Chen | E41: 46298 | F41: =YEAR(E41) -> 2026 | G41: =TEXT(E41,"mmmm") -> October | H41: =TEXT(E41, "dddd") -> Saturday | I41: 0.74104167 | J41: =HOUR(I41) -> 17 | K41: =MINUTE(I41) -> 47 | L41: Smartphone | M41: Mobile Devices | N41: 5 | O41: 527.12 | P41: =VLOOKUP(L41,'Product-cost'!A:B,2,FALSE) -> 300 | Q41: Europe | R41: liamchen@sales.techg.com | S41: Battery life amazing | T41: Postive | U41: =O41*N41 -> 2635.6 | V41: =P41*N41 -> 1500 | W41: =VLOOKUP(Q41,Taxrate!A:B,2,FALSE) -> 0.2 | X41: =U41*W41 -> 527.12 | Y41: =VLOOKUP(L41,'Discount Rate'!A:B,2,FALSE) -> 0.1 | Z41: =Y41*U41 -> 263.56 | AA41: =U41-X41-Z41 -> 1844.92 | AB41: =AA41-V41 -> 344.92
A42: ORD-00041 | B42: CUST-819 | C42: REP-28 | D42: Maria Garcia | E42: 46245 | F42: =YEAR(E42) -> 2026 | G42: =TEXT(E42,"mmmm") -> August | H42: =TEXT(E42, "dddd") -> Tuesday | I42: 0.53530093 | J42: =HOUR(I42) -> 12 | K42: =MINUTE(I42) -> 50 | L42: Smartwatch | M42: Wearables | N42: 15 | O42: 188.63 | P42: =VLOOKUP(L42,'Product-cost'!A:B,2,FALSE) -> 150 | Q42: Europe | R42: mariagarcia@sales.techg.com | T42: Neutral | U42: =O42*N42 -> 2829.45 | V42: =P42*N42 -> 2250 | W42: =VLOOKUP(Q42,Taxrate!A:B,2,FALSE) -> 0.2 | X42: =U42*W42 -> 565.89 | Y42: =VLOOKUP(L42,'Discount Rate'!A:B,2,FALSE) -> 0.07 | Z42: =Y42*U42 -> 198.0615 | AA42: =U42-X42-Z42 -> 2065.4985 | AB42: =AA42-V42 -> -184.5015
A43: ORD-00042 | B43: CUST-944 | C43: REP-34 | D43: Fatima Adebayo | E43: 45826 | F43: =YEAR(E43) -> 2025 | G43: =TEXT(E43,"mmmm") -> June | H43: =TEXT(E43, "dddd") -> Wednesday | I43: 0.65577546 | J43: =HOUR(I43) -> 15 | K43: =MINUTE(I43) -> 44 | L43: Headphones | M43: Audio | N43: 9 | O43: 152.83 | P43: =VLOOKUP(L43,'Product-cost'!A:B,2,FALSE) -> 50 | Q43: Africa | R43: fatimaadebayo@sales.techg.com | T43: Neutral | U43: =O43*N43 -> 1375.47 | V43: =P43*N43 -> 450 | W43: =VLOOKUP(Q43,Taxrate!A:B,2,FALSE) -> 0.12 | X43: =U43*W43 -> 165.0564 | Y43: =VLOOKUP(L43,'Discount Rate'!A:B,2,FALSE) -> 0.03 | Z43: =Y43*U43 -> 41.2641 | AA43: =U43-X43-Z43 -> 1169.1495 | AB43: =AA43-V43 -> 719.1495
A44: ORD-00043 | B44: CUST-981 | C44: REP-34 | D44: Fatima Adebayo | E44: 46244 | F44: =YEAR(E44) -> 2026 | G44: =TEXT(E44,"mmmm") -> August | H44: =TEXT(E44, "dddd") -> Monday | I44: 0.71027778 | J44: =HOUR(I44) -> 17 | K44: =MINUTE(I44) -> 2 | L44: Smartphone | M44: Mobile Devices | N44: 11 | O44: 563.45 | P44: =VLOOKUP(L44,'Product-cost'!A:B,2,FALSE) -> 300 | Q44: Africa | R44: fatimaadebayo@tg.inc | S44: Battery life amazing | T44: Postive | U44: =O44*N44 -> 6197.95 | V44: =P44*N44 -> 3300 | W44: =VLOOKUP(Q44,Taxrate!A:B,2,FALSE) -> 0.12 | X44: =U44*W44 -> 743.754 | Y44: =VLOOKUP(L44,'Discount Rate'!A:B,2,FALSE) -> 0.1 | Z44: =Y44*U44 -> 619.795 | AA44: =U44-X44-Z44 -> 4834.401 | AB44: =AA44-V44 -> 1534.401
A45: ORD-00044 | B45: CUST-978 | C45: REP-15 | D45: Sophie Lee | E45: 45770 | F45: =YEAR(E45) -> 2025 | G45: =TEXT(E45,"mmmm") -> April | H45: =TEXT(E45, "dddd") -> Wednesday | I45: 0.52945602 | J45: =HOUR(I45) -> 12 | K45: =MINUTE(I45) -> 42 | L45: Smartwatch | M45: Wearables | N45: 7 | O45: 500 | P45: =VLOOKUP(L45,'Product-cost'!A:B,2,FALSE) -> 150 | Q45: Asia | R45: sophielee@tg.inc | S45: Love the design | T45: Postive | U45: =O45*N45 -> 3500 | V45: =P45*N45 -> 1050 | W45: =VLOOKUP(Q45,Taxrate!A:B,2,FALSE) -> 0.1 | X45: =U45*W45 -> 350 | Y45: =VLOOKUP(L45,'Discount Rate'!A:B,2,FALSE) -> 0.07 | Z45: =Y45*U45 -> 245 | AA45: =U45-X45-Z45 -> 2905 | AB45: =AA45-V45 -> 1855
A46: ORD-00045 | B46: CUST-573 | C46: REP-24 | D46: Liam Chen | E46: 45311 | F46: =YEAR(E46) -> 2024 | G46: =TEXT(E46,"mmmm") -> January | H46: =TEXT(E46, "dddd") -> Saturday | I46: 0.74202546 | J46: =HOUR(I46) -> 17 | K46: =MINUTE(I46) -> 48 | L46: Headphones | M46: Audio | N46: 4 | O46: 129.83 | P46: =VLOOKUP(L46,'Product-cost'!A:B,2,FALSE) -> 50 | Q46: Asia | R46: liamchen@techgadgetsco.com | S46: Very satisfied | T46: Postive | U46: =O46*N46 -> 519.32 | V46: =P46*N46 -> 200 | W46: =VLOOKUP(Q46,Taxrate!A:B,2,FALSE) -> 0.1 | X46: =U46*W46 -> 51.932 | Y46: =VLOOKUP(L46,'Discount Rate'!A:B,2,FALSE) -> 0.03 | Z46: =Y46*U46 -> 15.5796 | AA46: =U46-X46-Z46 -> 451.8084 | AB46: =AA46-V46 -> 251.8084
A47: ORD-00046 | B47: CUST-517 | C47: REP-12 | D47: Olivia Patel | E47: 45159 | F47: =YEAR(E47) -> 2023 | G47: =TEXT(E47,"mmmm") -> August | H47: =TEXT(E47, "dddd") -> Monday | I47: 0.40408565 | J47: =HOUR(I47) -> 9 | K47: =MINUTE(I47) -> 41 | L47: Smartphone | M47: Mobile Devices | N47: 12 | O47: 691.62 | P47: =VLOOKUP(L47,'Product-cost'!A:B,2,FALSE) -> 300 | Q47: South America | R47: oliviapatel@techgadgetsco.com | S47: A bit expensive but worth it | T47: Neutral | U47: =O47*N47 -> 8299.44 | V47: =P47*N47 -> 3600 | W47: =VLOOKUP(Q47,Taxrate!A:B,2,FALSE) -> 0.15 | X47: =U47*W47 -> 1244.916 | Y47: =VLOOKUP(L47,'Discount Rate'!A:B,2,FALSE) -> 0.1 | Z47: =Y47*U47 -> 829.944 | AA47: =U47-X47-Z47 -> 6224.58 | AB47: =AA47-V47 -> 2624.58
A48: ORD-00047 | B48: CUST-239 | C48: REP-12 | D48: Olivia Patel | E48: 45776 | F48: =YEAR(E48) -> 2025 | G48: =TEXT(E48,"mmmm") -> April | H48: =TEXT(E48, "dddd") -> Tuesday | I48: 0.85575231 | J48: =HOUR(I48) -> 20 | K48: =MINUTE(I48) -> 32 | L48: Laptop | M48: Computers | N48: 5 | O48: 1089.96 | P48: =VLOOKUP(L48,'Product-cost'!A:B,2,FALSE) -> 600 | Q48: South America | R48: oliviapatel@tg.inc | S48: Great product | T48: Postive | U48: =O48*N48 -> 5449.8 | V48: =P48*N48 -> 3000 | W48: =VLOOKUP(Q48,Taxrate!A:B,2,FALSE) -> 0.15 | X48: =U48*W48 -> 817.47 | Y48: =VLOOKUP(L48,'Discount Rate'!A:B,2,FALSE) -> 0.05 | Z48: =Y48*U48 -> 272.49 | AA48: =U48-X48-Z48 -> 4359.84 | AB48: =AA48-V48 -> 1359.84
A49: ORD-00048 | B49: CUST-429 | C49: REP-16 | D49: Sophie Lee | E49: 46098 | F49: =YEAR(E49) -> 2026 | G49: =TEXT(E49,"mmmm") -> March | H49: =TEXT(E49, "dddd") -> Tuesday | I49: 0.49640046 | J49: =HOUR(I49) -> 11 | K49: =MINUTE(I49) -> 54 | L49: Headphones | M49: Audio | N49: 7 | O49: 172.89 | P49: =VLOOKUP(L49,'Product-cost'!A:B,2,FALSE) -> 50 | Q49: South America | R49: sophielee@sales.techg.com | S49: A bit expensive but worth it | T49: Neutral | U49: =O49*N49 -> 1210.23 | V49: =P49*N49 -> 350 | W49: =VLOOKUP(Q49,Taxrate!A:B,2,FALSE) -> 0.15 | X49: =U49*W49 -> 181.5345 | Y49: =VLOOKUP(L49,'Discount Rate'!A:B,2,FALSE) -> 0.03 | Z49: =Y49*U49 -> 36.3069 | AA49: =U49-X49-Z49 -> 992.3886 | AB49: =AA49-V49 -> 642.3886
A50: ORD-00049 | B50: CUST-704 | C50: REP-21 | D50: Fatima Adebayo | E50: 45828 | F50: =YEAR(E50) -> 2025 | G50: =TEXT(E50,"mmmm") -> June | H50: =TEXT(E50, "dddd") -> Friday | I50: 0.70728009 | J50: =HOUR(I50) -> 16 | K50: =MINUTE(I50) -> 58 | L50: Laptop | M50: Computers | N50: 7 | O50: 1284.98 | P50: =VLOOKUP(L50,'Product-cost'!A:B,2,FALSE) -> 600 | Q50: North America | R50: fatimaadebayo@tg.inc | S50: Highly recommend | T50: Postive | U50: =O50*N50 -> 8994.86 | V50: =P50*N50 -> 4200 | W50: =VLOOKUP(Q50,Taxrate!A:B,2,FALSE) -> 0.07 | X50: =U50*W50 -> 629.6402 | Y50: =VLOOKUP(L50,'Discount Rate'!A:B,2,FALSE) -> 0.05 | Z50: =Y50*U50 -> 449.743 | AA50: =U50-X50-Z50 -> 7915.4768 | AB50: =AA50-V50 -> 3715.4768
A51: ORD-00050 | B51: CUST-979 | C51: REP-33 | D51: Ahmed Khan | E51: 45575 | F51: =YEAR(E51) -> 2024 | G51: =TEXT(E51,"mmmm") -> October | H51: =TEXT(E51, "dddd") -> Thursday | I51: 0.89863426 | J51: =HOUR(I51) -> 21 | K51: =MINUTE(I51) -> 34 | L51: Smartwatch | M51: Wearables | N51: 7 | O51: 277.3 | P51: =VLOOKUP(L51,'Product-cost'!A:B,2,FALSE) -> 150 | Q51: Europe | R51: ahmedkhan@tg.inc | S51: Good value for money | T51: Postive | U51: =O51*N51 -> 1941.1 | V51: =P51*N51 -> 1050 | W51: =VLOOKUP(Q51,Taxrate!A:B,2,FALSE) -> 0.2 | X51: =U51*W51 -> 388.22 | Y51: =VLOOKUP(L51,'Discount Rate'!A:B,2,FALSE) -> 0.07 | Z51: =Y51*U51 -> 135.877 | AA51: =U51-X51-Z51 -> 1417.003 | AB51: =AA51-V51 -> 367.003
A52: ORD-00051 | B52: CUST-147 | C52: REP-21 | D52: Fatima Adebayo | E52: 45527 | F52: =YEAR(E52) -> 2024 | G52: =TEXT(E52,"mmmm") -> August | H52: =TEXT(E52, "dddd") -> Friday | I52: 0.56052083 | J52: =HOUR(I52) -> 13 | K52: =MINUTE(I52) -> 27 | L52: Smartphone | M52: Mobile Devices | N52: 10 | O52: 534.02 | P52: =VLOOKUP(L52,'Product-cost'!A:B,2,FALSE) -> 300 | Q52: Europe | R52: fatimaadebayo@tg.inc | S52: Very satisfied | T52: Postive | U52: =O52*N52 -> 5340.2 | V52: =P52*N52 -> 3000 | W52: =VLOOKUP(Q52,Taxrate!A:B,2,FALSE) -> 0.2 | X52: =U52*W52 -> 1068.04 | Y52: =VLOOKUP(L52,'Discount Rate'!A:B,2,FALSE) -> 0.1 | Z52: =Y52*U52 -> 534.02 | AA52: =U52-X52-Z52 -> 3738.14 | AB52: =AA52-V52 -> 738.14
A53: ORD-00052 | B53: CUST-753 | C53: REP-18 | D53: Noah Kim | E53: 45449 | F53: =YEAR(E53) -> 2024 | G53: =TEXT(E53,"mmmm") -> June | H53: =TEXT(E53, "dddd") -> Thursday | I53: 0.85413194 | J53: =HOUR(I53) -> 20 | K53: =MINUTE(I53) -> 29 | L53: Tablet | M53: Tablets | N53: 3 | O53: 500 | P53: =VLOOKUP(L53,'Product-cost'!A:B,2,FALSE) -> 200 | Q53: Asia | R53: noahkim@sales.techg.com | T53: Neutral | U53: =O53*N53 -> 1500 | V53: =P53*N53 -> 600 | W53: =VLOOKUP(Q53,Taxrate!A:B,2,FALSE) -> 0.1 | X53: =U53*W53 -> 150 | Y53: =VLOOKUP(L53,'Discount Rate'!A:B,2,FALSE) -> 0.08 | Z53: =Y53*U53 -> 120 | AA53: =U53-X53-Z53 -> 1230 | AB53: =AA53-V53 -> 630
A54: ORD-00053 | B54: CUST-973 | C54: REP-29 | D54: Sophie Lee | E54: 45412 | F54: =YEAR(E54) -> 2024 | G54: =TEXT(E54,"mmmm") -> April | H54: =TEXT(E54, "dddd") -> Tuesday | I54: 0.72402778 | J54: =HOUR(I54) -> 17 | K54: =MINUTE(I54) -> 22 | L54: Tablet | M54: Tablets | N54: 5 | O54: 500 | P54: =VLOOKUP(L54,'Product-cost'!A:B,2,FALSE) -> 200 | Q54: South America | R54: sophielee@tg.inc | S54: Quick shipping | T54: Postive | U54: =O54*N54 -> 2500 | V54: =P54*N54 -> 1000 | W54: =VLOOKUP(Q54,Taxrate!A:B,2,FALSE) -> 0.15 | X54: =U54*W54 -> 375 | Y54: =VLOOKUP(L54,'Discount Rate'!A:B,2,FALSE) -> 0.08 | Z54: =Y54*U54 -> 200 | AA54: =U54-X54-Z54 -> 1925 | AB54: =AA54-V54 -> 925
A55: ORD-00054 | B55: CUST-393 | C55: REP-17 | D55: Maria Garcia | E55: 45375 | F55: =YEAR(E55) -> 2024 | G55: =TEXT(E55,"mmmm") -> March | H55: =TEXT(E55, "dddd") -> Sunday | I55: 0.71994213 | J55: =HOUR(I55) -> 17 | K55: =MINUTE(I55) -> 16 | L55: Smartphone | M55: Mobile Devices | N55: 15 | O55: 491.83 | P55: =VLOOKUP(L55,'Product-cost'!A:B,2,FALSE) -> 300 | Q55: South America | R55: mariagarcia@tg.inc | T55: Neutral | U55: =O55*N55 -> 7377.45 | V55: =P55*N55 -> 4500 | W55: =VLOOKUP(Q55,Taxrate!A:B,2,FALSE) -> 0.15 | X55: =U55*W55 -> 1106.6175 | Y55: =VLOOKUP(L55,'Discount Rate'!A:B,2,FALSE) -> 0.1 | Z55: =Y55*U55 -> 737.745 | AA55: =U55-X55-Z55 -> 5533.0875 | AB55: =AA55-V55 -> 1033.0875
A56: ORD-00055 | B56: CUST-905 | C56: REP-33 | D56: Ahmed Khan | E56: 46014 | F56: =YEAR(E56) -> 2025 | G56: =TEXT(E56,"mmmm") -> December | H56: =TEXT(E56, "dddd") -> Tuesday | I56: 0.88212963 | J56: =HOUR(I56) -> 21 | K56: =MINUTE(I56) -> 10 | L56: Headphones | M56: Audio | N56: 5 | O56: 145.4 | P56: =VLOOKUP(L56,'Product-cost'!A:B,2,FALSE) -> 50 | Q56: North America | R56: ahmedkhan@tg.inc | S56: Very satisfied | T56: Postive | U56: =O56*N56 -> 727 | V56: =P56*N56 -> 250 | W56: =VLOOKUP(Q56,Taxrate!A:B,2,FALSE) -> 0.07 | X56: =U56*W56 -> 50.89 | Y56: =VLOOKUP(L56,'Discount Rate'!A:B,2,FALSE) -> 0.03 | Z56: =Y56*U56 -> 21.81 | AA56: =U56-X56-Z56 -> 654.3 | AB56: =AA56-V56 -> 404.3
A57: ORD-00056 | B57: CUST-966 | C57: REP-33 | D57: Ahmed Khan | E57: 45023 | F57: =YEAR(E57) -> 2023 | G57: =TEXT(E57,"mmmm") -> April | H57: =TEXT(E57, "dddd") -> Friday | I57: 0.34483796 | J57: =HOUR(I57) -> 8 | K57: =MINUTE(I57) -> 16 | L57: Laptop | M57: Computers | N57: 11 | O57: 931.08 | P57: =VLOOKUP(L57,'Product-cost'!A:B,2,FALSE) -> 600 | Q57: South America | R57: ahmedkhan@tg.inc | S57: Very satisfied | T57: Postive | U57: =O57*N57 -> 10241.88 | V57: =P57*N57 -> 6600 | W57: =VLOOKUP(Q57,Taxrate!A:B,2,FALSE) -> 0.15 | X57: =U57*W57 -> 1536.282 | Y57: =VLOOKUP(L57,'Discount Rate'!A:B,2,FALSE) -> 0.05 | Z57: =Y57*U57 -> 512.094 | AA57: =U57-X57-Z57 -> 8193.504 | AB57: =AA57-V57 -> 1593.504
A58: ORD-00057 | B58: CUST-435 | C58: REP-35 | D58: Carlos Rodriguez | E58: 46253 | F58: =YEAR(E58) -> 2026 | G58: =TEXT(E58,"mmmm") -> August | H58: =TEXT(E58, "dddd") -> Wednesday | I58: 0.78644676 | J58: =HOUR(I58) -> 18 | K58: =MINUTE(I58) -> 52 | L58: Tablet | M58: Tablets | N58: 2 | O58: 509.25 | P58: =VLOOKUP(L58,'Product-cost'!A:B,2,FALSE) -> 200 | Q58: Asia | R58: carlosrodriguez@sales.techg.com | S58: A bit expensive but worth it | T58: Neutral | U58: =O58*N58 -> 1018.5 | V58: =P58*N58 -> 400 | W58: =VLOOKUP(Q58,Taxrate!A:B,2,FALSE) -> 0.1 | X58: =U58*W58 -> 101.85 | Y58: =VLOOKUP(L58,'Discount Rate'!A:B,2,FALSE) -> 0.08 | Z58: =Y58*U58 -> 81.48 | AA58: =U58-X58-Z58 -> 835.17 | AB58: =AA58-V58 -> 435.17
A59: ORD-00058 | B59: CUST-813 | C59: REP-33 | D59: Ahmed Khan | E59: 46129 | F59: =YEAR(E59) -> 2026 | G59: =TEXT(E59,"mmmm") -> April | H59: =TEXT(E59, "dddd") -> Friday | I59: 0.611875 | J59: =HOUR(I59) -> 14 | K59: =MINUTE(I59) -> 41 | L59: Headphones | M59: Audio | N59: 5 | O59: 500 | P59: =VLOOKUP(L59,'Product-cost'!A:B,2,FALSE) -> 50 | Q59: Asia | R59: ahmedkhan@tg.inc | T59: Neutral | U59: =O59*N59 -> 2500 | V59: =P59*N59 -> 250 | W59: =VLOOKUP(Q59,Taxrate!A:B,2,FALSE) -> 0.1 | X59: =U59*W59 -> 250 | Y59: =VLOOKUP(L59,'Discount Rate'!A:B,2,FALSE) -> 0.03 | Z59: =Y59*U59 -> 75 | AA59: =U59-X59-Z59 -> 2175 | AB59: =AA59-V59 -> 1925
A60: ORD-00059 | B60: CUST-760 | C60: REP-22 | D60: Fatima Adebayo | E60: 45742 | F60: =YEAR(E60) -> 2025 | G60: =TEXT(E60,"mmmm") -> March | H60: =TEXT(E60, "dddd") -> Wednesday | I60: 0.46381944 | J60: =HOUR(I60) -> 11 | K60: =MINUTE(I60) -> 7 | L60: Headphones | M60: Audio | N60: 7 | O60: 167.96 | P60: =VLOOKUP(L60,'Product-cost'!A:B,2,FALSE) -> 50 | Q60: North America | R60: fatimaadebayo@tg.inc | T60: Neutral | U60: =O60*N60 -> 1175.72 | V60: =P60*N60 -> 350 | W60: =VLOOKUP(Q60,Taxrate!A:B,2,FALSE) -> 0.07 | X60: =U60*W60 -> 82.3004 | Y60: =VLOOKUP(L60,'Discount Rate'!A:B,2,FALSE) -> 0.03 | Z60: =Y60*U60 -> 35.2716 | AA60: =U60-X60-Z60 -> 1058.148 | AB60: =AA60-V60 -> 708.148
A61: ORD-00060 | B61: CUST-321 | C61: REP-17 | D61: Maria Garcia | E61: 45229 | F61: =YEAR(E61) -> 2023 | G61: =TEXT(E61,"mmmm") -> October | H61: =TEXT(E61, "dddd") -> Monday | I61: 0.53760417 | J61: =HOUR(I61) -> 12 | K61: =MINUTE(I61) -> 54 | L61: Smartphone | M61: Mobile Devices | N61: 13 | O61: 678.32 | P61: =VLOOKUP(L61,'Product-cost'!A:B,2,FALSE) -> 300 | Q61: North America | R61: mariagarcia@tg.inc | T61: Neutral | U61: =O61*N61 -> 8818.16 | V61: =P61*N61 -> 3900 | W61: =VLOOKUP(Q61,Taxrate!A:B,2,FALSE) -> 0.07 | X61: =U61*W61 -> 617.2712 | Y61: =VLOOKUP(L61,'Discount Rate'!A:B,2,FALSE) -> 0.1 | Z61: =Y61*U61 -> 881.816 | AA61: =U61-X61-Z61 -> 7319.0728 | AB61: =AA61-V61 -> 3419.0728
A62: ORD-00061 | B62: CUST-531 | C62: REP-32 | D62: Maria Garcia | E62: 45235 | F62: =YEAR(E62) -> 2023 | G62: =TEXT(E62,"mmmm") -> November | H62: =TEXT(E62, "dddd") -> Sunday | I62: 0.65929398 | J62: =HOUR(I62) -> 15 | K62: =MINUTE(I62) -> 49 | L62: Smartwatch | M62: Wearables | N62: 8 | O62: 280 | P62: =VLOOKUP(L62,'Product-cost'!A:B,2,FALSE) -> 150 | Q62: North America | R62: mariagarcia@tg.inc | T62: Neutral | U62: =O62*N62 -> 2240 | V62: =P62*N62 -> 1200 | W62: =VLOOKUP(Q62,Taxrate!A:B,2,FALSE) -> 0.07 | X62: =U62*W62 -> 156.8 | Y62: =VLOOKUP(L62,'Discount Rate'!A:B,2,FALSE) -> 0.07 | Z62: =Y62*U62 -> 156.8 | AA62: =U62-X62-Z62 -> 1926.4 | AB62: =AA62-V62 -> 726.4
A63: ORD-00062 | B63: CUST-590 | C63: REP-23 | D63: Noah Kim | E63: 46184 | F63: =YEAR(E63) -> 2026 | G63: =TEXT(E63,"mmmm") -> June | H63: =TEXT(E63, "dddd") -> Thursday | I63: 0.6569213 | J63: =HOUR(I63) -> 15 | K63: =MINUTE(I63) -> 45 | L63: Headphones | M63: Audio | N63: 7 | O63: 500 | P63: =VLOOKUP(L63,'Product-cost'!A:B,2,FALSE) -> 50 | Q63: Africa | R63: noahkim@sales.techg.com | S63: Great product | T63: Postive | U63: =O63*N63 -> 3500 | V63: =P63*N63 -> 350 | W63: =VLOOKUP(Q63,Taxrate!A:B,2,FALSE) -> 0.12 | X63: =U63*W63 -> 420 | Y63: =VLOOKUP(L63,'Discount Rate'!A:B,2,FALSE) -> 0.03 | Z63: =Y63*U63 -> 105 | AA63: =U63-X63-Z63 -> 2975 | AB63: =AA63-V63 -> 2625
A64: ORD-00063 | B64: CUST-617 | C64: REP-35 | D64: Carlos Rodriguez | E64: 45130 | F64: =YEAR(E64) -> 2023 | G64: =TEXT(E64,"mmmm") -> July | H64: =TEXT(E64, "dddd") -> Sunday | I64: 0.90394676 | J64: =HOUR(I64) -> 21 | K64: =MINUTE(I64) -> 41 | L64: Smartwatch | M64: Wearables | N64: 4 | O64: 273.69 | P64: =VLOOKUP(L64,'Product-cost'!A:B,2,FALSE) -> 150 | Q64: South America | R64: carlosrodriguez@techgadgetsco.com | S64: Good value for money | T64: Postive | U64: =O64*N64 -> 1094.76 | V64: =P64*N64 -> 600 | W64: =VLOOKUP(Q64,Taxrate!A:B,2,FALSE) -> 0.15 | X64: =U64*W64 -> 164.214 | Y64: =VLOOKUP(L64,'Discount Rate'!A:B,2,FALSE) -> 0.07 | Z64: =Y64*U64 -> 76.6332 | AA64: =U64-X64-Z64 -> 853.9128 | AB64: =AA64-V64 -> 253.9128
A65: ORD-00064 | B65: CUST-256 | C65: REP-29 | D65: Sophie Lee | E65: 45084 | F65: =YEAR(E65) -> 2023 | G65: =TEXT(E65,"mmmm") -> June | H65: =TEXT(E65, "dddd") -> Wednesday | I65: 0.39381944 | J65: =HOUR(I65) -> 9 | K65: =MINUTE(I65) -> 27 | L65: Tablet | M65: Tablets | N65: 9 | O65: 500 | P65: =VLOOKUP(L65,'Product-cost'!A:B,2,FALSE) -> 200 | Q65: Africa | R65: sophielee@tg.inc | S65: Not as expected | T65: Negative | U65: =O65*N65 -> 4500 | V65: =P65*N65 -> 1800 | W65: =VLOOKUP(Q65,Taxrate!A:B,2,FALSE) -> 0.12 | X65: =U65*W65 -> 540 | Y65: =VLOOKUP(L65,'Discount Rate'!A:B,2,FALSE) -> 0.08 | Z65: =Y65*U65 -> 360 | AA65: =U65-X65-Z65 -> 3600 | AB65: =AA65-V65 -> 1800
A66: ORD-00065 | B66: CUST-714 | C66: REP-20 | D66: Sophie Lee | E66: 44934 | F66: =YEAR(E66) -> 2023 | G66: =TEXT(E66,"mmmm") -> January | H66: =TEXT(E66, "dddd") -> Sunday | I66: 0.44618056 | J66: =HOUR(I66) -> 10 | K66: =MINUTE(I66) -> 42 | L66: Smartphone | M66: Mobile Devices | N66: 6 | O66: 590.27 | P66: =VLOOKUP(L66,'Product-cost'!A:B,2,FALSE) -> 300 | Q66: Asia | R66: sophielee@sales.techg.com | S66: Excellent quality | T66: Postive | U66: =O66*N66 -> 3541.62 | V66: =P66*N66 -> 1800 | W66: =VLOOKUP(Q66,Taxrate!A:B,2,FALSE) -> 0.1 | X66: =U66*W66 -> 354.162 | Y66: =VLOOKUP(L66,'Discount Rate'!A:B,2,FALSE) -> 0.1 | Z66: =Y66*U66 -> 354.162 | AA66: =U66-X66-Z66 -> 2833.296 | AB66: =AA66-V66 -> 1033.296
A67: ORD-00066 | B67: CUST-129 | C67: REP-15 | D67: Sophie Lee | E67: 46307 | F67: =YEAR(E67) -> 2026 | G67: =TEXT(E67,"mmmm") -> October | H67: =TEXT(E67, "dddd") -> Monday | I67: 0.55694444 | J67: =HOUR(I67) -> 13 | K67: =MINUTE(I67) -> 22 | L67: Smartphone | M67: Mobile Devices | N67: 10 | O67: 500.88 | P67: =VLOOKUP(L67,'Product-cost'!A:B,2,FALSE) -> 300 | Q67: North America | R67: sophielee@tg.inc | S67: Perfect fit | T67: Postive | U67: =O67*N67 -> 5008.8 | V67: =P67*N67 -> 3000 | W67: =VLOOKUP(Q67,Taxrate!A:B,2,FALSE) -> 0.07 | X67: =U67*W67 -> 350.616 | Y67: =VLOOKUP(L67,'Discount Rate'!A:B,2,FALSE) -> 0.1 | Z67: =Y67*U67 -> 500.88 | AA67: =U67-X67-Z67 -> 4157.304 | AB67: =AA67-V67 -> 1157.304
A68: ORD-00067 | B68: CUST-895 | C68: REP-34 | D68: Fatima Adebayo | E68: 45034 | F68: =YEAR(E68) -> 2023 | G68: =TEXT(E68,"mmmm") -> April | H68: =TEXT(E68, "dddd") -> Tuesday | I68: 0.45045139 | J68: =HOUR(I68) -> 10 | K68: =MINUTE(I68) -> 48 | L68: Laptop | M68: Computers | N68: 5 | O68: 1012.01 | P68: =VLOOKUP(L68,'Product-cost'!A:B,2,FALSE) -> 600 | Q68: Africa | R68: fatimaadebayo@tg.inc | S68: Good value for money | T68: Postive | U68: =O68*N68 -> 5060.05 | V68: =P68*N68 -> 3000 | W68: =VLOOKUP(Q68,Taxrate!A:B,2,FALSE) -> 0.12 | X68: =U68*W68 -> 607.206 | Y68: =VLOOKUP(L68,'Discount Rate'!A:B,2,FALSE) -> 0.05 | Z68: =Y68*U68 -> 253.0025 | AA68: =U68-X68-Z68 -> 4199.8415 | AB68: =AA68-V68 -> 1199.8415
A69: ORD-00068 | B69: CUST-707 | C69: REP-29 | D69: Sophie Lee | E69: 45020 | F69: =YEAR(E69) -> 2023 | G69: =TEXT(E69,"mmmm") -> April | H69: =TEXT(E69, "dddd") -> Tuesday | I69: 0.60975694 | J69: =HOUR(I69) -> 14 | K69: =MINUTE(I69) -> 38 | L69: Laptop | M69: Computers | N69: 4 | O69: 1182.08 | P69: =VLOOKUP(L69,'Product-cost'!A:B,2,FALSE) -> 600 | Q69: Asia | R69: sophielee@techgadgetsco.com | T69: Neutral | U69: =O69*N69 -> 4728.32 | V69: =P69*N69 -> 2400 | W69: =VLOOKUP(Q69,Taxrate!A:B,2,FALSE) -> 0.1 | X69: =U69*W69 -> 472.832 | Y69: =VLOOKUP(L69,'Discount Rate'!A:B,2,FALSE) -> 0.05 | Z69: =Y69*U69 -> 236.416 | AA69: =U69-X69-Z69 -> 4019.072 | AB69: =AA69-V69 -> 1619.072
A70: ORD-00069 | B70: CUST-672 | C70: REP-22 | D70: Fatima Adebayo | E70: 45740 | F70: =YEAR(E70) -> 2025 | G70: =TEXT(E70,"mmmm") -> March | H70: =TEXT(E70, "dddd") -> Monday | I70: 0.58436343 | J70: =HOUR(I70) -> 14 | K70: =MINUTE(I70) -> 1 | L70: Laptop | M70: Computers | N70: 10 | O70: 1002.21 | P70: =VLOOKUP(L70,'Product-cost'!A:B,2,FALSE) -> 600 | Q70: South America | R70: fatimaadebayo@tg.inc | S70: Fantastic customer service | T70: Postive | U70: =O70*N70 -> 10022.1 | V70: =P70*N70 -> 6000 | W70: =VLOOKUP(Q70,Taxrate!A:B,2,FALSE) -> 0.15 | X70: =U70*W70 -> 1503.315 | Y70: =VLOOKUP(L70,'Discount Rate'!A:B,2,FALSE) -> 0.05 | Z70: =Y70*U70 -> 501.105 | AA70: =U70-X70-Z70 -> 8017.68 | AB70: =AA70-V70 -> 2017.68
A71: ORD-00070 | B71: CUST-470 | C71: REP-12 | D71: Olivia Patel | E71: 45054 | F71: =YEAR(E71) -> 2023 | G71: =TEXT(E71,"mmmm") -> May | H71: =TEXT(E71, "dddd") -> Monday | I71: 0.60931713 | J71: =HOUR(I71) -> 14 | K71: =MINUTE(I71) -> 37 | L71: Smartwatch | M71: Wearables | N71: 7 | O71: 258.04 | P71: =VLOOKUP(L71,'Product-cost'!A:B,2,FALSE) -> 150 | Q71: Europe | R71: oliviapatel@tg.inc | S71: Good value for money | T71: Postive | U71: =O71*N71 -> 1806.28 | V71: =P71*N71 -> 1050 | W71: =VLOOKUP(Q71,Taxrate!A:B,2,FALSE) -> 0.2 | X71: =U71*W71 -> 361.256 | Y71: =VLOOKUP(L71,'Discount Rate'!A:B,2,FALSE) -> 0.07 | Z71: =Y71*U71 -> 126.4396 | AA71: =U71-X71-Z71 -> 1318.5844 | AB71: =AA71-V71 -> 268.5844
A72: ORD-00071 | B72: CUST-459 | C72: REP-14 | D72: Maria Garcia | E72: 45137 | F72: =YEAR(E72) -> 2023 | G72: =TEXT(E72,"mmmm") -> July | H72: =TEXT(E72, "dddd") -> Sunday | I72: 0.50846065 | J72: =HOUR(I72) -> 12 | K72: =MINUTE(I72) -> 12 | L72: Smartwatch | M72: Wearables | N72: 13 | O72: 195.49 | P72: =VLOOKUP(L72,'Product-cost'!A:B,2,FALSE) -> 150 | Q72: South America | R72: mariagarcia@techgadgetsco.com | S72: Great product | T72: Postive | U72: =O72*N72 -> 2541.37 | V72: =P72*N72 -> 1950 | W72: =VLOOKUP(Q72,Taxrate!A:B,2,FALSE) -> 0.15 | X72: =U72*W72 -> 381.2055 | Y72: =VLOOKUP(L72,'Discount Rate'!A:B,2,FALSE) -> 0.07 | Z72: =Y72*U72 -> 177.8959 | AA72: =U72-X72-Z72 -> 1982.2686 | AB72: =AA72-V72 -> 32.2686
A73: ORD-00072 | B73: CUST-169 | C73: REP-29 | D73: Sophie Lee | E73: 46220 | F73: =YEAR(E73) -> 2026 | G73: =TEXT(E73,"mmmm") -> July | H73: =TEXT(E73, "dddd") -> Friday | I73: 0.84556713 | J73: =HOUR(I73) -> 20 | K73: =MINUTE(I73) -> 17 | L73: Laptop | M73: Computers | N73: 2 | O73: 1025.96 | P73: =VLOOKUP(L73,'Product-cost'!A:B,2,FALSE) -> 600 | Q73: North America | R73: sophielee@techgadgetsco.com | S73: Would buy again | T73: Postive | U73: =O73*N73 -> 2051.92 | V73: =P73*N73 -> 1200 | W73: =VLOOKUP(Q73,Taxrate!A:B,2,FALSE) -> 0.07 | X73: =U73*W73 -> 143.6344 | Y73: =VLOOKUP(L73,'Discount Rate'!A:B,2,FALSE) -> 0.05 | Z73: =Y73*U73 -> 102.596 | AA73: =U73-X73-Z73 -> 1805.6896 | AB73: =AA73-V73 -> 605.6896
A74: ORD-00073 | B74: CUST-667 | C74: REP-11 | D74: Emma Dubois | E74: 46097 | F74: =YEAR(E74) -> 2026 | G74: =TEXT(E74,"mmmm") -> March | H74: =TEXT(E74, "dddd") -> Monday | I74: 0.56840278 | J74: =HOUR(I74) -> 13 | K74: =MINUTE(I74) -> 38 | L74: Smartwatch | M74: Wearables | N74: 1 | O74: 265.21 | P74: =VLOOKUP(L74,'Product-cost'!A:B,2,FALSE) -> 150 | Q74: Asia | R74: emmadubois@techgadgetsco.com | S74: Quick shipping | T74: Postive | U74: =O74*N74 -> 265.21 | V74: =P74*N74 -> 150 | W74: =VLOOKUP(Q74,Taxrate!A:B,2,FALSE) -> 0.1 | X74: =U74*W74 -> 26.521 | Y74: =VLOOKUP(L74,'Discount Rate'!A:B,2,FALSE) -> 0.07 | Z74: =Y74*U74 -> 18.5647 | AA74: =U74-X74-Z74 -> 220.1243 | AB74: =AA74-V74 -> 70.1243
A75: ORD-00074 | B75: CUST-635 | C75: REP-35 | D75: Carlos Rodriguez | E75: 45672 | F75: =YEAR(E75) -> 2025 | G75: =TEXT(E75,"mmmm") -> January | H75: =TEXT(E75, "dddd") -> Wednesday | I75: 0.51696759 | J75: =HOUR(I75) -> 12 | K75: =MINUTE(I75) -> 24 | L75: Tablet | M75: Tablets | N75: 1 | O75: 449.46 | P75: =VLOOKUP(L75,'Product-cost'!A:B,2,FALSE) -> 200 | Q75: North America | R75: carlosrodriguez@sales.techg.com | T75: Neutral | U75: =O75*N75 -> 449.46 | V75: =P75*N75 -> 200 | W75: =VLOOKUP(Q75,Taxrate!A:B,2,FALSE) -> 0.07 | X75: =U75*W75 -> 31.4622 | Y75: =VLOOKUP(L75,'Discount Rate'!A:B,2,FALSE) -> 0.08 | Z75: =Y75*U75 -> 35.9568 | AA75: =U75-X75-Z75 -> 382.041 | AB75: =AA75-V75 -> 182.041
A76: ORD-00075 | B76: CUST-994 | C76: REP-14 | D76: Maria Garcia | E76: 45093 | F76: =YEAR(E76) -> 2023 | G76: =TEXT(E76,"mmmm") -> June | H76: =TEXT(E76, "dddd") -> Friday | I76: 0.55533565 | J76: =HOUR(I76) -> 13 | K76: =MINUTE(I76) -> 19 | L76: Headphones | M76: Audio | N76: 12 | O76: 143.22 | P76: =VLOOKUP(L76,'Product-cost'!A:B,2,FALSE) -> 50 | Q76: South America | R76: mariagarcia@sales.techg.com | T76: Neutral | U76: =O76*N76 -> 1718.64 | V76: =P76*N76 -> 600 | W76: =VLOOKUP(Q76,Taxrate!A:B,2,FALSE) -> 0.15 | X76: =U76*W76 -> 257.796 | Y76: =VLOOKUP(L76,'Discount Rate'!A:B,2,FALSE) -> 0.03 | Z76: =Y76*U76 -> 51.5592 | AA76: =U76-X76-Z76 -> 1409.2848 | AB76: =AA76-V76 -> 809.2848
A77: ORD-00076 | B77: CUST-118 | C77: REP-22 | D77: Fatima Adebayo | E77: 45413 | F77: =YEAR(E77) -> 2024 | G77: =TEXT(E77,"mmmm") -> May | H77: =TEXT(E77, "dddd") -> Wednesday | I77: 0.57605324 | J77: =HOUR(I77) -> 13 | K77: =MINUTE(I77) -> 49 | L77: Smartphone | M77: Mobile Devices | N77: 3 | O77: 568.74 | P77: =VLOOKUP(L77,'Product-cost'!A:B,2,FALSE) -> 300 | Q77: North America | R77: fatimaadebayo@sales.techg.com | T77: Neutral | U77: =O77*N77 -> 1706.22 | V77: =P77*N77 -> 900 | W77: =VLOOKUP(Q77,Taxrate!A:B,2,FALSE) -> 0.07 | X77: =U77*W77 -> 119.4354 | Y77: =VLOOKUP(L77,'Discount Rate'!A:B,2,FALSE) -> 0.1 | Z77: =Y77*U77 -> 170.622 | AA77: =U77-X77-Z77 -> 1416.1626 | AB77: =AA77-V77 -> 516.1626
A78: ORD-00077 | B78: CUST-234 | C78: REP-35 | D78: Carlos Rodriguez | E78: 45271 | F78: =YEAR(E78) -> 2023 | G78: =TEXT(E78,"mmmm") -> December | H78: =TEXT(E78, "dddd") -> Monday | I78: 0.45398148 | J78: =HOUR(I78) -> 10 | K78: =MINUTE(I78) -> 53 | L78: Smartwatch | M78: Wearables | N78: 3 | O78: 180.81 | P78: =VLOOKUP(L78,'Product-cost'!A:B,2,FALSE) -> 150 | Q78: Asia | R78: carlosrodriguez@techgadgetsco.com | T78: Neutral | U78: =O78*N78 -> 542.43 | V78: =P78*N78 -> 450 | W78: =VLOOKUP(Q78,Taxrate!A:B,2,FALSE) -> 0.1 | X78: =U78*W78 -> 54.243 | Y78: =VLOOKUP(L78,'Discount Rate'!A:B,2,FALSE) -> 0.07 | Z78: =Y78*U78 -> 37.9701 | AA78: =U78-X78-Z78 -> 450.2169 | AB78: =AA78-V78 -> 0.2169
A79: ORD-00078 | B79: CUST-344 | C79: REP-20 | D79: Sophie Lee | E79: 45324 | F79: =YEAR(E79) -> 2024 | G79: =TEXT(E79,"mmmm") -> February | H79: =TEXT(E79, "dddd") -> Friday | I79: 0.77532407 | J79: =HOUR(I79) -> 18 | K79: =MINUTE(I79) -> 36 | L79: Headphones | M79: Audio | N79: 13 | O79: 159.56 | P79: =VLOOKUP(L79,'Product-cost'!A:B,2,FALSE) -> 50 | Q79: Europe | R79: sophielee@sales.techg.com | T79: Neutral | U79: =O79*N79 -> 2074.28 | V79: =P79*N79 -> 650 | W79: =VLOOKUP(Q79,Taxrate!A:B,2,FALSE) -> 0.2 | X79: =U79*W79 -> 414.856 | Y79: =VLOOKUP(L79,'Discount Rate'!A:B,2,FALSE) -> 0.03 | Z79: =Y79*U79 -> 62.2284 | AA79: =U79-X79-Z79 -> 1597.1956 | AB79: =AA79-V79 -> 947.1956
A80: ORD-00079 | B80: CUST-205 | C80: REP-32 | D80: Maria Garcia | E80: 45451 | F80: =YEAR(E80) -> 2024 | G80: =TEXT(E80,"mmmm") -> June | H80: =TEXT(E80, "dddd") -> Saturday | I80: 0.84047454 | J80: =HOUR(I80) -> 20 | K80: =MINUTE(I80) -> 10 | L80: Headphones | M80: Audio | N80: 3 | O80: 126.88 | P80: =VLOOKUP(L80,'Product-cost'!A:B,2,FALSE) -> 50 | Q80: Europe | R80: mariagarcia@tg.inc | T80: Neutral | U80: =O80*N80 -> 380.64 | V80: =P80*N80 -> 150 | W80: =VLOOKUP(Q80,Taxrate!A:B,2,FALSE) -> 0.2 | X80: =U80*W80 -> 76.128 | Y80: =VLOOKUP(L80,'Discount Rate'!A:B,2,FALSE) -> 0.03 | Z80: =Y80*U80 -> 11.4192 | AA80: =U80-X80-Z80 -> 293.0928 | AB80: =AA80-V80 -> 143.0928
A81: ORD-00080 | B81: CUST-183 | C81: REP-22 | D81: Fatima Adebayo | E81: 44984 | F81: =YEAR(E81) -> 2023 | G81: =TEXT(E81,"mmmm") -> February | H81: =TEXT(E81, "dddd") -> Monday | I81: 0.41232639 | J81: =HOUR(I81) -> 9 | K81: =MINUTE(I81) -> 53 | L81: Tablet | M81: Tablets | N81: 3 | O81: 500 | P81: =VLOOKUP(L81,'Product-cost'!A:B,2,FALSE) -> 200 | Q81: South America | R81: fatimaadebayo@tg.inc | S81: Perfect fit | T81: Postive | U81: =O81*N81 -> 1500 | V81: =P81*N81 -> 600 | W81: =VLOOKUP(Q81,Taxrate!A:B,2,FALSE) -> 0.15 | X81: =U81*W81 -> 225 | Y81: =VLOOKUP(L81,'Discount Rate'!A:B,2,FALSE) -> 0.08 | Z81: =Y81*U81 -> 120 | AA81: =U81-X81-Z81 -> 1155 | AB81: =AA81-V81 -> 555
A82: ORD-00081 | B82: CUST-320 | C82: REP-14 | D82: Maria Garcia | E82: 46173 | F82: =YEAR(E82) -> 2026 | G82: =TEXT(E82,"mmmm") -> May | H82: =TEXT(E82, "dddd") -> Sunday | I82: 0.40923611 | J82: =HOUR(I82) -> 9 | K82: =MINUTE(I82) -> 49 | L82: Smartphone | M82: Mobile Devices | N82: 1 | O82: 671.69 | P82: =VLOOKUP(L82,'Product-cost'!A:B,2,FALSE) -> 300 | Q82: Africa | R82: mariagarcia@tg.inc | S82: Excellent quality | T82: Postive | U82: =O82*N82 -> 671.69 | V82: =P82*N82 -> 300 | W82: =VLOOKUP(Q82,Taxrate!A:B,2,FALSE) -> 0.12 | X82: =U82*W82 -> 80.6028 | Y82: =VLOOKUP(L82,'Discount Rate'!A:B,2,FALSE) -> 0.1 | Z82: =Y82*U82 -> 67.169 | AA82: =U82-X82-Z82 -> 523.9182 | AB82: =AA82-V82 -> 223.9182
A83: ORD-00082 | B83: CUST-398 | C83: REP-24 | D83: Liam Chen | E83: 46186 | F83: =YEAR(E83) -> 2026 | G83: =TEXT(E83,"mmmm") -> June | H83: =TEXT(E83, "dddd") -> Saturday | I83: 0.48363426 | J83: =HOUR(I83) -> 11 | K83: =MINUTE(I83) -> 36 | L83: Smartphone | M83: Mobile Devices | N83: 2 | O83: 588.18 | P83: =VLOOKUP(L83,'Product-cost'!A:B,2,FALSE) -> 300 | Q83: Africa | R83: liamchen@techgadgetsco.com | S83: Excellent quality | T83: Postive | U83: =O83*N83 -> 1176.36 | V83: =P83*N83 -> 600 | W83: =VLOOKUP(Q83,Taxrate!A:B,2,FALSE) -> 0.12 | X83: =U83*W83 -> 141.1632 | Y83: =VLOOKUP(L83,'Discount Rate'!A:B,2,FALSE) -> 0.1 | Z83: =Y83*U83 -> 117.636 | AA83: =U83-X83-Z83 -> 917.5608 | AB83: =AA83-V83 -> 317.5608
A84: ORD-00083 | B84: CUST-482 | C84: REP-18 | D84: Noah Kim | E84: 45658 | F84: =YEAR(E84) -> 2025 | G84: =TEXT(E84,"mmmm") -> January | H84: =TEXT(E84, "dddd") -> Wednesday | I84: 0.55261574 | J84: =HOUR(I84) -> 13 | K84: =MINUTE(I84) -> 15 | L84: Laptop | M84: Computers | N84: 12 | O84: 866.7 | P84: =VLOOKUP(L84,'Product-cost'!A:B,2,FALSE) -> 600 | Q84: Asia | R84: noahkim@tg.inc | S84: Perfect fit | T84: Postive | U84: =O84*N84 -> 10400.4 | V84: =P84*N84 -> 7200 | W84: =VLOOKUP(Q84,Taxrate!A:B,2,FALSE) -> 0.1 | X84: =U84*W84 -> 1040.04 | Y84: =VLOOKUP(L84,'Discount Rate'!A:B,2,FALSE) -> 0.05 | Z84: =Y84*U84 -> 520.02 | AA84: =U84-X84-Z84 -> 8840.34 | AB84: =AA84-V84 -> 1640.34
A85: ORD-00084 | B85: CUST-238 | C85: REP-12 | D85: Olivia Patel | E85: 45002 | F85: =YEAR(E85) -> 2023 | G85: =TEXT(E85,"mmmm") -> March | H85: =TEXT(E85, "dddd") -> Friday | I85: 0.46030093 | J85: =HOUR(I85) -> 11 | K85: =MINUTE(I85) -> 2 | L85: Smartphone | M85: Mobile Devices | N85: 6 | O85: 634.62 | P85: =VLOOKUP(L85,'Product-cost'!A:B,2,FALSE) -> 300 | Q85: Africa | R85: oliviapatel@tg.inc | T85: Neutral | U85: =O85*N85 -> 3807.72 | V85: =P85*N85 -> 1800 | W85: =VLOOKUP(Q85,Taxrate!A:B,2,FALSE) -> 0.12 | X85: =U85*W85 -> 456.9264 | Y85: =VLOOKUP(L85,'Discount Rate'!A:B,2,FALSE) -> 0.1 | Z85: =Y85*U85 -> 380.772 | AA85: =U85-X85-Z85 -> 2970.0216 | AB85: =AA85-V85 -> 1170.0216
A86: ORD-00085 | B86: CUST-439 | C86: REP-18 | D86: Noah Kim | E86: 45680 | F86: =YEAR(E86) -> 2025 | G86: =TEXT(E86,"mmmm") -> January | H86: =TEXT(E86, "dddd") -> Thursday | I86: 0.6162963 | J86: =HOUR(I86) -> 14 | K86: =MINUTE(I86) -> 47 | L86: Headphones | M86: Audio | N86: 3 | O86: 157.31 | P86: =VLOOKUP(L86,'Product-cost'!A:B,2,FALSE) -> 50 | Q86: Africa | R86: noahkim@tg.inc | S86: Not as expected | T86: Negative | U86: =O86*N86 -> 471.93 | V86: =P86*N86 -> 150 | W86: =VLOOKUP(Q86,Taxrate!A:B,2,FALSE) -> 0.12 | X86: =U86*W86 -> 56.6316 | Y86: =VLOOKUP(L86,'Discount Rate'!A:B,2,FALSE) -> 0.03 | Z86: =Y86*U86 -> 14.1579 | AA86: =U86-X86-Z86 -> 401.1405 | AB86: =AA86-V86 -> 251.1405
A87: ORD-00086 | B87: CUST-428 | C87: REP-13 | D87: Ahmed Khan | E87: 45333 | F87: =YEAR(E87) -> 2024 | G87: =TEXT(E87,"mmmm") -> February | H87: =TEXT(E87, "dddd") -> Sunday | I87: 0.51988426 | J87: =HOUR(I87) -> 12 | K87: =MINUTE(I87) -> 28 | L87: Headphones | M87: Audio | N87: 8 | O87: 123.18 | P87: =VLOOKUP(L87,'Product-cost'!A:B,2,FALSE) -> 50 | Q87: Asia | R87: ahmedkhan@tg.inc | T87: Neutral | U87: =O87*N87 -> 985.44 | V87: =P87*N87 -> 400 | W87: =VLOOKUP(Q87,Taxrate!A:B,2,FALSE) -> 0.1 | X87: =U87*W87 -> 98.544 | Y87: =VLOOKUP(L87,'Discount Rate'!A:B,2,FALSE) -> 0.03 | Z87: =Y87*U87 -> 29.5632 | AA87: =U87-X87-Z87 -> 857.3328 | AB87: =AA87-V87 -> 457.3328
A88: ORD-00087 | B88: CUST-920 | C88: REP-15 | D88: Sophie Lee | E88: 45219 | F88: =YEAR(E88) -> 2023 | G88: =TEXT(E88,"mmmm") -> October | H88: =TEXT(E88, "dddd") -> Friday | I88: 0.33893519 | J88: =HOUR(I88) -> 8 | K88: =MINUTE(I88) -> 8 | L88: Smartphone | M88: Mobile Devices | N88: 6 | O88: 764.84 | P88: =VLOOKUP(L88,'Product-cost'!A:B,2,FALSE) -> 300 | Q88: North America | R88: sophielee@techgadgetsco.com | S88: Fast delivery | T88: Postive | U88: =O88*N88 -> 4589.04 | V88: =P88*N88 -> 1800 | W88: =VLOOKUP(Q88,Taxrate!A:B,2,FALSE) -> 0.07 | X88: =U88*W88 -> 321.2328 | Y88: =VLOOKUP(L88,'Discount Rate'!A:B,2,FALSE) -> 0.1 | Z88: =Y88*U88 -> 458.904 | AA88: =U88-X88-Z88 -> 3808.9032 | AB88: =AA88-V88 -> 2008.9032
A89: ORD-00088 | B89: CUST-475 | C89: REP-23 | D89: Noah Kim | E89: 46257 | F89: =YEAR(E89) -> 2026 | G89: =TEXT(E89,"mmmm") -> August | H89: =TEXT(E89, "dddd") -> Sunday | I89: 0.46320602 | J89: =HOUR(I89) -> 11 | K89: =MINUTE(I89) -> 7 | L89: Smartphone | M89: Mobile Devices | N89: 7 | O89: 515.33 | P89: =VLOOKUP(L89,'Product-cost'!A:B,2,FALSE) -> 300 | Q89: Asia | R89: noahkim@sales.techg.com | S89: Battery life amazing | T89: Postive | U89: =O89*N89 -> 3607.31 | V89: =P89*N89 -> 2100 | W89: =VLOOKUP(Q89,Taxrate!A:B,2,FALSE) -> 0.1 | X89: =U89*W89 -> 360.731 | Y89: =VLOOKUP(L89,'Discount Rate'!A:B,2,FALSE) -> 0.1 | Z89: =Y89*U89 -> 360.731 | AA89: =U89-X89-Z89 -> 2885.848 | AB89: =AA89-V89 -> 785.848
A90: ORD-00089 | B90: CUST-276 | C90: REP-28 | D90: Maria Garcia | E90: 46323 | F90: =YEAR(E90) -> 2026 | G90: =TEXT(E90,"mmmm") -> October | H90: =TEXT(E90, "dddd") -> Wednesday | I90: 0.76579861 | J90: =HOUR(I90) -> 18 | K90: =MINUTE(I90) -> 22 | L90: Laptop | M90: Computers | N90: 5 | O90: 1225.68 | P90: =VLOOKUP(L90,'Product-cost'!A:B,2,FALSE) -> 600 | Q90: Europe | R90: mariagarcia@sales.techg.com | S90: Packaging was damaged | T90: Negative | U90: =O90*N90 -> 6128.4 | V90: =P90*N90 -> 3000 | W90: =VLOOKUP(Q90,Taxrate!A:B,2,FALSE) -> 0.2 | X90: =U90*W90 -> 1225.68 | Y90: =VLOOKUP(L90,'Discount Rate'!A:B,2,FALSE) -> 0.05 | Z90: =Y90*U90 -> 306.42 | AA90: =U90-X90-Z90 -> 4596.3 | AB90: =AA90-V90 -> 1596.3
A91: ORD-00090 | B91: CUST-469 | C91: REP-33 | D91: Ahmed Khan | E91: 45884 | F91: =YEAR(E91) -> 2025 | G91: =TEXT(E91,"mmmm") -> August | H91: =TEXT(E91, "dddd") -> Friday | I91: 0.74728009 | J91: =HOUR(I91) -> 17 | K91: =MINUTE(I91) -> 56 | L91: Laptop | M91: Computers | N91: 12 | O91: 1062.85 | P91: =VLOOKUP(L91,'Product-cost'!A:B,2,FALSE) -> 600 | Q91: South America | R91: ahmedkhan@tg.inc | S91: Would buy again | T91: Postive | U91: =O91*N91 -> 12754.2 | V91: =P91*N91 -> 7200 | W91: =VLOOKUP(Q91,Taxrate!A:B,2,FALSE) -> 0.15 | X91: =U91*W91 -> 1913.13 | Y91: =VLOOKUP(L91,'Discount Rate'!A:B,2,FALSE) -> 0.05 | Z91: =Y91*U91 -> 637.71 | AA91: =U91-X91-Z91 -> 10203.36 | AB91: =AA91-V91 -> 3003.36
A92: ORD-00091 | B92: CUST-999 | C92: REP-33 | D92: Ahmed Khan | E92: 45191 | F92: =YEAR(E92) -> 2023 | G92: =TEXT(E92,"mmmm") -> September | H92: =TEXT(E92, "dddd") -> Friday | I92: 0.70758102 | J92: =HOUR(I92) -> 16 | K92: =MINUTE(I92) -> 58 | L92: Laptop | M92: Computers | N92: 9 | O92: 882.33 | P92: =VLOOKUP(L92,'Product-cost'!A:B,2,FALSE) -> 600 | Q92: Asia | R92: ahmedkhan@sales.techg.com | S92: Love the design | T92: Postive | U92: =O92*N92 -> 7940.97 | V92: =P92*N92 -> 5400 | W92: =VLOOKUP(Q92,Taxrate!A:B,2,FALSE) -> 0.1 | X92: =U92*W92 -> 794.097 | Y92: =VLOOKUP(L92,'Discount Rate'!A:B,2,FALSE) -> 0.05 | Z92: =Y92*U92 -> 397.0485 | AA92: =U92-X92-Z92 -> 6749.8245 | AB92: =AA92-V92 -> 1349.8245
A93: ORD-00092 | B93: CUST-750 | C93: REP-33 | D93: Ahmed Khan | E93: 45183 | F93: =YEAR(E93) -> 2023 | G93: =TEXT(E93,"mmmm") -> September | H93: =TEXT(E93, "dddd") -> Thursday | I93: 0.73200231 | J93: =HOUR(I93) -> 17 | K93: =MINUTE(I93) -> 34 | L93: Smartwatch | M93: Wearables | N93: 10 | O93: 192.96 | P93: =VLOOKUP(L93,'Product-cost'!A:B,2,FALSE) -> 150 | Q93: Africa | R93: ahmedkhan@tg.inc | S93: Quick shipping | T93: Postive | U93: =O93*N93 -> 1929.6 | V93: =P93*N93 -> 1500 | W93: =VLOOKUP(Q93,Taxrate!A:B,2,FALSE) -> 0.12 | X93: =U93*W93 -> 231.552 | Y93: =VLOOKUP(L93,'Discount Rate'!A:B,2,FALSE) -> 0.07 | Z93: =Y93*U93 -> 135.072 | AA93: =U93-X93-Z93 -> 1562.976 | AB93: =AA93-V93 -> 62.976
A94: ORD-00093 | B94: CUST-756 | C94: REP-34 | D94: Fatima Adebayo | E94: 46260 | F94: =YEAR(E94) -> 2026 | G94: =TEXT(E94,"mmmm") -> August | H94: =TEXT(E94, "dddd") -> Wednesday | I94: 0.85863426 | J94: =HOUR(I94) -> 20 | K94: =MINUTE(I94) -> 36 | L94: Smartwatch | M94: Wearables | N94: 8 | O94: 236.01 | P94: =VLOOKUP(L94,'Product-cost'!A:B,2,FALSE) -> 150 | Q94: Asia | R94: fatimaadebayo@sales.techg.com | T94: Neutral | U94: =O94*N94 -> 1888.08 | V94: =P94*N94 -> 1200 | W94: =VLOOKUP(Q94,Taxrate!A:B,2,FALSE) -> 0.1 | X94: =U94*W94 -> 188.808 | Y94: =VLOOKUP(L94,'Discount Rate'!A:B,2,FALSE) -> 0.07 | Z94: =Y94*U94 -> 132.1656 | AA94: =U94-X94-Z94 -> 1567.1064 | AB94: =AA94-V94 -> 367.1064
A95: ORD-00094 | B95: CUST-525 | C95: REP-29 | D95: Sophie Lee | E95: 45344 | F95: =YEAR(E95) -> 2024 | G95: =TEXT(E95,"mmmm") -> February | H95: =TEXT(E95, "dddd") -> Thursday | I95: 0.71481481 | J95: =HOUR(I95) -> 17 | K95: =MINUTE(I95) -> 9 | L95: Tablet | M95: Tablets | N95: 14 | O95: 399.74 | P95: =VLOOKUP(L95,'Product-cost'!A:B,2,FALSE) -> 200 | Q95: Asia | R95: sophielee@techgadgetsco.com | S95: Good value for money | T95: Postive | U95: =O95*N95 -> 5596.36 | V95: =P95*N95 -> 2800 | W95: =VLOOKUP(Q95,Taxrate!A:B,2,FALSE) -> 0.1 | X95: =U95*W95 -> 559.636 | Y95: =VLOOKUP(L95,'Discount Rate'!A:B,2,FALSE) -> 0.08 | Z95: =Y95*U95 -> 447.7088 | AA95: =U95-X95-Z95 -> 4589.0152 | AB95: =AA95-V95 -> 1789.0152
A96: ORD-00095 | B96: CUST-397 | C96: REP-23 | D96: Noah Kim | E96: 45435 | F96: =YEAR(E96) -> 2024 | G96: =TEXT(E96,"mmmm") -> May | H96: =TEXT(E96, "dddd") -> Thursday | I96: 0.88957176 | J96: =HOUR(I96) -> 21 | K96: =MINUTE(I96) -> 20 | L96: Smartwatch | M96: Wearables | N96: 4 | O96: 230.81 | P96: =VLOOKUP(L96,'Product-cost'!A:B,2,FALSE) -> 150 | Q96: Africa | R96: noahkim@sales.techg.com | S96: Would buy again | T96: Postive | U96: =O96*N96 -> 923.24 | V96: =P96*N96 -> 600 | W96: =VLOOKUP(Q96,Taxrate!A:B,2,FALSE) -> 0.12 | X96: =U96*W96 -> 110.7888 | Y96: =VLOOKUP(L96,'Discount Rate'!A:B,2,FALSE) -> 0.07 | Z96: =Y96*U96 -> 64.6268 | AA96: =U96-X96-Z96 -> 747.8244 | AB96: =AA96-V96 -> 147.8244
A97: ORD-00096 | B97: CUST-320 | C97: REP-34 | D97: Fatima Adebayo | E97: 45203 | F97: =YEAR(E97) -> 2023 | G97: =TEXT(E97,"mmmm") -> October | H97: =TEXT(E97, "dddd") -> Wednesday | I97: 0.52196759 | J97: =HOUR(I97) -> 12 | K97: =MINUTE(I97) -> 31 | L97: Headphones | M97: Audio | N97: 1 | O97: 152.32 | P97: =VLOOKUP(L97,'Product-cost'!A:B,2,FALSE) -> 50 | Q97: Asia | R97: fatimaadebayo@sales.techg.com | T97: Neutral | U97: =O97*N97 -> 152.32 | V97: =P97*N97 -> 50 | W97: =VLOOKUP(Q97,Taxrate!A:B,2,FALSE) -> 0.1 | X97: =U97*W97 -> 15.232 | Y97: =VLOOKUP(L97,'Discount Rate'!A:B,2,FALSE) -> 0.03 | Z97: =Y97*U97 -> 4.5696 | AA97: =U97-X97-Z97 -> 132.5184 | AB97: =AA97-V97 -> 82.5184
A98: ORD-00097 | B98: CUST-395 | C98: REP-12 | D98: Olivia Patel | E98: 45959 | F98: =YEAR(E98) -> 2025 | G98: =TEXT(E98,"mmmm") -> October | H98: =TEXT(E98, "dddd") -> Wednesday | I98: 0.85783565 | J98: =HOUR(I98) -> 20 | K98: =MINUTE(I98) -> 35 | L98: Smartwatch | M98: Wearables | N98: 2 | O98: 186.63 | P98: =VLOOKUP(L98,'Product-cost'!A:B,2,FALSE) -> 150 | Q98: Asia | R98: oliviapatel@tg.inc | S98: A bit expensive but worth it | T98: Neutral | U98: =O98*N98 -> 373.26 | V98: =P98*N98 -> 300 | W98: =VLOOKUP(Q98,Taxrate!A:B,2,FALSE) -> 0.1 | X98: =U98*W98 -> 37.326 | Y98: =VLOOKUP(L98,'Discount Rate'!A:B,2,FALSE) -> 0.07 | Z98: =Y98*U98 -> 26.1282 | AA98: =U98-X98-Z98 -> 309.8058 | AB98: =AA98-V98 -> 9.8058
A99: ORD-00098 | B99: CUST-146 | C99: REP-11 | D99: Emma Dubois | E99: 45609 | F99: =YEAR(E99) -> 2024 | G99: =TEXT(E99,"mmmm") -> November | H99: =TEXT(E99, "dddd") -> Wednesday | I99: 0.68690972 | J99: =HOUR(I99) -> 16 | K99: =MINUTE(I99) -> 29 | L99: Smartwatch | M99: Wearables | N99: 3 | O99: 243.44 | P99: =VLOOKUP(L99,'Product-cost'!A:B,2,FALSE) -> 150 | Q99: Europe | R99: emmadubois@tg.inc | S99: Great product | T99: Postive | U99: =O99*N99 -> 730.32 | V99: =P99*N99 -> 450 | W99: =VLOOKUP(Q99,Taxrate!A:B,2,FALSE) -> 0.2 | X99: =U99*W99 -> 146.064 | Y99: =VLOOKUP(L99,'Discount Rate'!A:B,2,FALSE) -> 0.07 | Z99: =Y99*U99 -> 51.1224 | AA99: =U99-X99-Z99 -> 533.1336 | AB99: =AA99-V99 -> 83.1336
A100: ORD-00099 | B100: CUST-676 | C100: REP-20 | D100: Sophie Lee | E100: 45018 | F100: =YEAR(E100) -> 2023 | G100: =TEXT(E100,"mmmm") -> April | H100: =TEXT(E100, "dddd") -> Sunday | I100: 0.5716088 | J100: =HOUR(I100) -> 13 | K100: =MINUTE(I100) -> 43 | L100: Headphones | M100: Audio | N100: 13 | O100: 185.41 | P100: =VLOOKUP(L100,'Product-cost'!A:B,2,FALSE) -> 50 | Q100: North America | R100: sophielee@sales.techg.com | S100: Very satisfied | T100: Postive | U100: =O100*N100 -> 2410.33 | V100: =P100*N100 -> 650 | W100: =VLOOKUP(Q100,Taxrate!A:B,2,FALSE) -> 0.07 | X100: =U100*W100 -> 168.7231 | Y100: =VLOOKUP(L100,'Discount Rate'!A:B,2,FALSE) -> 0.03 | Z100: =Y100*U100 -> 72.3099 | AA100: =U100-X100-Z100 -> 2169.297 | AB100: =AA100-V100 -> 1519.297
...

Sheet dashboard
D1: SALES TECH DASHBORAD
B2: SALES TOLTAL REVENU | C2: TOTAL COST | D2: TOTAL TAX | E2: NUM OF ORDERS | F2: NUMOF SALES REP
B3: 1331871.6 | C3: 867350 | D3: 215288.03 | E3: 435 | F3: 9

Sheet Product-cost
A1: Product | B1: Cost
A2: Laptop | B2: 600
A3: Smartphone | B3: 300
A4: Tablet | B4: 200
A5: Headphones | B5: 50
A6: Smartwatch | B6: 150

Sheet Taxrate
A1: Region | B1: TaxRate
A2: North America | B2: 0.07
A3: Europe | B3: 0.2
A4: Asia | B4: 0.1
A5: South America | B5: 0.15
A6: Africa | B6: 0.12

Sheet Discount Rate
A1: Product | B1: DiscountRate
A2: Laptop | B2: 0.05
A3: Smartphone | B3: 0.1
A4: Tablet | B4: 0.08
A5: Headphones | B5: 0.03
A6: Smartwatch | B6: 0.07
