Workbook

Sheet Sales Dataset
A1: OrderID | B1: CustomerID | C1: SalesRepID | D1: sales repname | E1: sales rep firstnname | F1: sales rep surname | G1: Date | H1: year | I1: month | J1: day | K1: Time | L1: hour | M1: minute | N1: seconds | O1: product | P1: product category | Q1: OrderQuantity | R1: UnitPrice | S1: Unit Cost | T1: sales region | U1: SalesRepEmail | V1: feeback | W1: feedback cateory | X1: Gross Revenue | Y1: Total Cost | Z1: Tax Rate | AA1: Tax Amount | AB1: Discount Rate | AC1: discount amount | AD1: Net Sales
A2: ORD-00001 | B2: CUST-754 | C2: REP-13 | D2: Ahmed Khan | E2: Ahmed | F2: Khan | G2: 45490 | H2: =YEAR(G2) -> 2024 | I2: =TEXT(G2,"mmmm") -> July | J2: =TEXT(G2,"dddd") -> Wednesday | K2: 0.46443287 | L2: =HOUR(K2) -> 11 | M2: =MINUTE(K2) -> 8 | N2: =SECOND(K2) -> 47 | O2: Laptop | P2: Computers | Q2: 15 | R2: 1095.25 | S2: =VLOOKUP(O2,'Product-cost'!A:B,2,) -> 600 | T2: North America | U2: ahmedkhan@tg.inc | V2: Excellent Quality | W2: positive | X2: =R2*Q2 -> 16428.75 | Y2: =S2*Q2 -> 9000 | Z2: =VLOOKUP(T2,Taxrate!A:B,2,FALSE) -> 0.07 | AA2: =X2*Z2 -> 1150.0125 | AB2: =VLOOKUP('Sales Dataset'!O2,'Discount Rate'!A:B,2,) -> 0.05 | AC2: =Y2*AB2 -> 450 | AD2: =Y2-AB2-Z2 -> 8999.88
A3: ORD-00002 | B3: CUST-529 | C3: REP-17 | D3: Maria Garcia | E3: Maria | F3: Garcia | G3: 46133 | H3: =YEAR(G3) -> 2026 | I3: =TEXT(G3,"mmmm") -> April | J3: =TEXT(G3,"dddd") -> Tuesday | K3: 0.87152778 | L3: =HOUR(K3) -> 20 | M3: =MINUTE(K3) -> 55 | N3: =SECOND(K3) -> 0 | O3: Smartphone | P3: Mobile Devices | Q3: 6 | R3: 544.59 | S3: =VLOOKUP(O3,'Product-cost'!A:B,2,) -> 300 | T3: Asia | U3: mariagarcia@tg.inc | V3: Fast Delivery | W3: positive | X3: =R3*Q3 -> 3267.54 | Y3: =S3*Q3 -> 1800 | Z3: =VLOOKUP(T3,Taxrate!A:B,2,FALSE) -> 0.1 | AA3: =X3*Z3 -> 326.754 | AB3: =VLOOKUP('Sales Dataset'!O3,'Discount Rate'!A:B,2,) -> 0.1 | AC3: =Y3*AB3 -> 180 | AD3: =Y3-AB3-Z3 -> 1799.8
A4: ORD-00003 | B4: CUST-649 | C4: REP-13 | D4: Ahmed Khan | E4: Ahmed | F4: Khan | G4: 45236 | H4: =YEAR(G4) -> 2023 | I4: =TEXT(G4,"mmmm") -> November | J4: =TEXT(G4,"dddd") -> Monday | K4: 0.90322917 | L4: =HOUR(K4) -> 21 | M4: =MINUTE(K4) -> 40 | N4: =SECOND(K4) -> 39 | O4: Tablet | P4: Tablets | Q4: 12 | R4: 500 | S4: =VLOOKUP(O4,'Product-cost'!A:B,2,) -> 200 | T4: Europe | U4: ahmedkhan@sales.techg.com | V4: Good Value For Money | W4: positive | X4: =R4*Q4 -> 6000 | Y4: =S4*Q4 -> 2400 | Z4: =VLOOKUP(T4,Taxrate!A:B,2,FALSE) -> 0.2 | AA4: =X4*Z4 -> 1200 | AB4: =VLOOKUP('Sales Dataset'!O4,'Discount Rate'!A:B,2,) -> 0.08 | AC4: =Y4*AB4 -> 192 | AD4: =Y4-AB4-Z4 -> 2399.72
A5: ORD-00004 | B5: CUST-266 | C5: REP-22 | D5: Fatima Adebayo | E5: Fatima | F5: Adebayo | G5: 45415 | H5: =YEAR(G5) -> 2024 | I5: =TEXT(G5,"mmmm") -> May | J5: =TEXT(G5,"dddd") -> Friday | K5: 0.83313657 | L5: =HOUR(K5) -> 19 | M5: =MINUTE(K5) -> 59 | N5: =SECOND(K5) -> 43 | O5: Laptop | P5: Computers | Q5: 3 | R5: 922.41 | S5: =VLOOKUP(O5,'Product-cost'!A:B,2,) -> 600 | T5: South America | U5: fatimaadebayo@sales.techg.com | V5: Very Satisfied | W5: positive | X5: =R5*Q5 -> 2767.23 | Y5: =S5*Q5 -> 1800 | Z5: =VLOOKUP(T5,Taxrate!A:B,2,FALSE) -> 0.15 | AA5: =X5*Z5 -> 415.0845 | AB5: =VLOOKUP('Sales Dataset'!O5,'Discount Rate'!A:B,2,) -> 0.05 | AC5: =Y5*AB5 -> 90 | AD5: =Y5-AB5-Z5 -> 1799.8
A6: ORD-00005 | B6: CUST-334 | C6: REP-11 | D6: Emma Dubois | E6: Emma | F6: Dubois | G6: 45661 | H6: =YEAR(G6) -> 2025 | I6: =TEXT(G6,"mmmm") -> January | J6: =TEXT(G6,"dddd") -> Saturday | K6: 0.38469907 | L6: =HOUR(K6) -> 9 | M6: =MINUTE(K6) -> 13 | N6: =SECOND(K6) -> 58 | O6: Smartwatch | P6: Wearables | Q6: 6 | R6: 230.92 | S6: =VLOOKUP(O6,'Product-cost'!A:B,2,) -> 150 | T6: South America | U6: emmadubois@techgadgetsco.com | W6: neutral | X6: =R6*Q6 -> 1385.52 | Y6: =S6*Q6 -> 900 | Z6: =VLOOKUP(T6,Taxrate!A:B,2,FALSE) -> 0.15 | AA6: =X6*Z6 -> 207.828 | AB6: =VLOOKUP('Sales Dataset'!O6,'Discount Rate'!A:B,2,) -> 0.07 | AC6: =Y6*AB6 -> 63 | AD6: =Y6-AB6-Z6 -> 899.78
A7: ORD-00006 | B7: CUST-470 | C7: REP-17 | D7: Maria Garcia | E7: Maria | F7: Garcia | G7: 45911 | H7: =YEAR(G7) -> 2025 | I7: =TEXT(G7,"mmmm") -> September | J7: =TEXT(G7,"dddd") -> Thursday | K7: 0.40836806 | L7: =HOUR(K7) -> 9 | M7: =MINUTE(K7) -> 48 | N7: =SECOND(K7) -> 3 | O7: Laptop | P7: Computers | Q7: 3 | R7: 1011.08 | S7: =VLOOKUP(O7,'Product-cost'!A:B,2,) -> 600 | T7: North America | U7: mariagarcia@techgadgetsco.com | W7: neutral | X7: =R7*Q7 -> 3033.24 | Y7: =S7*Q7 -> 1800 | Z7: =VLOOKUP(T7,Taxrate!A:B,2,FALSE) -> 0.07 | AA7: =X7*Z7 -> 212.3268 | AB7: =VLOOKUP('Sales Dataset'!O7,'Discount Rate'!A:B,2,) -> 0.05 | AC7: =Y7*AB7 -> 90 | AD7: =Y7-AB7-Z7 -> 1799.88
A8: ORD-00007 | B8: CUST-838 | C8: REP-13 | D8: Ahmed Khan | E8: Ahmed | F8: Khan | G8: 46150 | H8: =YEAR(G8) -> 2026 | I8: =TEXT(G8,"mmmm") -> May | J8: =TEXT(G8,"dddd") -> Friday | K8: 0.3878125 | L8: =HOUR(K8) -> 9 | M8: =MINUTE(K8) -> 18 | N8: =SECOND(K8) -> 27 | O8: Smartphone | P8: Mobile Devices | Q8: 12 | R8: 559.02 | S8: =VLOOKUP(O8,'Product-cost'!A:B,2,) -> 300 | T8: Africa | U8: ahmedkhan@sales.techg.com | W8: neutral | X8: =R8*Q8 -> 6708.24 | Y8: =S8*Q8 -> 3600 | Z8: =VLOOKUP(T8,Taxrate!A:B,2,FALSE) -> 0.12 | AA8: =X8*Z8 -> 804.9888 | AB8: =VLOOKUP('Sales Dataset'!O8,'Discount Rate'!A:B,2,) -> 0.1 | AC8: =Y8*AB8 -> 360 | AD8: =Y8-AB8-Z8 -> 3599.78
A9: ORD-00008 | B9: CUST-482 | C9: REP-15 | D9: Sophie Lee | E9: Sophie | F9: Lee | G9: 46013 | H9: =YEAR(G9) -> 2025 | I9: =TEXT(G9,"mmmm") -> December | J9: =TEXT(G9,"dddd") -> Monday | K9: 0.72258102 | L9: =HOUR(K9) -> 17 | M9: =MINUTE(K9) -> 20 | N9: =SECOND(K9) -> 31 | O9: Laptop | P9: Computers | Q9: 6 | R9: 1215.83 | S9: =VLOOKUP(O9,'Product-cost'!A:B,2,) -> 600 | T9: Asia | U9: sophielee@sales.techg.com | W9: neutral | X9: =R9*Q9 -> 7294.98 | Y9: =S9*Q9 -> 3600 | Z9: =VLOOKUP(T9,Taxrate!A:B,2,FALSE) -> 0.1 | AA9: =X9*Z9 -> 729.498 | AB9: =VLOOKUP('Sales Dataset'!O9,'Discount Rate'!A:B,2,) -> 0.05 | AC9: =Y9*AB9 -> 180 | AD9: =Y9-AB9-Z9 -> 3599.85
A10: ORD-00009 | B10: CUST-878 | C10: REP-33 | D10: Ahmed Khan | E10: Ahmed | F10: Khan | G10: 45189 | H10: =YEAR(G10) -> 2023 | I10: =TEXT(G10,"mmmm") -> September | J10: =TEXT(G10,"dddd") -> Wednesday | K10: 0.6737963 | L10: =HOUR(K10) -> 16 | M10: =MINUTE(K10) -> 10 | N10: =SECOND(K10) -> 16 | O10: Smartwatch | P10: Wearables | Q10: 7 | R10: 278.18 | S10: =VLOOKUP(O10,'Product-cost'!A:B,2,) -> 150 | T10: Europe | U10: ahmedkhan@sales.techg.com | V10: Fast Delivery | W10: positive | X10: =R10*Q10 -> 1947.26 | Y10: =S10*Q10 -> 1050 | Z10: =VLOOKUP(T10,Taxrate!A:B,2,FALSE) -> 0.2 | AA10: =X10*Z10 -> 389.452 | AB10: =VLOOKUP('Sales Dataset'!O10,'Discount Rate'!A:B,2,) -> 0.07 | AC10: =Y10*AB10 -> 73.5 | AD10: =Y10-AB10-Z10 -> 1049.73
A11: ORD-00010 | B11: CUST-330 | C11: REP-12 | D11: Olivia Patel | E11: Olivia | F11: Patel | G11: 44970 | H11: =YEAR(G11) -> 2023 | I11: =TEXT(G11,"mmmm") -> February | J11: =TEXT(G11,"dddd") -> Monday | K11: 0.71805556 | L11: =HOUR(K11) -> 17 | M11: =MINUTE(K11) -> 14 | N11: =SECOND(K11) -> 0 | O11: Laptop | P11: Computers | Q11: 1 | R11: 1252.71 | S11: =VLOOKUP(O11,'Product-cost'!A:B,2,) -> 600 | T11: Asia | U11: oliviapatel@tg.inc | V11: Packaging Was Damaged | W11: negative | X11: =R11*Q11 -> 1252.71 | Y11: =S11*Q11 -> 600 | Z11: =VLOOKUP(T11,Taxrate!A:B,2,FALSE) -> 0.1 | AA11: =X11*Z11 -> 125.271 | AB11: =VLOOKUP('Sales Dataset'!O11,'Discount Rate'!A:B,2,) -> 0.05 | AC11: =Y11*AB11 -> 30 | AD11: =Y11-AB11-Z11 -> 599.85
A12: ORD-00011 | B12: CUST-690 | C12: REP-29 | D12: Sophie Lee | E12: Sophie | F12: Lee | G12: 45895 | H12: =YEAR(G12) -> 2025 | I12: =TEXT(G12,"mmmm") -> August | J12: =TEXT(G12,"dddd") -> Tuesday | K12: 0.46256944 | L12: =HOUR(K12) -> 11 | M12: =MINUTE(K12) -> 6 | N12: =SECOND(K12) -> 6 | O12: Headphones | P12: Audio | Q12: 7 | R12: 174.68 | S12: =VLOOKUP(O12,'Product-cost'!A:B,2,) -> 50 | T12: North America | U12: sophielee@tg.inc | V12: Good Value For Money | W12: positive | X12: =R12*Q12 -> 1222.76 | Y12: =S12*Q12 -> 350 | Z12: =VLOOKUP(T12,Taxrate!A:B,2,FALSE) -> 0.07 | AA12: =X12*Z12 -> 85.5932 | AB12: =VLOOKUP('Sales Dataset'!O12,'Discount Rate'!A:B,2,) -> 0.03 | AC12: =Y12*AB12 -> 10.5 | AD12: =Y12-AB12-Z12 -> 349.9
A13: ORD-00012 | B13: CUST-532 | C13: REP-15 | D13: Sophie Lee | E13: Sophie | F13: Lee | G13: 45785 | H13: =YEAR(G13) -> 2025 | I13: =TEXT(G13,"mmmm") -> May | J13: =TEXT(G13,"dddd") -> Thursday | K13: 0.91601852 | L13: =HOUR(K13) -> 21 | M13: =MINUTE(K13) -> 59 | N13: =SECOND(K13) -> 4 | O13: Headphones | P13: Audio | Q13: 14 | R13: 123.79 | S13: =VLOOKUP(O13,'Product-cost'!A:B,2,) -> 50 | T13: Africa | U13: sophielee@tg.inc | V13: Very Satisfied | W13: positive | X13: =R13*Q13 -> 1733.06 | Y13: =S13*Q13 -> 700 | Z13: =VLOOKUP(T13,Taxrate!A:B,2,FALSE) -> 0.12 | AA13: =X13*Z13 -> 207.9672 | AB13: =VLOOKUP('Sales Dataset'!O13,'Discount Rate'!A:B,2,) -> 0.03 | AC13: =Y13*AB13 -> 21 | AD13: =Y13-AB13-Z13 -> 699.85
A14: ORD-00013 | B14: CUST-510 | C14: REP-11 | D14: Emma Dubois | E14: Emma | F14: Dubois | G14: 45703 | H14: =YEAR(G14) -> 2025 | I14: =TEXT(G14,"mmmm") -> February | J14: =TEXT(G14,"dddd") -> Saturday | K14: 0.59512731 | L14: =HOUR(K14) -> 14 | M14: =MINUTE(K14) -> 16 | N14: =SECOND(K14) -> 59 | O14: Headphones | P14: Audio | Q14: 12 | R14: 194.66 | S14: =VLOOKUP(O14,'Product-cost'!A:B,2,) -> 50 | T14: Africa | U14: emmadubois@tg.inc | V14: Packaging Was Damaged | W14: negative | X14: =R14*Q14 -> 2335.92 | Y14: =S14*Q14 -> 600 | Z14: =VLOOKUP(T14,Taxrate!A:B,2,FALSE) -> 0.12 | AA14: =X14*Z14 -> 280.3104 | AB14: =VLOOKUP('Sales Dataset'!O14,'Discount Rate'!A:B,2,) -> 0.03 | AC14: =Y14*AB14 -> 18 | AD14: =Y14-AB14-Z14 -> 599.85
A15: ORD-00014 | B15: CUST-865 | C15: REP-21 | D15: Fatima Adebayo | E15: Fatima | F15: Adebayo | G15: 45029 | H15: =YEAR(G15) -> 2023 | I15: =TEXT(G15,"mmmm") -> April | J15: =TEXT(G15,"dddd") -> Thursday | K15: 0.70756944 | L15: =HOUR(K15) -> 16 | M15: =MINUTE(K15) -> 58 | N15: =SECOND(K15) -> 54 | O15: Smartwatch | P15: Wearables | Q15: 9 | R15: 500 | S15: =VLOOKUP(O15,'Product-cost'!A:B,2,) -> 150 | T15: Europe | U15: fatimaadebayo@tg.inc | W15: neutral | X15: =R15*Q15 -> 4500 | Y15: =S15*Q15 -> 1350 | Z15: =VLOOKUP(T15,Taxrate!A:B,2,FALSE) -> 0.2 | AA15: =X15*Z15 -> 900 | AB15: =VLOOKUP('Sales Dataset'!O15,'Discount Rate'!A:B,2,) -> 0.07 | AC15: =Y15*AB15 -> 94.5 | AD15: =Y15-AB15-Z15 -> 1349.73
A16: ORD-00015 | B16: CUST-708 | C16: REP-11 | D16: Emma Dubois | E16: Emma | F16: Dubois | G16: 45094 | H16: =YEAR(G16) -> 2023 | I16: =TEXT(G16,"mmmm") -> June | J16: =TEXT(G16,"dddd") -> Saturday | K16: 0.77611111 | L16: =HOUR(K16) -> 18 | M16: =MINUTE(K16) -> 37 | N16: =SECOND(K16) -> 36 | O16: Smartwatch | P16: Wearables | Q16: 5 | R16: 254.78 | S16: =VLOOKUP(O16,'Product-cost'!A:B,2,) -> 150 | T16: Europe | U16: emmadubois@sales.techg.com | V16: Perfect Fit | W16: positive | X16: =R16*Q16 -> 1273.9 | Y16: =S16*Q16 -> 750 | Z16: =VLOOKUP(T16,Taxrate!A:B,2,FALSE) -> 0.2 | AA16: =X16*Z16 -> 254.78 | AB16: =VLOOKUP('Sales Dataset'!O16,'Discount Rate'!A:B,2,) -> 0.07 | AC16: =Y16*AB16 -> 52.5 | AD16: =Y16-AB16-Z16 -> 749.73
A17: ORD-00016 | B17: CUST-569 | C17: REP-35 | D17: Carlos Rodriguez | E17: Carlos | F17: Rodriguez | G17: 45131 | H17: =YEAR(G17) -> 2023 | I17: =TEXT(G17,"mmmm") -> July | J17: =TEXT(G17,"dddd") -> Monday | K17: 0.67606481 | L17: =HOUR(K17) -> 16 | M17: =MINUTE(K17) -> 13 | N17: =SECOND(K17) -> 32 | O17: Tablet | P17: Tablets | Q17: 6 | R17: 495.85 | S17: =VLOOKUP(O17,'Product-cost'!A:B,2,) -> 200 | T17: Asia | U17: carlosrodriguez@tg.inc | W17: neutral | X17: =R17*Q17 -> 2975.1 | Y17: =S17*Q17 -> 1200 | Z17: =VLOOKUP(T17,Taxrate!A:B,2,FALSE) -> 0.1 | AA17: =X17*Z17 -> 297.51 | AB17: =VLOOKUP('Sales Dataset'!O17,'Discount Rate'!A:B,2,) -> 0.08 | AC17: =Y17*AB17 -> 96 | AD17: =Y17-AB17-Z17 -> 1199.82
A18: ORD-00017 | B18: CUST-108 | C18: REP-33 | D18: Ahmed Khan | E18: Ahmed | F18: Khan | G18: 46285 | H18: =YEAR(G18) -> 2026 | I18: =TEXT(G18,"mmmm") -> September | J18: =TEXT(G18,"dddd") -> Sunday | K18: 0.4278588 | L18: =HOUR(K18) -> 10 | M18: =MINUTE(K18) -> 16 | N18: =SECOND(K18) -> 7 | O18: Laptop | P18: Computers | Q18: 3 | R18: 1102.41 | S18: =VLOOKUP(O18,'Product-cost'!A:B,2,) -> 600 | T18: Asia | U18: ahmedkhan@tg.inc | V18: Battery Life Amazing | W18: positive | X18: =R18*Q18 -> 3307.23 | Y18: =S18*Q18 -> 1800 | Z18: =VLOOKUP(T18,Taxrate!A:B,2,FALSE) -> 0.1 | AA18: =X18*Z18 -> 330.723 | AB18: =VLOOKUP('Sales Dataset'!O18,'Discount Rate'!A:B,2,) -> 0.05 | AC18: =Y18*AB18 -> 90 | AD18: =Y18-AB18-Z18 -> 1799.85
A19: ORD-00018 | B19: CUST-749 | C19: REP-24 | D19: Liam Chen | E19: Liam | F19: Chen | G19: 44930 | H19: =YEAR(G19) -> 2023 | I19: =TEXT(G19,"mmmm") -> January | J19: =TEXT(G19,"dddd") -> Wednesday | K19: 0.57578704 | L19: =HOUR(K19) -> 13 | M19: =MINUTE(K19) -> 49 | N19: =SECOND(K19) -> 8 | O19: Tablet | P19: Tablets | Q19: 8 | R19: 405.54 | S19: =VLOOKUP(O19,'Product-cost'!A:B,2,) -> 200 | T19: North America | U19: liamchen@sales.techg.com | V19: A Bit Expensive But Worth It | W19: neutral | X19: =R19*Q19 -> 3244.32 | Y19: =S19*Q19 -> 1600 | Z19: =VLOOKUP(T19,Taxrate!A:B,2,FALSE) -> 0.07 | AA19: =X19*Z19 -> 227.1024 | AB19: =VLOOKUP('Sales Dataset'!O19,'Discount Rate'!A:B,2,) -> 0.08 | AC19: =Y19*AB19 -> 128 | AD19: =Y19-AB19-Z19 -> 1599.85
A20: ORD-00019 | B20: CUST-251 | C20: REP-24 | D20: Liam Chen | E20: Liam | F20: Chen | G20: 45012 | H20: =YEAR(G20) -> 2023 | I20: =TEXT(G20,"mmmm") -> March | J20: =TEXT(G20,"dddd") -> Monday | K20: 0.58193287 | L20: =HOUR(K20) -> 13 | M20: =MINUTE(K20) -> 57 | N20: =SECOND(K20) -> 59 | O20: Laptop | P20: Computers | Q20: 4 | R20: 1133.47 | S20: =VLOOKUP(O20,'Product-cost'!A:B,2,) -> 600 | T20: Asia | U20: liamchen@techgadgetsco.com | V20: A Bit Expensive But Worth It | W20: neutral | X20: =R20*Q20 -> 4533.88 | Y20: =S20*Q20 -> 2400 | Z20: =VLOOKUP(T20,Taxrate!A:B,2,FALSE) -> 0.1 | AA20: =X20*Z20 -> 453.388 | AB20: =VLOOKUP('Sales Dataset'!O20,'Discount Rate'!A:B,2,) -> 0.05 | AC20: =Y20*AB20 -> 120 | AD20: =Y20-AB20-Z20 -> 2399.85
A21: ORD-00020 | B21: CUST-919 | C21: REP-15 | D21: Sophie Lee | E21: Sophie | F21: Lee | G21: 44977 | H21: =YEAR(G21) -> 2023 | I21: =TEXT(G21,"mmmm") -> February | J21: =TEXT(G21,"dddd") -> Monday | K21: 0.83288194 | L21: =HOUR(K21) -> 19 | M21: =MINUTE(K21) -> 59 | N21: =SECOND(K21) -> 21 | O21: Headphones | P21: Audio | Q21: 14 | R21: 138.61 | S21: =VLOOKUP(O21,'Product-cost'!A:B,2,) -> 50 | T21: Europe | U21: sophielee@tg.inc | V21: Battery Life Amazing | W21: positive | X21: =R21*Q21 -> 1940.54 | Y21: =S21*Q21 -> 700 | Z21: =VLOOKUP(T21,Taxrate!A:B,2,FALSE) -> 0.2 | AA21: =X21*Z21 -> 388.108 | AB21: =VLOOKUP('Sales Dataset'!O21,'Discount Rate'!A:B,2,) -> 0.03 | AC21: =Y21*AB21 -> 21 | AD21: =Y21-AB21-Z21 -> 699.77
A22: ORD-00021 | B22: CUST-412 | C22: REP-17 | D22: Maria Garcia | E22: Maria | F22: Garcia | G22: 44975 | H22: =YEAR(G22) -> 2023 | I22: =TEXT(G22,"mmmm") -> February | J22: =TEXT(G22,"dddd") -> Saturday | K22: 0.59811343 | L22: =HOUR(K22) -> 14 | M22: =MINUTE(K22) -> 21 | N22: =SECOND(K22) -> 17 | O22: Laptop | P22: Computers | Q22: 5 | R22: 1054.7 | S22: =VLOOKUP(O22,'Product-cost'!A:B,2,) -> 600 | T22: Africa | U22: mariagarcia@techgadgetsco.com | W22: neutral | X22: =R22*Q22 -> 5273.5 | Y22: =S22*Q22 -> 3000 | Z22: =VLOOKUP(T22,Taxrate!A:B,2,FALSE) -> 0.12 | AA22: =X22*Z22 -> 632.82 | AB22: =VLOOKUP('Sales Dataset'!O22,'Discount Rate'!A:B,2,) -> 0.05 | AC22: =Y22*AB22 -> 150 | AD22: =Y22-AB22-Z22 -> 2999.83
A23: ORD-00022 | B23: CUST-211 | C23: REP-35 | D23: Carlos Rodriguez | E23: Carlos | F23: Rodriguez | G23: 45516 | H23: =YEAR(G23) -> 2024 | I23: =TEXT(G23,"mmmm") -> August | J23: =TEXT(G23,"dddd") -> Monday | K23: 0.61009259 | L23: =HOUR(K23) -> 14 | M23: =MINUTE(K23) -> 38 | N23: =SECOND(K23) -> 32 | O23: Laptop | P23: Computers | Q23: 10 | R23: 822.19 | S23: =VLOOKUP(O23,'Product-cost'!A:B,2,) -> 600 | T23: South America | U23: carlosrodriguez@techgadgetsco.com | V23: Packaging Was Damaged | W23: negative | X23: =R23*Q23 -> 8221.9 | Y23: =S23*Q23 -> 6000 | Z23: =VLOOKUP(T23,Taxrate!A:B,2,FALSE) -> 0.15 | AA23: =X23*Z23 -> 1233.285 | AB23: =VLOOKUP('Sales Dataset'!O23,'Discount Rate'!A:B,2,) -> 0.05 | AC23: =Y23*AB23 -> 300 | AD23: =Y23-AB23-Z23 -> 5999.8
A24: ORD-00023 | B24: CUST-438 | C24: REP-35 | D24: Carlos Rodriguez | E24: Carlos | F24: Rodriguez | G24: 46285 | H24: =YEAR(G24) -> 2026 | I24: =TEXT(G24,"mmmm") -> September | J24: =TEXT(G24,"dddd") -> Sunday | K24: 0.83146991 | L24: =HOUR(K24) -> 19 | M24: =MINUTE(K24) -> 57 | N24: =SECOND(K24) -> 19 | O24: Smartwatch | P24: Wearables | Q24: 7 | R24: 252.69 | S24: =VLOOKUP(O24,'Product-cost'!A:B,2,) -> 150 | T24: Africa | U24: carlosrodriguez@techgadgetsco.com | V24: Fantastic Customer Service | W24: positive | X24: =R24*Q24 -> 1768.83 | Y24: =S24*Q24 -> 1050 | Z24: =VLOOKUP(T24,Taxrate!A:B,2,FALSE) -> 0.12 | AA24: =X24*Z24 -> 212.2596 | AB24: =VLOOKUP('Sales Dataset'!O24,'Discount Rate'!A:B,2,) -> 0.07 | AC24: =Y24*AB24 -> 73.5 | AD24: =Y24-AB24-Z24 -> 1049.81
A25: ORD-00024 | B25: CUST-100 | C25: REP-20 | D25: Sophie Lee | E25: Sophie | F25: Lee | G25: 45446 | H25: =YEAR(G25) -> 2024 | I25: =TEXT(G25,"mmmm") -> June | J25: =TEXT(G25,"dddd") -> Monday | K25: 0.85946759 | L25: =HOUR(K25) -> 20 | M25: =MINUTE(K25) -> 37 | N25: =SECOND(K25) -> 38 | O25: Tablet | P25: Tablets | Q25: 8 | R25: 422.23 | S25: =VLOOKUP(O25,'Product-cost'!A:B,2,) -> 200 | T25: Europe | U25: sophielee@sales.techg.com | W25: neutral | X25: =R25*Q25 -> 3377.84 | Y25: =S25*Q25 -> 1600 | Z25: =VLOOKUP(T25,Taxrate!A:B,2,FALSE) -> 0.2 | AA25: =X25*Z25 -> 675.568 | AB25: =VLOOKUP('Sales Dataset'!O25,'Discount Rate'!A:B,2,) -> 0.08 | AC25: =Y25*AB25 -> 128 | AD25: =Y25-AB25-Z25 -> 1599.72
A26: ORD-00025 | B26: CUST-417 | C26: REP-17 | D26: Maria Garcia | E26: Maria | F26: Garcia | G26: 45228 | H26: =YEAR(G26) -> 2023 | I26: =TEXT(G26,"mmmm") -> October | J26: =TEXT(G26,"dddd") -> Sunday | K26: 0.34409722 | L26: =HOUR(K26) -> 8 | M26: =MINUTE(K26) -> 15 | N26: =SECOND(K26) -> 30 | O26: Smartwatch | P26: Wearables | Q26: 2 | R26: 273.48 | S26: =VLOOKUP(O26,'Product-cost'!A:B,2,) -> 150 | T26: Africa | U26: mariagarcia@techgadgetsco.com | W26: neutral | X26: =R26*Q26 -> 546.96 | Y26: =S26*Q26 -> 300 | Z26: =VLOOKUP(T26,Taxrate!A:B,2,FALSE) -> 0.12 | AA26: =X26*Z26 -> 65.6352 | AB26: =VLOOKUP('Sales Dataset'!O26,'Discount Rate'!A:B,2,) -> 0.07 | AC26: =Y26*AB26 -> 21 | AD26: =Y26-AB26-Z26 -> 299.81
A27: ORD-00026 | B27: CUST-981 | C27: REP-13 | D27: Ahmed Khan | E27: Ahmed | F27: Khan | G27: 45375 | H27: =YEAR(G27) -> 2024 | I27: =TEXT(G27,"mmmm") -> March | J27: =TEXT(G27,"dddd") -> Sunday | K27: 0.86427083 | L27: =HOUR(K27) -> 20 | M27: =MINUTE(K27) -> 44 | N27: =SECOND(K27) -> 33 | O27: Headphones | P27: Audio | Q27: 7 | R27: 183.63 | S27: =VLOOKUP(O27,'Product-cost'!A:B,2,) -> 50 | T27: South America | U27: ahmedkhan@sales.techg.com | V27: Great Product | W27: positive | X27: =R27*Q27 -> 1285.41 | Y27: =S27*Q27 -> 350 | Z27: =VLOOKUP(T27,Taxrate!A:B,2,FALSE) -> 0.15 | AA27: =X27*Z27 -> 192.8115 | AB27: =VLOOKUP('Sales Dataset'!O27,'Discount Rate'!A:B,2,) -> 0.03 | AC27: =Y27*AB27 -> 10.5 | AD27: =Y27-AB27-Z27 -> 349.82
A28: ORD-00027 | B28: CUST-836 | C28: REP-32 | D28: Maria Garcia | E28: Maria | F28: Garcia | G28: 46049 | H28: =YEAR(G28) -> 2026 | I28: =TEXT(G28,"mmmm") -> January | J28: =TEXT(G28,"dddd") -> Tuesday | K28: 0.44994213 | L28: =HOUR(K28) -> 10 | M28: =MINUTE(K28) -> 47 | N28: =SECOND(K28) -> 55 | O28: Headphones | P28: Audio | Q28: 13 | R28: 167.82 | S28: =VLOOKUP(O28,'Product-cost'!A:B,2,) -> 50 | T28: Africa | U28: mariagarcia@techgadgetsco.com | W28: neutral | X28: =R28*Q28 -> 2181.66 | Y28: =S28*Q28 -> 650 | Z28: =VLOOKUP(T28,Taxrate!A:B,2,FALSE) -> 0.12 | AA28: =X28*Z28 -> 261.7992 | AB28: =VLOOKUP('Sales Dataset'!O28,'Discount Rate'!A:B,2,) -> 0.03 | AC28: =Y28*AB28 -> 19.5 | AD28: =Y28-AB28-Z28 -> 649.85
A29: ORD-00028 | B29: CUST-182 | C29: REP-14 | D29: Maria Garcia | E29: Maria | F29: Garcia | G29: 45400 | H29: =YEAR(G29) -> 2024 | I29: =TEXT(G29,"mmmm") -> April | J29: =TEXT(G29,"dddd") -> Thursday | K29: 0.7984375 | L29: =HOUR(K29) -> 19 | M29: =MINUTE(K29) -> 9 | N29: =SECOND(K29) -> 45 | O29: Smartphone | P29: Mobile Devices | Q29: 7 | R29: 642.78 | S29: =VLOOKUP(O29,'Product-cost'!A:B,2,) -> 300 | T29: South America | U29: mariagarcia@techgadgetsco.com | V29: Excellent Quality | W29: positive | X29: =R29*Q29 -> 4499.46 | Y29: =S29*Q29 -> 2100 | Z29: =VLOOKUP(T29,Taxrate!A:B,2,FALSE) -> 0.15 | AA29: =X29*Z29 -> 674.919 | AB29: =VLOOKUP('Sales Dataset'!O29,'Discount Rate'!A:B,2,) -> 0.1 | AC29: =Y29*AB29 -> 210 | AD29: =Y29-AB29-Z29 -> 2099.75
A30: ORD-00029 | B30: CUST-106 | C30: REP-22 | D30: Fatima Adebayo | E30: Fatima | F30: Adebayo | G30: 45903 | H30: =YEAR(G30) -> 2025 | I30: =TEXT(G30,"mmmm") -> September | J30: =TEXT(G30,"dddd") -> Wednesday | K30: 0.69984954 | L30: =HOUR(K30) -> 16 | M30: =MINUTE(K30) -> 47 | N30: =SECOND(K30) -> 47 | O30: Smartwatch | P30: Wearables | Q30: 15 | R30: 200.14 | S30: =VLOOKUP(O30,'Product-cost'!A:B,2,) -> 150 | T30: South America | U30: fatimaadebayo@sales.techg.com | V30: Highly Recommend | W30: positive | X30: =R30*Q30 -> 3002.1 | Y30: =S30*Q30 -> 2250 | Z30: =VLOOKUP(T30,Taxrate!A:B,2,FALSE) -> 0.15 | AA30: =X30*Z30 -> 450.315 | AB30: =VLOOKUP('Sales Dataset'!O30,'Discount Rate'!A:B,2,) -> 0.07 | AC30: =Y30*AB30 -> 157.5 | AD30: =Y30-AB30-Z30 -> 2249.78
A31: ORD-00030 | B31: CUST-737 | C31: REP-33 | D31: Ahmed Khan | E31: Ahmed | F31: Khan | G31: 45733 | H31: =YEAR(G31) -> 2025 | I31: =TEXT(G31,"mmmm") -> March | J31: =TEXT(G31,"dddd") -> Monday | K31: 0.40378472 | L31: =HOUR(K31) -> 9 | M31: =MINUTE(K31) -> 41 | N31: =SECOND(K31) -> 27 | O31: Smartphone | P31: Mobile Devices | Q31: 3 | R31: 500 | S31: =VLOOKUP(O31,'Product-cost'!A:B,2,) -> 300 | T31: South America | U31: ahmedkhan@sales.techg.com | V31: Highly Recommend | W31: positive | X31: =R31*Q31 -> 1500 | Y31: =S31*Q31 -> 900 | Z31: =VLOOKUP(T31,Taxrate!A:B,2,FALSE) -> 0.15 | AA31: =X31*Z31 -> 225 | AB31: =VLOOKUP('Sales Dataset'!O31,'Discount Rate'!A:B,2,) -> 0.1 | AC31: =Y31*AB31 -> 90 | AD31: =Y31-AB31-Z31 -> 899.75
A32: ORD-00031 | B32: CUST-954 | C32: REP-12 | D32: Olivia Patel | E32: Olivia | F32: Patel | G32: 45171 | H32: =YEAR(G32) -> 2023 | I32: =TEXT(G32,"mmmm") -> September | J32: =TEXT(G32,"dddd") -> Saturday | K32: 0.55186343 | L32: =HOUR(K32) -> 13 | M32: =MINUTE(K32) -> 14 | N32: =SECOND(K32) -> 41 | O32: Laptop | P32: Computers | Q32: 11 | R32: 500 | S32: =VLOOKUP(O32,'Product-cost'!A:B,2,) -> 600 | T32: North America | U32: oliviapatel@tg.inc | V32: A Bit Expensive But Worth It | W32: neutral | X32: =R32*Q32 -> 5500 | Y32: =S32*Q32 -> 6600 | Z32: =VLOOKUP(T32,Taxrate!A:B,2,FALSE) -> 0.07 | AA32: =X32*Z32 -> 385 | AB32: =VLOOKUP('Sales Dataset'!O32,'Discount Rate'!A:B,2,) -> 0.05 | AC32: =Y32*AB32 -> 330 | AD32: =Y32-AB32-Z32 -> 6599.88
A33: ORD-00032 | B33: CUST-323 | C33: REP-28 | D33: Maria Garcia | E33: Maria | F33: Garcia | G33: 45682 | H33: =YEAR(G33) -> 2025 | I33: =TEXT(G33,"mmmm") -> January | J33: =TEXT(G33,"dddd") -> Saturday | K33: 0.7352662 | L33: =HOUR(K33) -> 17 | M33: =MINUTE(K33) -> 38 | N33: =SECOND(K33) -> 47 | O33: Laptop | P33: Computers | Q33: 3 | R33: 854.05 | S33: =VLOOKUP(O33,'Product-cost'!A:B,2,) -> 600 | T33: North America | U33: mariagarcia@tg.inc | V33: Highly Recommend | W33: positive | X33: =R33*Q33 -> 2562.15 | Y33: =S33*Q33 -> 1800 | Z33: =VLOOKUP(T33,Taxrate!A:B,2,FALSE) -> 0.07 | AA33: =X33*Z33 -> 179.3505 | AB33: =VLOOKUP('Sales Dataset'!O33,'Discount Rate'!A:B,2,) -> 0.05 | AC33: =Y33*AB33 -> 90 | AD33: =Y33-AB33-Z33 -> 1799.88
A34: ORD-00033 | B34: CUST-807 | C34: REP-17 | D34: Maria Garcia | E34: Maria | F34: Garcia | G34: 46354 | H34: =YEAR(G34) -> 2026 | I34: =TEXT(G34,"mmmm") -> November | J34: =TEXT(G34,"dddd") -> Saturday | K34: 0.90530093 | L34: =HOUR(K34) -> 21 | M34: =MINUTE(K34) -> 43 | N34: =SECOND(K34) -> 38 | O34: Laptop | P34: Computers | Q34: 10 | R34: 973.6 | S34: =VLOOKUP(O34,'Product-cost'!A:B,2,) -> 600 | T34: South America | U34: mariagarcia@techgadgetsco.com | V34: Excellent Quality | W34: positive | X34: =R34*Q34 -> 9736 | Y34: =S34*Q34 -> 6000 | Z34: =VLOOKUP(T34,Taxrate!A:B,2,FALSE) -> 0.15 | AA34: =X34*Z34 -> 1460.4 | AB34: =VLOOKUP('Sales Dataset'!O34,'Discount Rate'!A:B,2,) -> 0.05 | AC34: =Y34*AB34 -> 300 | AD34: =Y34-AB34-Z34 -> 5999.8
A35: ORD-00034 | B35: CUST-470 | C35: REP-28 | D35: Maria Garcia | E35: Maria | F35: Garcia | G35: 45936 | H35: =YEAR(G35) -> 2025 | I35: =TEXT(G35,"mmmm") -> October | J35: =TEXT(G35,"dddd") -> Monday | K35: 0.81505787 | L35: =HOUR(K35) -> 19 | M35: =MINUTE(K35) -> 33 | N35: =SECOND(K35) -> 41 | O35: Tablet | P35: Tablets | Q35: 15 | R35: 416.7 | S35: =VLOOKUP(O35,'Product-cost'!A:B,2,) -> 200 | T35: South America | U35: mariagarcia@sales.techg.com | V35: Very Satisfied | W35: positive | X35: =R35*Q35 -> 6250.5 | Y35: =S35*Q35 -> 3000 | Z35: =VLOOKUP(T35,Taxrate!A:B,2,FALSE) -> 0.15 | AA35: =X35*Z35 -> 937.575 | AB35: =VLOOKUP('Sales Dataset'!O35,'Discount Rate'!A:B,2,) -> 0.08 | AC35: =Y35*AB35 -> 240 | AD35: =Y35-AB35-Z35 -> 2999.77
A36: ORD-00035 | B36: CUST-349 | C36: REP-28 | D36: Maria Garcia | E36: Maria | F36: Garcia | G36: 45615 | H36: =YEAR(G36) -> 2024 | I36: =TEXT(G36,"mmmm") -> November | J36: =TEXT(G36,"dddd") -> Tuesday | K36: 0.66273148 | L36: =HOUR(K36) -> 15 | M36: =MINUTE(K36) -> 54 | N36: =SECOND(K36) -> 20 | O36: Smartphone | P36: Mobile Devices | Q36: 6 | R36: 582.1 | S36: =VLOOKUP(O36,'Product-cost'!A:B,2,) -> 300 | T36: Africa | U36: mariagarcia@tg.inc | W36: neutral | X36: =R36*Q36 -> 3492.6 | Y36: =S36*Q36 -> 1800 | Z36: =VLOOKUP(T36,Taxrate!A:B,2,FALSE) -> 0.12 | AA36: =X36*Z36 -> 419.112 | AB36: =VLOOKUP('Sales Dataset'!O36,'Discount Rate'!A:B,2,) -> 0.1 | AC36: =Y36*AB36 -> 180 | AD36: =Y36-AB36-Z36 -> 1799.78
A37: ORD-00036 | B37: CUST-876 | C37: REP-17 | D37: Maria Garcia | E37: Maria | F37: Garcia | G37: 46249 | H37: =YEAR(G37) -> 2026 | I37: =TEXT(G37,"mmmm") -> August | J37: =TEXT(G37,"dddd") -> Saturday | K37: 0.6597338 | L37: =HOUR(K37) -> 15 | M37: =MINUTE(K37) -> 50 | N37: =SECOND(K37) -> 1 | O37: Laptop | P37: Computers | Q37: 7 | R37: 953.1 | S37: =VLOOKUP(O37,'Product-cost'!A:B,2,) -> 600 | T37: Africa | U37: mariagarcia@tg.inc | V37: Great Product | W37: positive | X37: =R37*Q37 -> 6671.7 | Y37: =S37*Q37 -> 4200 | Z37: =VLOOKUP(T37,Taxrate!A:B,2,FALSE) -> 0.12 | AA37: =X37*Z37 -> 800.604 | AB37: =VLOOKUP('Sales Dataset'!O37,'Discount Rate'!A:B,2,) -> 0.05 | AC37: =Y37*AB37 -> 210 | AD37: =Y37-AB37-Z37 -> 4199.83
A38: ORD-00037 | B38: CUST-336 | C38: REP-13 | D38: Ahmed Khan | E38: Ahmed | F38: Khan | G38: 45514 | H38: =YEAR(G38) -> 2024 | I38: =TEXT(G38,"mmmm") -> August | J38: =TEXT(G38,"dddd") -> Saturday | K38: 0.81583333 | L38: =HOUR(K38) -> 19 | M38: =MINUTE(K38) -> 34 | N38: =SECOND(K38) -> 48 | O38: Smartphone | P38: Mobile Devices | Q38: 12 | R38: 697.38 | S38: =VLOOKUP(O38,'Product-cost'!A:B,2,) -> 300 | T38: Africa | U38: ahmedkhan@tg.inc | W38: neutral | X38: =R38*Q38 -> 8368.56 | Y38: =S38*Q38 -> 3600 | Z38: =VLOOKUP(T38,Taxrate!A:B,2,FALSE) -> 0.12 | AA38: =X38*Z38 -> 1004.2272 | AB38: =VLOOKUP('Sales Dataset'!O38,'Discount Rate'!A:B,2,) -> 0.1 | AC38: =Y38*AB38 -> 360 | AD38: =Y38-AB38-Z38 -> 3599.78
A39: ORD-00038 | B39: CUST-646 | C39: REP-14 | D39: Maria Garcia | E39: Maria | F39: Garcia | G39: 45020 | H39: =YEAR(G39) -> 2023 | I39: =TEXT(G39,"mmmm") -> April | J39: =TEXT(G39,"dddd") -> Tuesday | K39: 0.67967593 | L39: =HOUR(K39) -> 16 | M39: =MINUTE(K39) -> 18 | N39: =SECOND(K39) -> 44 | O39: Smartphone | P39: Mobile Devices | Q39: 13 | R39: 741.82 | S39: =VLOOKUP(O39,'Product-cost'!A:B,2,) -> 300 | T39: Africa | U39: mariagarcia@sales.techg.com | V39: Quick Shipping | W39: positive | X39: =R39*Q39 -> 9643.66 | Y39: =S39*Q39 -> 3900 | Z39: =VLOOKUP(T39,Taxrate!A:B,2,FALSE) -> 0.12 | AA39: =X39*Z39 -> 1157.2392 | AB39: =VLOOKUP('Sales Dataset'!O39,'Discount Rate'!A:B,2,) -> 0.1 | AC39: =Y39*AB39 -> 390 | AD39: =Y39-AB39-Z39 -> 3899.78
A40: ORD-00039 | B40: CUST-166 | C40: REP-23 | D40: Noah Kim | E40: Noah | F40: Kim | G40: 44932 | H40: =YEAR(G40) -> 2023 | I40: =TEXT(G40,"mmmm") -> January | J40: =TEXT(G40,"dddd") -> Friday | K40: 0.42350694 | L40: =HOUR(K40) -> 10 | M40: =MINUTE(K40) -> 9 | N40: =SECOND(K40) -> 51 | O40: Smartwatch | P40: Wearables | Q40: 2 | R40: 189.03 | S40: =VLOOKUP(O40,'Product-cost'!A:B,2,) -> 150 | T40: South America | U40: noahkim@sales.techg.com | V40: Love The Design | W40: positive | X40: =R40*Q40 -> 378.06 | Y40: =S40*Q40 -> 300 | Z40: =VLOOKUP(T40,Taxrate!A:B,2,FALSE) -> 0.15 | AA40: =X40*Z40 -> 56.709 | AB40: =VLOOKUP('Sales Dataset'!O40,'Discount Rate'!A:B,2,) -> 0.07 | AC40: =Y40*AB40 -> 21 | AD40: =Y40-AB40-Z40 -> 299.78
A41: ORD-00040 | B41: CUST-702 | C41: REP-24 | D41: Liam Chen | E41: Liam | F41: Chen | G41: 46298 | H41: =YEAR(G41) -> 2026 | I41: =TEXT(G41,"mmmm") -> October | J41: =TEXT(G41,"dddd") -> Saturday | K41: 0.74104167 | L41: =HOUR(K41) -> 17 | M41: =MINUTE(K41) -> 47 | N41: =SECOND(K41) -> 6 | O41: Smartphone | P41: Mobile Devices | Q41: 5 | R41: 527.12 | S41: =VLOOKUP(O41,'Product-cost'!A:B,2,) -> 300 | T41: Europe | U41: liamchen@sales.techg.com | V41: Battery Life Amazing | W41: positive | X41: =R41*Q41 -> 2635.6 | Y41: =S41*Q41 -> 1500 | Z41: =VLOOKUP(T41,Taxrate!A:B,2,FALSE) -> 0.2 | AA41: =X41*Z41 -> 527.12 | AB41: =VLOOKUP('Sales Dataset'!O41,'Discount Rate'!A:B,2,) -> 0.1 | AC41: =Y41*AB41 -> 150 | AD41: =Y41-AB41-Z41 -> 1499.7
A42: ORD-00041 | B42: CUST-819 | C42: REP-28 | D42: Maria Garcia | E42: Maria | F42: Garcia | G42: 46245 | H42: =YEAR(G42) -> 2026 | I42: =TEXT(G42,"mmmm") -> August | J42: =TEXT(G42,"dddd") -> Tuesday | K42: 0.53530093 | L42: =HOUR(K42) -> 12 | M42: =MINUTE(K42) -> 50 | N42: =SECOND(K42) -> 50 | O42: Smartwatch | P42: Wearables | Q42: 15 | R42: 188.63 | S42: =VLOOKUP(O42,'Product-cost'!A:B,2,) -> 150 | T42: Europe | U42: mariagarcia@sales.techg.com | W42: neutral | X42: =R42*Q42 -> 2829.45 | Y42: =S42*Q42 -> 2250 | Z42: =VLOOKUP(T42,Taxrate!A:B,2,FALSE) -> 0.2 | AA42: =X42*Z42 -> 565.89 | AB42: =VLOOKUP('Sales Dataset'!O42,'Discount Rate'!A:B,2,) -> 0.07 | AC42: =Y42*AB42 -> 157.5 | AD42: =Y42-AB42-Z42 -> 2249.73
A43: ORD-00042 | B43: CUST-944 | C43: REP-34 | D43: Fatima Adebayo | E43: Fatima | F43: Adebayo | G43: 45826 | H43: =YEAR(G43) -> 2025 | I43: =TEXT(G43,"mmmm") -> June | J43: =TEXT(G43,"dddd") -> Wednesday | K43: 0.65577546 | L43: =HOUR(K43) -> 15 | M43: =MINUTE(K43) -> 44 | N43: =SECOND(K43) -> 19 | O43: Headphones | P43: Audio | Q43: 9 | R43: 152.83 | S43: =VLOOKUP(O43,'Product-cost'!A:B,2,) -> 50 | T43: Africa | U43: fatimaadebayo@sales.techg.com | W43: neutral | X43: =R43*Q43 -> 1375.47 | Y43: =S43*Q43 -> 450 | Z43: =VLOOKUP(T43,Taxrate!A:B,2,FALSE) -> 0.12 | AA43: =X43*Z43 -> 165.0564 | AB43: =VLOOKUP('Sales Dataset'!O43,'Discount Rate'!A:B,2,) -> 0.03 | AC43: =Y43*AB43 -> 13.5 | AD43: =Y43-AB43-Z43 -> 449.85
A44: ORD-00043 | B44: CUST-981 | C44: REP-34 | D44: Fatima Adebayo | E44: Fatima | F44: Adebayo | G44: 46244 | H44: =YEAR(G44) -> 2026 | I44: =TEXT(G44,"mmmm") -> August | J44: =TEXT(G44,"dddd") -> Monday | K44: 0.71027778 | L44: =HOUR(K44) -> 17 | M44: =MINUTE(K44) -> 2 | N44: =SECOND(K44) -> 48 | O44: Smartphone | P44: Mobile Devices | Q44: 11 | R44: 563.45 | S44: =VLOOKUP(O44,'Product-cost'!A:B,2,) -> 300 | T44: Africa | U44: fatimaadebayo@tg.inc | V44: Battery Life Amazing | W44: positive | X44: =R44*Q44 -> 6197.95 | Y44: =S44*Q44 -> 3300 | Z44: =VLOOKUP(T44,Taxrate!A:B,2,FALSE) -> 0.12 | AA44: =X44*Z44 -> 743.754 | AB44: =VLOOKUP('Sales Dataset'!O44,'Discount Rate'!A:B,2,) -> 0.1 | AC44: =Y44*AB44 -> 330 | AD44: =Y44-AB44-Z44 -> 3299.78
A45: ORD-00044 | B45: CUST-978 | C45: REP-15 | D45: Sophie Lee | E45: Sophie | F45: Lee | G45: 45770 | H45: =YEAR(G45) -> 2025 | I45: =TEXT(G45,"mmmm") -> April | J45: =TEXT(G45,"dddd") -> Wednesday | K45: 0.52945602 | L45: =HOUR(K45) -> 12 | M45: =MINUTE(K45) -> 42 | N45: =SECOND(K45) -> 25 | O45: Smartwatch | P45: Wearables | Q45: 7 | R45: 500 | S45: =VLOOKUP(O45,'Product-cost'!A:B,2,) -> 150 | T45: Asia | U45: sophielee@tg.inc | V45: Love The Design | W45: positive | X45: =R45*Q45 -> 3500 | Y45: =S45*Q45 -> 1050 | Z45: =VLOOKUP(T45,Taxrate!A:B,2,FALSE) -> 0.1 | AA45: =X45*Z45 -> 350 | AB45: =VLOOKUP('Sales Dataset'!O45,'Discount Rate'!A:B,2,) -> 0.07 | AC45: =Y45*AB45 -> 73.5 | AD45: =Y45-AB45-Z45 -> 1049.83
A46: ORD-00045 | B46: CUST-573 | C46: REP-24 | D46: Liam Chen | E46: Liam | F46: Chen | G46: 45311 | H46: =YEAR(G46) -> 2024 | I46: =TEXT(G46,"mmmm") -> January | J46: =TEXT(G46,"dddd") -> Saturday | K46: 0.74202546 | L46: =HOUR(K46) -> 17 | M46: =MINUTE(K46) -> 48 | N46: =SECOND(K46) -> 31 | O46: Headphones | P46: Audio | Q46: 4 | R46: 129.83 | S46: =VLOOKUP(O46,'Product-cost'!A:B,2,) -> 50 | T46: Asia | U46: liamchen@techgadgetsco.com | V46: Very Satisfied | W46: positive | X46: =R46*Q46 -> 519.32 | Y46: =S46*Q46 -> 200 | Z46: =VLOOKUP(T46,Taxrate!A:B,2,FALSE) -> 0.1 | AA46: =X46*Z46 -> 51.932 | AB46: =VLOOKUP('Sales Dataset'!O46,'Discount Rate'!A:B,2,) -> 0.03 | AC46: =Y46*AB46 -> 6 | AD46: =Y46-AB46-Z46 -> 199.87
A47: ORD-00046 | B47: CUST-517 | C47: REP-12 | D47: Olivia Patel | E47: Olivia | F47: Patel | G47: 45159 | H47: =YEAR(G47) -> 2023 | I47: =TEXT(G47,"mmmm") -> August | J47: =TEXT(G47,"dddd") -> Monday | K47: 0.40408565 | L47: =HOUR(K47) -> 9 | M47: =MINUTE(K47) -> 41 | N47: =SECOND(K47) -> 53 | O47: Smartphone | P47: Mobile Devices | Q47: 12 | R47: 691.62 | S47: =VLOOKUP(O47,'Product-cost'!A:B,2,) -> 300 | T47: South America | U47: oliviapatel@techgadgetsco.com | V47: A Bit Expensive But Worth It | W47: neutral | X47: =R47*Q47 -> 8299.44 | Y47: =S47*Q47 -> 3600 | Z47: =VLOOKUP(T47,Taxrate!A:B,2,FALSE) -> 0.15 | AA47: =X47*Z47 -> 1244.916 | AB47: =VLOOKUP('Sales Dataset'!O47,'Discount Rate'!A:B,2,) -> 0.1 | AC47: =Y47*AB47 -> 360 | AD47: =Y47-AB47-Z47 -> 3599.75
A48: ORD-00047 | B48: CUST-239 | C48: REP-12 | D48: Olivia Patel | E48: Olivia | F48: Patel | G48: 45776 | H48: =YEAR(G48) -> 2025 | I48: =TEXT(G48,"mmmm") -> April | J48: =TEXT(G48,"dddd") -> Tuesday | K48: 0.85575231 | L48: =HOUR(K48) -> 20 | M48: =MINUTE(K48) -> 32 | N48: =SECOND(K48) -> 17 | O48: Laptop | P48: Computers | Q48: 5 | R48: 1089.96 | S48: =VLOOKUP(O48,'Product-cost'!A:B,2,) -> 600 | T48: South America | U48: oliviapatel@tg.inc | V48: Great Product | W48: positive | X48: =R48*Q48 -> 5449.8 | Y48: =S48*Q48 -> 3000 | Z48: =VLOOKUP(T48,Taxrate!A:B,2,FALSE) -> 0.15 | AA48: =X48*Z48 -> 817.47 | AB48: =VLOOKUP('Sales Dataset'!O48,'Discount Rate'!A:B,2,) -> 0.05 | AC48: =Y48*AB48 -> 150 | AD48: =Y48-AB48-Z48 -> 2999.8
A49: ORD-00048 | B49: CUST-429 | C49: REP-16 | D49: Sophie Lee | E49: Sophie | F49: Lee | G49: 46098 | H49: =YEAR(G49) -> 2026 | I49: =TEXT(G49,"mmmm") -> March | J49: =TEXT(G49,"dddd") -> Tuesday | K49: 0.49640046 | L49: =HOUR(K49) -> 11 | M49: =MINUTE(K49) -> 54 | N49: =SECOND(K49) -> 49 | O49: Headphones | P49: Audio | Q49: 7 | R49: 172.89 | S49: =VLOOKUP(O49,'Product-cost'!A:B,2,) -> 50 | T49: South America | U49: sophielee@sales.techg.com | V49: A Bit Expensive But Worth It | W49: neutral | X49: =R49*Q49 -> 1210.23 | Y49: =S49*Q49 -> 350 | Z49: =VLOOKUP(T49,Taxrate!A:B,2,FALSE) -> 0.15 | AA49: =X49*Z49 -> 181.5345 | AB49: =VLOOKUP('Sales Dataset'!O49,'Discount Rate'!A:B,2,) -> 0.03 | AC49: =Y49*AB49 -> 10.5 | AD49: =Y49-AB49-Z49 -> 349.82
A50: ORD-00049 | B50: CUST-704 | C50: REP-21 | D50: Fatima Adebayo | E50: Fatima | F50: Adebayo | G50: 45828 | H50: =YEAR(G50) -> 2025 | I50: =TEXT(G50,"mmmm") -> June | J50: =TEXT(G50,"dddd") -> Friday | K50: 0.70728009 | L50: =HOUR(K50) -> 16 | M50: =MINUTE(K50) -> 58 | N50: =SECOND(K50) -> 29 | O50: Laptop | P50: Computers | Q50: 7 | R50: 1284.98 | S50: =VLOOKUP(O50,'Product-cost'!A:B,2,) -> 600 | T50: North America | U50: fatimaadebayo@tg.inc | V50: Highly Recommend | W50: positive | X50: =R50*Q50 -> 8994.86 | Y50: =S50*Q50 -> 4200 | Z50: =VLOOKUP(T50,Taxrate!A:B,2,FALSE) -> 0.07 | AA50: =X50*Z50 -> 629.6402 | AB50: =VLOOKUP('Sales Dataset'!O50,'Discount Rate'!A:B,2,) -> 0.05 | AC50: =Y50*AB50 -> 210 | AD50: =Y50-AB50-Z50 -> 4199.88
A51: ORD-00050 | B51: CUST-979 | C51: REP-33 | D51: Ahmed Khan | E51: Ahmed | F51: Khan | G51: 45575 | H51: =YEAR(G51) -> 2024 | I51: =TEXT(G51,"mmmm") -> October | J51: =TEXT(G51,"dddd") -> Thursday | K51: 0.89863426 | L51: =HOUR(K51) -> 21 | M51: =MINUTE(K51) -> 34 | N51: =SECOND(K51) -> 2 | O51: Smartwatch | P51: Wearables | Q51: 7 | R51: 277.3 | S51: =VLOOKUP(O51,'Product-cost'!A:B,2,) -> 150 | T51: Europe | U51: ahmedkhan@tg.inc | V51: Good Value For Money | W51: positive | X51: =R51*Q51 -> 1941.1 | Y51: =S51*Q51 -> 1050 | Z51: =VLOOKUP(T51,Taxrate!A:B,2,FALSE) -> 0.2 | AA51: =X51*Z51 -> 388.22 | AB51: =VLOOKUP('Sales Dataset'!O51,'Discount Rate'!A:B,2,) -> 0.07 | AC51: =Y51*AB51 -> 73.5 | AD51: =Y51-AB51-Z51 -> 1049.73
A52: ORD-00051 | B52: CUST-147 | C52: REP-21 | D52: Fatima Adebayo | E52: Fatima | F52: Adebayo | G52: 45527 | H52: =YEAR(G52) -> 2024 | I52: =TEXT(G52,"mmmm") -> August | J52: =TEXT(G52,"dddd") -> Friday | K52: 0.56052083 | L52: =HOUR(K52) -> 13 | M52: =MINUTE(K52) -> 27 | N52: =SECOND(K52) -> 9 | O52: Smartphone | P52: Mobile Devices | Q52: 10 | R52: 534.02 | S52: =VLOOKUP(O52,'Product-cost'!A:B,2,) -> 300 | T52: Europe | U52: fatimaadebayo@tg.inc | V52: Very Satisfied | W52: positive | X52: =R52*Q52 -> 5340.2 | Y52: =S52*Q52 -> 3000 | Z52: =VLOOKUP(T52,Taxrate!A:B,2,FALSE) -> 0.2 | AA52: =X52*Z52 -> 1068.04 | AB52: =VLOOKUP('Sales Dataset'!O52,'Discount Rate'!A:B,2,) -> 0.1 | AC52: =Y52*AB52 -> 300 | AD52: =Y52-AB52-Z52 -> 2999.7
A53: ORD-00052 | B53: CUST-753 | C53: REP-18 | D53: Noah Kim | E53: Noah | F53: Kim | G53: 45449 | H53: =YEAR(G53) -> 2024 | I53: =TEXT(G53,"mmmm") -> June | J53: =TEXT(G53,"dddd") -> Thursday | K53: 0.85413194 | L53: =HOUR(K53) -> 20 | M53: =MINUTE(K53) -> 29 | N53: =SECOND(K53) -> 57 | O53: Tablet | P53: Tablets | Q53: 3 | R53: 500 | S53: =VLOOKUP(O53,'Product-cost'!A:B,2,) -> 200 | T53: Asia | U53: noahkim@sales.techg.com | W53: neutral | X53: =R53*Q53 -> 1500 | Y53: =S53*Q53 -> 600 | Z53: =VLOOKUP(T53,Taxrate!A:B,2,FALSE) -> 0.1 | AA53: =X53*Z53 -> 150 | AB53: =VLOOKUP('Sales Dataset'!O53,'Discount Rate'!A:B,2,) -> 0.08 | AC53: =Y53*AB53 -> 48 | AD53: =Y53-AB53-Z53 -> 599.82
A54: ORD-00053 | B54: CUST-973 | C54: REP-29 | D54: Sophie Lee | E54: Sophie | F54: Lee | G54: 45412 | H54: =YEAR(G54) -> 2024 | I54: =TEXT(G54,"mmmm") -> April | J54: =TEXT(G54,"dddd") -> Tuesday | K54: 0.72402778 | L54: =HOUR(K54) -> 17 | M54: =MINUTE(K54) -> 22 | N54: =SECOND(K54) -> 36 | O54: Tablet | P54: Tablets | Q54: 5 | R54: 500 | S54: =VLOOKUP(O54,'Product-cost'!A:B,2,) -> 200 | T54: South America | U54: sophielee@tg.inc | V54: Quick Shipping | W54: positive | X54: =R54*Q54 -> 2500 | Y54: =S54*Q54 -> 1000 | Z54: =VLOOKUP(T54,Taxrate!A:B,2,FALSE) -> 0.15 | AA54: =X54*Z54 -> 375 | AB54: =VLOOKUP('Sales Dataset'!O54,'Discount Rate'!A:B,2,) -> 0.08 | AC54: =Y54*AB54 -> 80 | AD54: =Y54-AB54-Z54 -> 999.77
A55: ORD-00054 | B55: CUST-393 | C55: REP-17 | D55: Maria Garcia | E55: Maria | F55: Garcia | G55: 45375 | H55: =YEAR(G55) -> 2024 | I55: =TEXT(G55,"mmmm") -> March | J55: =TEXT(G55,"dddd") -> Sunday | K55: 0.71994213 | L55: =HOUR(K55) -> 17 | M55: =MINUTE(K55) -> 16 | N55: =SECOND(K55) -> 43 | O55: Smartphone | P55: Mobile Devices | Q55: 15 | R55: 491.83 | S55: =VLOOKUP(O55,'Product-cost'!A:B,2,) -> 300 | T55: South America | U55: mariagarcia@tg.inc | W55: neutral | X55: =R55*Q55 -> 7377.45 | Y55: =S55*Q55 -> 4500 | Z55: =VLOOKUP(T55,Taxrate!A:B,2,FALSE) -> 0.15 | AA55: =X55*Z55 -> 1106.6175 | AB55: =VLOOKUP('Sales Dataset'!O55,'Discount Rate'!A:B,2,) -> 0.1 | AC55: =Y55*AB55 -> 450 | AD55: =Y55-AB55-Z55 -> 4499.75
A56: ORD-00055 | B56: CUST-905 | C56: REP-33 | D56: Ahmed Khan | E56: Ahmed | F56: Khan | G56: 46014 | H56: =YEAR(G56) -> 2025 | I56: =TEXT(G56,"mmmm") -> December | J56: =TEXT(G56,"dddd") -> Tuesday | K56: 0.88212963 | L56: =HOUR(K56) -> 21 | M56: =MINUTE(K56) -> 10 | N56: =SECOND(K56) -> 16 | O56: Headphones | P56: Audio | Q56: 5 | R56: 145.4 | S56: =VLOOKUP(O56,'Product-cost'!A:B,2,) -> 50 | T56: North America | U56: ahmedkhan@tg.inc | V56: Very Satisfied | W56: positive | X56: =R56*Q56 -> 727 | Y56: =S56*Q56 -> 250 | Z56: =VLOOKUP(T56,Taxrate!A:B,2,FALSE) -> 0.07 | AA56: =X56*Z56 -> 50.89 | AB56: =VLOOKUP('Sales Dataset'!O56,'Discount Rate'!A:B,2,) -> 0.03 | AC56: =Y56*AB56 -> 7.5 | AD56: =Y56-AB56-Z56 -> 249.9
A57: ORD-00056 | B57: CUST-966 | C57: REP-33 | D57: Ahmed Khan | E57: Ahmed | F57: Khan | G57: 45023 | H57: =YEAR(G57) -> 2023 | I57: =TEXT(G57,"mmmm") -> April | J57: =TEXT(G57,"dddd") -> Friday | K57: 0.34483796 | L57: =HOUR(K57) -> 8 | M57: =MINUTE(K57) -> 16 | N57: =SECOND(K57) -> 34 | O57: Laptop | P57: Computers | Q57: 11 | R57: 931.08 | S57: =VLOOKUP(O57,'Product-cost'!A:B,2,) -> 600 | T57: South America | U57: ahmedkhan@tg.inc | V57: Very Satisfied | W57: positive | X57: =R57*Q57 -> 10241.88 | Y57: =S57*Q57 -> 6600 | Z57: =VLOOKUP(T57,Taxrate!A:B,2,FALSE) -> 0.15 | AA57: =X57*Z57 -> 1536.282 | AB57: =VLOOKUP('Sales Dataset'!O57,'Discount Rate'!A:B,2,) -> 0.05 | AC57: =Y57*AB57 -> 330 | AD57: =Y57-AB57-Z57 -> 6599.8
A58: ORD-00057 | B58: CUST-435 | C58: REP-35 | D58: Carlos Rodriguez | E58: Carlos | F58: Rodriguez | G58: 46253 | H58: =YEAR(G58) -> 2026 | I58: =TEXT(G58,"mmmm") -> August | J58: =TEXT(G58,"dddd") -> Wednesday | K58: 0.78644676 | L58: =HOUR(K58) -> 18 | M58: =MINUTE(K58) -> 52 | N58: =SECOND(K58) -> 29 | O58: Tablet | P58: Tablets | Q58: 2 | R58: 509.25 | S58: =VLOOKUP(O58,'Product-cost'!A:B,2,) -> 200 | T58: Asia | U58: carlosrodriguez@sales.techg.com | V58: A Bit Expensive But Worth It | W58: neutral | X58: =R58*Q58 -> 1018.5 | Y58: =S58*Q58 -> 400 | Z58: =VLOOKUP(T58,Taxrate!A:B,2,FALSE) -> 0.1 | AA58: =X58*Z58 -> 101.85 | AB58: =VLOOKUP('Sales Dataset'!O58,'Discount Rate'!A:B,2,) -> 0.08 | AC58: =Y58*AB58 -> 32 | AD58: =Y58-AB58-Z58 -> 399.82
A59: ORD-00058 | B59: CUST-813 | C59: REP-33 | D59: Ahmed Khan | E59: Ahmed | F59: Khan | G59: 46129 | H59: =YEAR(G59) -> 2026 | I59: =TEXT(G59,"mmmm") -> April | J59: =TEXT(G59,"dddd") -> Friday | K59: 0.611875 | L59: =HOUR(K59) -> 14 | M59: =MINUTE(K59) -> 41 | N59: =SECOND(K59) -> 6 | O59: Headphones | P59: Audio | Q59: 5 | R59: 500 | S59: =VLOOKUP(O59,'Product-cost'!A:B,2,) -> 50 | T59: Asia | U59: ahmedkhan@tg.inc | W59: neutral | X59: =R59*Q59 -> 2500 | Y59: =S59*Q59 -> 250 | Z59: =VLOOKUP(T59,Taxrate!A:B,2,FALSE) -> 0.1 | AA59: =X59*Z59 -> 250 | AB59: =VLOOKUP('Sales Dataset'!O59,'Discount Rate'!A:B,2,) -> 0.03 | AC59: =Y59*AB59 -> 7.5 | AD59: =Y59-AB59-Z59 -> 249.87
A60: ORD-00059 | B60: CUST-760 | C60: REP-22 | D60: Fatima Adebayo | E60: Fatima | F60: Adebayo | G60: 45742 | H60: =YEAR(G60) -> 2025 | I60: =TEXT(G60,"mmmm") -> March | J60: =TEXT(G60,"dddd") -> Wednesday | K60: 0.46381944 | L60: =HOUR(K60) -> 11 | M60: =MINUTE(K60) -> 7 | N60: =SECOND(K60) -> 54 | O60: Headphones | P60: Audio | Q60: 7 | R60: 167.96 | S60: =VLOOKUP(O60,'Product-cost'!A:B,2,) -> 50 | T60: North America | U60: fatimaadebayo@tg.inc | W60: neutral | X60: =R60*Q60 -> 1175.72 | Y60: =S60*Q60 -> 350 | Z60: =VLOOKUP(T60,Taxrate!A:B,2,FALSE) -> 0.07 | AA60: =X60*Z60 -> 82.3004 | AB60: =VLOOKUP('Sales Dataset'!O60,'Discount Rate'!A:B,2,) -> 0.03 | AC60: =Y60*AB60 -> 10.5 | AD60: =Y60-AB60-Z60 -> 349.9
A61: ORD-00060 | B61: CUST-321 | C61: REP-17 | D61: Maria Garcia | E61: Maria | F61: Garcia | G61: 45229 | H61: =YEAR(G61) -> 2023 | I61: =TEXT(G61,"mmmm") -> October | J61: =TEXT(G61,"dddd") -> Monday | K61: 0.53760417 | L61: =HOUR(K61) -> 12 | M61: =MINUTE(K61) -> 54 | N61: =SECOND(K61) -> 9 | O61: Smartphone | P61: Mobile Devices | Q61: 13 | R61: 678.32 | S61: =VLOOKUP(O61,'Product-cost'!A:B,2,) -> 300 | T61: North America | U61: mariagarcia@tg.inc | W61: neutral | X61: =R61*Q61 -> 8818.16 | Y61: =S61*Q61 -> 3900 | Z61: =VLOOKUP(T61,Taxrate!A:B,2,FALSE) -> 0.07 | AA61: =X61*Z61 -> 617.2712 | AB61: =VLOOKUP('Sales Dataset'!O61,'Discount Rate'!A:B,2,) -> 0.1 | AC61: =Y61*AB61 -> 390 | AD61: =Y61-AB61-Z61 -> 3899.83
A62: ORD-00061 | B62: CUST-531 | C62: REP-32 | D62: Maria Garcia | E62: Maria | F62: Garcia | G62: 45235 | H62: =YEAR(G62) -> 2023 | I62: =TEXT(G62,"mmmm") -> November | J62: =TEXT(G62,"dddd") -> Sunday | K62: 0.65929398 | L62: =HOUR(K62) -> 15 | M62: =MINUTE(K62) -> 49 | N62: =SECOND(K62) -> 23 | O62: Smartwatch | P62: Wearables | Q62: 8 | R62: 280 | S62: =VLOOKUP(O62,'Product-cost'!A:B,2,) -> 150 | T62: North America | U62: mariagarcia@tg.inc | W62: neutral | X62: =R62*Q62 -> 2240 | Y62: =S62*Q62 -> 1200 | Z62: =VLOOKUP(T62,Taxrate!A:B,2,FALSE) -> 0.07 | AA62: =X62*Z62 -> 156.8 | AB62: =VLOOKUP('Sales Dataset'!O62,'Discount Rate'!A:B,2,) -> 0.07 | AC62: =Y62*AB62 -> 84 | AD62: =Y62-AB62-Z62 -> 1199.86
A63: ORD-00062 | B63: CUST-590 | C63: REP-23 | D63: Noah Kim | E63: Noah | F63: Kim | G63: 46184 | H63: =YEAR(G63) -> 2026 | I63: =TEXT(G63,"mmmm") -> June | J63: =TEXT(G63,"dddd") -> Thursday | K63: 0.6569213 | L63: =HOUR(K63) -> 15 | M63: =MINUTE(K63) -> 45 | N63: =SECOND(K63) -> 58 | O63: Headphones | P63: Audio | Q63: 7 | R63: 500 | S63: =VLOOKUP(O63,'Product-cost'!A:B,2,) -> 50 | T63: Africa | U63: noahkim@sales.techg.com | V63: Great Product | W63: positive | X63: =R63*Q63 -> 3500 | Y63: =S63*Q63 -> 350 | Z63: =VLOOKUP(T63,Taxrate!A:B,2,FALSE) -> 0.12 | AA63: =X63*Z63 -> 420 | AB63: =VLOOKUP('Sales Dataset'!O63,'Discount Rate'!A:B,2,) -> 0.03 | AC63: =Y63*AB63 -> 10.5 | AD63: =Y63-AB63-Z63 -> 349.85
A64: ORD-00063 | B64: CUST-617 | C64: REP-35 | D64: Carlos Rodriguez | E64: Carlos | F64: Rodriguez | G64: 45130 | H64: =YEAR(G64) -> 2023 | I64: =TEXT(G64,"mmmm") -> July | J64: =TEXT(G64,"dddd") -> Sunday | K64: 0.90394676 | L64: =HOUR(K64) -> 21 | M64: =MINUTE(K64) -> 41 | N64: =SECOND(K64) -> 41 | O64: Smartwatch | P64: Wearables | Q64: 4 | R64: 273.69 | S64: =VLOOKUP(O64,'Product-cost'!A:B,2,) -> 150 | T64: South America | U64: carlosrodriguez@techgadgetsco.com | V64: Good Value For Money | W64: positive | X64: =R64*Q64 -> 1094.76 | Y64: =S64*Q64 -> 600 | Z64: =VLOOKUP(T64,Taxrate!A:B,2,FALSE) -> 0.15 | AA64: =X64*Z64 -> 164.214 | AB64: =VLOOKUP('Sales Dataset'!O64,'Discount Rate'!A:B,2,) -> 0.07 | AC64: =Y64*AB64 -> 42 | AD64: =Y64-AB64-Z64 -> 599.78
A65: ORD-00064 | B65: CUST-256 | C65: REP-29 | D65: Sophie Lee | E65: Sophie | F65: Lee | G65: 45084 | H65: =YEAR(G65) -> 2023 | I65: =TEXT(G65,"mmmm") -> June | J65: =TEXT(G65,"dddd") -> Wednesday | K65: 0.39381944 | L65: =HOUR(K65) -> 9 | M65: =MINUTE(K65) -> 27 | N65: =SECOND(K65) -> 6 | O65: Tablet | P65: Tablets | Q65: 9 | R65: 500 | S65: =VLOOKUP(O65,'Product-cost'!A:B,2,) -> 200 | T65: Africa | U65: sophielee@tg.inc | V65: Not As Expected | W65: negative | X65: =R65*Q65 -> 4500 | Y65: =S65*Q65 -> 1800 | Z65: =VLOOKUP(T65,Taxrate!A:B,2,FALSE) -> 0.12 | AA65: =X65*Z65 -> 540 | AB65: =VLOOKUP('Sales Dataset'!O65,'Discount Rate'!A:B,2,) -> 0.08 | AC65: =Y65*AB65 -> 144 | AD65: =Y65-AB65-Z65 -> 1799.8
A66: ORD-00065 | B66: CUST-714 | C66: REP-20 | D66: Sophie Lee | E66: Sophie | F66: Lee | G66: 44934 | H66: =YEAR(G66) -> 2023 | I66: =TEXT(G66,"mmmm") -> January | J66: =TEXT(G66,"dddd") -> Sunday | K66: 0.44618056 | L66: =HOUR(K66) -> 10 | M66: =MINUTE(K66) -> 42 | N66: =SECOND(K66) -> 30 | O66: Smartphone | P66: Mobile Devices | Q66: 6 | R66: 590.27 | S66: =VLOOKUP(O66,'Product-cost'!A:B,2,) -> 300 | T66: Asia | U66: sophielee@sales.techg.com | V66: Excellent Quality | W66: positive | X66: =R66*Q66 -> 3541.62 | Y66: =S66*Q66 -> 1800 | Z66: =VLOOKUP(T66,Taxrate!A:B,2,FALSE) -> 0.1 | AA66: =X66*Z66 -> 354.162 | AB66: =VLOOKUP('Sales Dataset'!O66,'Discount Rate'!A:B,2,) -> 0.1 | AC66: =Y66*AB66 -> 180 | AD66: =Y66-AB66-Z66 -> 1799.8
A67: ORD-00066 | B67: CUST-129 | C67: REP-15 | D67: Sophie Lee | E67: Sophie | F67: Lee | G67: 46307 | H67: =YEAR(G67) -> 2026 | I67: =TEXT(G67,"mmmm") -> October | J67: =TEXT(G67,"dddd") -> Monday | K67: 0.55694444 | L67: =HOUR(K67) -> 13 | M67: =MINUTE(K67) -> 22 | N67: =SECOND(K67) -> 0 | O67: Smartphone | P67: Mobile Devices | Q67: 10 | R67: 500.88 | S67: =VLOOKUP(O67,'Product-cost'!A:B,2,) -> 300 | T67: North America | U67: sophielee@tg.inc | V67: Perfect Fit | W67: positive | X67: =R67*Q67 -> 5008.8 | Y67: =S67*Q67 -> 3000 | Z67: =VLOOKUP(T67,Taxrate!A:B,2,FALSE) -> 0.07 | AA67: =X67*Z67 -> 350.616 | AB67: =VLOOKUP('Sales Dataset'!O67,'Discount Rate'!A:B,2,) -> 0.1 | AC67: =Y67*AB67 -> 300 | AD67: =Y67-AB67-Z67 -> 2999.83
A68: ORD-00067 | B68: CUST-895 | C68: REP-34 | D68: Fatima Adebayo | E68: Fatima | F68: Adebayo | G68: 45034 | H68: =YEAR(G68) -> 2023 | I68: =TEXT(G68,"mmmm") -> April | J68: =TEXT(G68,"dddd") -> Tuesday | K68: 0.45045139 | L68: =HOUR(K68) -> 10 | M68: =MINUTE(K68) -> 48 | N68: =SECOND(K68) -> 39 | O68: Laptop | P68: Computers | Q68: 5 | R68: 1012.01 | S68: =VLOOKUP(O68,'Product-cost'!A:B,2,) -> 600 | T68: Africa | U68: fatimaadebayo@tg.inc | V68: Good Value For Money | W68: positive | X68: =R68*Q68 -> 5060.05 | Y68: =S68*Q68 -> 3000 | Z68: =VLOOKUP(T68,Taxrate!A:B,2,FALSE) -> 0.12 | AA68: =X68*Z68 -> 607.206 | AB68: =VLOOKUP('Sales Dataset'!O68,'Discount Rate'!A:B,2,) -> 0.05 | AC68: =Y68*AB68 -> 150 | AD68: =Y68-AB68-Z68 -> 2999.83
A69: ORD-00068 | B69: CUST-707 | C69: REP-29 | D69: Sophie Lee | E69: Sophie | F69: Lee | G69: 45020 | H69: =YEAR(G69) -> 2023 | I69: =TEXT(G69,"mmmm") -> April | J69: =TEXT(G69,"dddd") -> Tuesday | K69: 0.60975694 | L69: =HOUR(K69) -> 14 | M69: =MINUTE(K69) -> 38 | N69: =SECOND(K69) -> 3 | O69: Laptop | P69: Computers | Q69: 4 | R69: 1182.08 | S69: =VLOOKUP(O69,'Product-cost'!A:B,2,) -> 600 | T69: Asia | U69: sophielee@techgadgetsco.com | W69: neutral | X69: =R69*Q69 -> 4728.32 | Y69: =S69*Q69 -> 2400 | Z69: =VLOOKUP(T69,Taxrate!A:B,2,FALSE) -> 0.1 | AA69: =X69*Z69 -> 472.832 | AB69: =VLOOKUP('Sales Dataset'!O69,'Discount Rate'!A:B,2,) -> 0.05 | AC69: =Y69*AB69 -> 120 | AD69: =Y69-AB69-Z69 -> 2399.85
A70: ORD-00069 | B70: CUST-672 | C70: REP-22 | D70: Fatima Adebayo | E70: Fatima | F70: Adebayo | G70: 45740 | H70: =YEAR(G70) -> 2025 | I70: =TEXT(G70,"mmmm") -> March | J70: =TEXT(G70,"dddd") -> Monday | K70: 0.58436343 | L70: =HOUR(K70) -> 14 | M70: =MINUTE(K70) -> 1 | N70: =SECOND(K70) -> 29 | O70: Laptop | P70: Computers | Q70: 10 | R70: 1002.21 | S70: =VLOOKUP(O70,'Product-cost'!A:B,2,) -> 600 | T70: South America | U70: fatimaadebayo@tg.inc | V70: Fantastic Customer Service | W70: positive | X70: =R70*Q70 -> 10022.1 | Y70: =S70*Q70 -> 6000 | Z70: =VLOOKUP(T70,Taxrate!A:B,2,FALSE) -> 0.15 | AA70: =X70*Z70 -> 1503.315 | AB70: =VLOOKUP('Sales Dataset'!O70,'Discount Rate'!A:B,2,) -> 0.05 | AC70: =Y70*AB70 -> 300 | AD70: =Y70-AB70-Z70 -> 5999.8
A71: ORD-00070 | B71: CUST-470 | C71: REP-12 | D71: Olivia Patel | E71: Olivia | F71: Patel | G71: 45054 | H71: =YEAR(G71) -> 2023 | I71: =TEXT(G71,"mmmm") -> May | J71: =TEXT(G71,"dddd") -> Monday | K71: 0.60931713 | L71: =HOUR(K71) -> 14 | M71: =MINUTE(K71) -> 37 | N71: =SECOND(K71) -> 25 | O71: Smartwatch | P71: Wearables | Q71: 7 | R71: 258.04 | S71: =VLOOKUP(O71,'Product-cost'!A:B,2,) -> 150 | T71: Europe | U71: oliviapatel@tg.inc | V71: Good Value For Money | W71: positive | X71: =R71*Q71 -> 1806.28 | Y71: =S71*Q71 -> 1050 | Z71: =VLOOKUP(T71,Taxrate!A:B,2,FALSE) -> 0.2 | AA71: =X71*Z71 -> 361.256 | AB71: =VLOOKUP('Sales Dataset'!O71,'Discount Rate'!A:B,2,) -> 0.07 | AC71: =Y71*AB71 -> 73.5 | AD71: =Y71-AB71-Z71 -> 1049.73
A72: ORD-00071 | B72: CUST-459 | C72: REP-14 | D72: Maria Garcia | E72: Maria | F72: Garcia | G72: 45137 | H72: =YEAR(G72) -> 2023 | I72: =TEXT(G72,"mmmm") -> July | J72: =TEXT(G72,"dddd") -> Sunday | K72: 0.50846065 | L72: =HOUR(K72) -> 12 | M72: =MINUTE(K72) -> 12 | N72: =SECOND(K72) -> 11 | O72: Smartwatch | P72: Wearables | Q72: 13 | R72: 195.49 | S72: =VLOOKUP(O72,'Product-cost'!A:B,2,) -> 150 | T72: South America | U72: mariagarcia@techgadgetsco.com | V72: Great Product | W72: positive | X72: =R72*Q72 -> 2541.37 | Y72: =S72*Q72 -> 1950 | Z72: =VLOOKUP(T72,Taxrate!A:B,2,FALSE) -> 0.15 | AA72: =X72*Z72 -> 381.2055 | AB72: =VLOOKUP('Sales Dataset'!O72,'Discount Rate'!A:B,2,) -> 0.07 | AC72: =Y72*AB72 -> 136.5 | AD72: =Y72-AB72-Z72 -> 1949.78
A73: ORD-00072 | B73: CUST-169 | C73: REP-29 | D73: Sophie Lee | E73: Sophie | F73: Lee | G73: 46220 | H73: =YEAR(G73) -> 2026 | I73: =TEXT(G73,"mmmm") -> July | J73: =TEXT(G73,"dddd") -> Friday | K73: 0.84556713 | L73: =HOUR(K73) -> 20 | M73: =MINUTE(K73) -> 17 | N73: =SECOND(K73) -> 37 | O73: Laptop | P73: Computers | Q73: 2 | R73: 1025.96 | S73: =VLOOKUP(O73,'Product-cost'!A:B,2,) -> 600 | T73: North America | U73: sophielee@techgadgetsco.com | V73: Would Buy Again | W73: positive | X73: =R73*Q73 -> 2051.92 | Y73: =S73*Q73 -> 1200 | Z73: =VLOOKUP(T73,Taxrate!A:B,2,FALSE) -> 0.07 | AA73: =X73*Z73 -> 143.6344 | AB73: =VLOOKUP('Sales Dataset'!O73,'Discount Rate'!A:B,2,) -> 0.05 | AC73: =Y73*AB73 -> 60 | AD73: =Y73-AB73-Z73 -> 1199.88
A74: ORD-00073 | B74: CUST-667 | C74: REP-11 | D74: Emma Dubois | E74: Emma | F74: Dubois | G74: 46097 | H74: =YEAR(G74) -> 2026 | I74: =TEXT(G74,"mmmm") -> March | J74: =TEXT(G74,"dddd") -> Monday | K74: 0.56840278 | L74: =HOUR(K74) -> 13 | M74: =MINUTE(K74) -> 38 | N74: =SECOND(K74) -> 30 | O74: Smartwatch | P74: Wearables | Q74: 1 | R74: 265.21 | S74: =VLOOKUP(O74,'Product-cost'!A:B,2,) -> 150 | T74: Asia | U74: emmadubois@techgadgetsco.com | V74: Quick Shipping | W74: positive | X74: =R74*Q74 -> 265.21 | Y74: =S74*Q74 -> 150 | Z74: =VLOOKUP(T74,Taxrate!A:B,2,FALSE) -> 0.1 | AA74: =X74*Z74 -> 26.521 | AB74: =VLOOKUP('Sales Dataset'!O74,'Discount Rate'!A:B,2,) -> 0.07 | AC74: =Y74*AB74 -> 10.5 | AD74: =Y74-AB74-Z74 -> 149.83
A75: ORD-00074 | B75: CUST-635 | C75: REP-35 | D75: Carlos Rodriguez | E75: Carlos | F75: Rodriguez | G75: 45672 | H75: =YEAR(G75) -> 2025 | I75: =TEXT(G75,"mmmm") -> January | J75: =TEXT(G75,"dddd") -> Wednesday | K75: 0.51696759 | L75: =HOUR(K75) -> 12 | M75: =MINUTE(K75) -> 24 | N75: =SECOND(K75) -> 26 | O75: Tablet | P75: Tablets | Q75: 1 | R75: 449.46 | S75: =VLOOKUP(O75,'Product-cost'!A:B,2,) -> 200 | T75: North America | U75: carlosrodriguez@sales.techg.com | W75: neutral | X75: =R75*Q75 -> 449.46 | Y75: =S75*Q75 -> 200 | Z75: =VLOOKUP(T75,Taxrate!A:B,2,FALSE) -> 0.07 | AA75: =X75*Z75 -> 31.4622 | AB75: =VLOOKUP('Sales Dataset'!O75,'Discount Rate'!A:B,2,) -> 0.08 | AC75: =Y75*AB75 -> 16 | AD75: =Y75-AB75-Z75 -> 199.85
A76: ORD-00075 | B76: CUST-994 | C76: REP-14 | D76: Maria Garcia | E76: Maria | F76: Garcia | G76: 45093 | H76: =YEAR(G76) -> 2023 | I76: =TEXT(G76,"mmmm") -> June | J76: =TEXT(G76,"dddd") -> Friday | K76: 0.55533565 | L76: =HOUR(K76) -> 13 | M76: =MINUTE(K76) -> 19 | N76: =SECOND(K76) -> 41 | O76: Headphones | P76: Audio | Q76: 12 | R76: 143.22 | S76: =VLOOKUP(O76,'Product-cost'!A:B,2,) -> 50 | T76: South America | U76: mariagarcia@sales.techg.com | W76: neutral | X76: =R76*Q76 -> 1718.64 | Y76: =S76*Q76 -> 600 | Z76: =VLOOKUP(T76,Taxrate!A:B,2,FALSE) -> 0.15 | AA76: =X76*Z76 -> 257.796 | AB76: =VLOOKUP('Sales Dataset'!O76,'Discount Rate'!A:B,2,) -> 0.03 | AC76: =Y76*AB76 -> 18 | AD76: =Y76-AB76-Z76 -> 599.82
A77: ORD-00076 | B77: CUST-118 | C77: REP-22 | D77: Fatima Adebayo | E77: Fatima | F77: Adebayo | G77: 45413 | H77: =YEAR(G77) -> 2024 | I77: =TEXT(G77,"mmmm") -> May | J77: =TEXT(G77,"dddd") -> Wednesday | K77: 0.57605324 | L77: =HOUR(K77) -> 13 | M77: =MINUTE(K77) -> 49 | N77: =SECOND(K77) -> 31 | O77: Smartphone | P77: Mobile Devices | Q77: 3 | R77: 568.74 | S77: =VLOOKUP(O77,'Product-cost'!A:B,2,) -> 300 | T77: North America | U77: fatimaadebayo@sales.techg.com | W77: neutral | X77: =R77*Q77 -> 1706.22 | Y77: =S77*Q77 -> 900 | Z77: =VLOOKUP(T77,Taxrate!A:B,2,FALSE) -> 0.07 | AA77: =X77*Z77 -> 119.4354 | AB77: =VLOOKUP('Sales Dataset'!O77,'Discount Rate'!A:B,2,) -> 0.1 | AC77: =Y77*AB77 -> 90 | AD77: =Y77-AB77-Z77 -> 899.83
A78: ORD-00077 | B78: CUST-234 | C78: REP-35 | D78: Carlos Rodriguez | E78: Carlos | F78: Rodriguez | G78: 45271 | H78: =YEAR(G78) -> 2023 | I78: =TEXT(G78,"mmmm") -> December | J78: =TEXT(G78,"dddd") -> Monday | K78: 0.45398148 | L78: =HOUR(K78) -> 10 | M78: =MINUTE(K78) -> 53 | N78: =SECOND(K78) -> 44 | O78: Smartwatch | P78: Wearables | Q78: 3 | R78: 180.81 | S78: =VLOOKUP(O78,'Product-cost'!A:B,2,) -> 150 | T78: Asia | U78: carlosrodriguez@techgadgetsco.com | W78: neutral | X78: =R78*Q78 -> 542.43 | Y78: =S78*Q78 -> 450 | Z78: =VLOOKUP(T78,Taxrate!A:B,2,FALSE) -> 0.1 | AA78: =X78*Z78 -> 54.243 | AB78: =VLOOKUP('Sales Dataset'!O78,'Discount Rate'!A:B,2,) -> 0.07 | AC78: =Y78*AB78 -> 31.5 | AD78: =Y78-AB78-Z78 -> 449.83
A79: ORD-00078 | B79: CUST-344 | C79: REP-20 | D79: Sophie Lee | E79: Sophie | F79: Lee | G79: 45324 | H79: =YEAR(G79) -> 2024 | I79: =TEXT(G79,"mmmm") -> February | J79: =TEXT(G79,"dddd") -> Friday | K79: 0.77532407 | L79: =HOUR(K79) -> 18 | M79: =MINUTE(K79) -> 36 | N79: =SECOND(K79) -> 28 | O79: Headphones | P79: Audio | Q79: 13 | R79: 159.56 | S79: =VLOOKUP(O79,'Product-cost'!A:B,2,) -> 50 | T79: Europe | U79: sophielee@sales.techg.com | W79: neutral | X79: =R79*Q79 -> 2074.28 | Y79: =S79*Q79 -> 650 | Z79: =VLOOKUP(T79,Taxrate!A:B,2,FALSE) -> 0.2 | AA79: =X79*Z79 -> 414.856 | AB79: =VLOOKUP('Sales Dataset'!O79,'Discount Rate'!A:B,2,) -> 0.03 | AC79: =Y79*AB79 -> 19.5 | AD79: =Y79-AB79-Z79 -> 649.77
A80: ORD-00079 | B80: CUST-205 | C80: REP-32 | D80: Maria Garcia | E80: Maria | F80: Garcia | G80: 45451 | H80: =YEAR(G80) -> 2024 | I80: =TEXT(G80,"mmmm") -> June | J80: =TEXT(G80,"dddd") -> Saturday | K80: 0.84047454 | L80: =HOUR(K80) -> 20 | M80: =MINUTE(K80) -> 10 | N80: =SECOND(K80) -> 17 | O80: Headphones | P80: Audio | Q80: 3 | R80: 126.88 | S80: =VLOOKUP(O80,'Product-cost'!A:B,2,) -> 50 | T80: Europe | U80: mariagarcia@tg.inc | W80: neutral | X80: =R80*Q80 -> 380.64 | Y80: =S80*Q80 -> 150 | Z80: =VLOOKUP(T80,Taxrate!A:B,2,FALSE) -> 0.2 | AA80: =X80*Z80 -> 76.128 | AB80: =VLOOKUP('Sales Dataset'!O80,'Discount Rate'!A:B,2,) -> 0.03 | AC80: =Y80*AB80 -> 4.5 | AD80: =Y80-AB80-Z80 -> 149.77
A81: ORD-00080 | B81: CUST-183 | C81: REP-22 | D81: Fatima Adebayo | E81: Fatima | F81: Adebayo | G81: 44984 | H81: =YEAR(G81) -> 2023 | I81: =TEXT(G81,"mmmm") -> February | J81: =TEXT(G81,"dddd") -> Monday | K81: 0.41232639 | L81: =HOUR(K81) -> 9 | M81: =MINUTE(K81) -> 53 | N81: =SECOND(K81) -> 45 | O81: Tablet | P81: Tablets | Q81: 3 | R81: 500 | S81: =VLOOKUP(O81,'Product-cost'!A:B,2,) -> 200 | T81: South America | U81: fatimaadebayo@tg.inc | V81: Perfect Fit | W81: positive | X81: =R81*Q81 -> 1500 | Y81: =S81*Q81 -> 600 | Z81: =VLOOKUP(T81,Taxrate!A:B,2,FALSE) -> 0.15 | AA81: =X81*Z81 -> 225 | AB81: =VLOOKUP('Sales Dataset'!O81,'Discount Rate'!A:B,2,) -> 0.08 | AC81: =Y81*AB81 -> 48 | AD81: =Y81-AB81-Z81 -> 599.77
A82: ORD-00081 | B82: CUST-320 | C82: REP-14 | D82: Maria Garcia | E82: Maria | F82: Garcia | G82: 46173 | H82: =YEAR(G82) -> 2026 | I82: =TEXT(G82,"mmmm") -> May | J82: =TEXT(G82,"dddd") -> Sunday | K82: 0.40923611 | L82: =HOUR(K82) -> 9 | M82: =MINUTE(K82) -> 49 | N82: =SECOND(K82) -> 18 | O82: Smartphone | P82: Mobile Devices | Q82: 1 | R82: 671.69 | S82: =VLOOKUP(O82,'Product-cost'!A:B,2,) -> 300 | T82: Africa | U82: mariagarcia@tg.inc | V82: Excellent Quality | W82: positive | X82: =R82*Q82 -> 671.69 | Y82: =S82*Q82 -> 300 | Z82: =VLOOKUP(T82,Taxrate!A:B,2,FALSE) -> 0.12 | AA82: =X82*Z82 -> 80.6028 | AB82: =VLOOKUP('Sales Dataset'!O82,'Discount Rate'!A:B,2,) -> 0.1 | AC82: =Y82*AB82 -> 30 | AD82: =Y82-AB82-Z82 -> 299.78
A83: ORD-00082 | B83: CUST-398 | C83: REP-24 | D83: Liam Chen | E83: Liam | F83: Chen | G83: 46186 | H83: =YEAR(G83) -> 2026 | I83: =TEXT(G83,"mmmm") -> June | J83: =TEXT(G83,"dddd") -> Saturday | K83: 0.48363426 | L83: =HOUR(K83) -> 11 | M83: =MINUTE(K83) -> 36 | N83: =SECOND(K83) -> 26 | O83: Smartphone | P83: Mobile Devices | Q83: 2 | R83: 588.18 | S83: =VLOOKUP(O83,'Product-cost'!A:B,2,) -> 300 | T83: Africa | U83: liamchen@techgadgetsco.com | V83: Excellent Quality | W83: positive | X83: =R83*Q83 -> 1176.36 | Y83: =S83*Q83 -> 600 | Z83: =VLOOKUP(T83,Taxrate!A:B,2,FALSE) -> 0.12 | AA83: =X83*Z83 -> 141.1632 | AB83: =VLOOKUP('Sales Dataset'!O83,'Discount Rate'!A:B,2,) -> 0.1 | AC83: =Y83*AB83 -> 60 | AD83: =Y83-AB83-Z83 -> 599.78
A84: ORD-00083 | B84: CUST-482 | C84: REP-18 | D84: Noah Kim | E84: Noah | F84: Kim | G84: 45658 | H84: =YEAR(G84) -> 2025 | I84: =TEXT(G84,"mmmm") -> January | J84: =TEXT(G84,"dddd") -> Wednesday | K84: 0.55261574 | L84: =HOUR(K84) -> 13 | M84: =MINUTE(K84) -> 15 | N84: =SECOND(K84) -> 46 | O84: Laptop | P84: Computers | Q84: 12 | R84: 866.7 | S84: =VLOOKUP(O84,'Product-cost'!A:B,2,) -> 600 | T84: Asia | U84: noahkim@tg.inc | V84: Perfect Fit | W84: positive | X84: =R84*Q84 -> 10400.4 | Y84: =S84*Q84 -> 7200 | Z84: =VLOOKUP(T84,Taxrate!A:B,2,FALSE) -> 0.1 | AA84: =X84*Z84 -> 1040.04 | AB84: =VLOOKUP('Sales Dataset'!O84,'Discount Rate'!A:B,2,) -> 0.05 | AC84: =Y84*AB84 -> 360 | AD84: =Y84-AB84-Z84 -> 7199.85
A85: ORD-00084 | B85: CUST-238 | C85: REP-12 | D85: Olivia Patel | E85: Olivia | F85: Patel | G85: 45002 | H85: =YEAR(G85) -> 2023 | I85: =TEXT(G85,"mmmm") -> March | J85: =TEXT(G85,"dddd") -> Friday | K85: 0.46030093 | L85: =HOUR(K85) -> 11 | M85: =MINUTE(K85) -> 2 | N85: =SECOND(K85) -> 50 | O85: Smartphone | P85: Mobile Devices | Q85: 6 | R85: 634.62 | S85: =VLOOKUP(O85,'Product-cost'!A:B,2,) -> 300 | T85: Africa | U85: oliviapatel@tg.inc | W85: neutral | X85: =R85*Q85 -> 3807.72 | Y85: =S85*Q85 -> 1800 | Z85: =VLOOKUP(T85,Taxrate!A:B,2,FALSE) -> 0.12 | AA85: =X85*Z85 -> 456.9264 | AB85: =VLOOKUP('Sales Dataset'!O85,'Discount Rate'!A:B,2,) -> 0.1 | AC85: =Y85*AB85 -> 180 | AD85: =Y85-AB85-Z85 -> 1799.78
A86: ORD-00085 | B86: CUST-439 | C86: REP-18 | D86: Noah Kim | E86: Noah | F86: Kim | G86: 45680 | H86: =YEAR(G86) -> 2025 | I86: =TEXT(G86,"mmmm") -> January | J86: =TEXT(G86,"dddd") -> Thursday | K86: 0.6162963 | L86: =HOUR(K86) -> 14 | M86: =MINUTE(K86) -> 47 | N86: =SECOND(K86) -> 28 | O86: Headphones | P86: Audio | Q86: 3 | R86: 157.31 | S86: =VLOOKUP(O86,'Product-cost'!A:B,2,) -> 50 | T86: Africa | U86: noahkim@tg.inc | V86: Not As Expected | W86: negative | X86: =R86*Q86 -> 471.93 | Y86: =S86*Q86 -> 150 | Z86: =VLOOKUP(T86,Taxrate!A:B,2,FALSE) -> 0.12 | AA86: =X86*Z86 -> 56.6316 | AB86: =VLOOKUP('Sales Dataset'!O86,'Discount Rate'!A:B,2,) -> 0.03 | AC86: =Y86*AB86 -> 4.5 | AD86: =Y86-AB86-Z86 -> 149.85
A87: ORD-00086 | B87: CUST-428 | C87: REP-13 | D87: Ahmed Khan | E87: Ahmed | F87: Khan | G87: 45333 | H87: =YEAR(G87) -> 2024 | I87: =TEXT(G87,"mmmm") -> February | J87: =TEXT(G87,"dddd") -> Sunday | K87: 0.51988426 | L87: =HOUR(K87) -> 12 | M87: =MINUTE(K87) -> 28 | N87: =SECOND(K87) -> 38 | O87: Headphones | P87: Audio | Q87: 8 | R87: 123.18 | S87: =VLOOKUP(O87,'Product-cost'!A:B,2,) -> 50 | T87: Asia | U87: ahmedkhan@tg.inc | W87: neutral | X87: =R87*Q87 -> 985.44 | Y87: =S87*Q87 -> 400 | Z87: =VLOOKUP(T87,Taxrate!A:B,2,FALSE) -> 0.1 | AA87: =X87*Z87 -> 98.544 | AB87: =VLOOKUP('Sales Dataset'!O87,'Discount Rate'!A:B,2,) -> 0.03 | AC87: =Y87*AB87 -> 12 | AD87: =Y87-AB87-Z87 -> 399.87
A88: ORD-00087 | B88: CUST-920 | C88: REP-15 | D88: Sophie Lee | E88: Sophie | F88: Lee | G88: 45219 | H88: =YEAR(G88) -> 2023 | I88: =TEXT(G88,"mmmm") -> October | J88: =TEXT(G88,"dddd") -> Friday | K88: 0.33893519 | L88: =HOUR(K88) -> 8 | M88: =MINUTE(K88) -> 8 | N88: =SECOND(K88) -> 4 | O88: Smartphone | P88: Mobile Devices | Q88: 6 | R88: 764.84 | S88: =VLOOKUP(O88,'Product-cost'!A:B,2,) -> 300 | T88: North America | U88: sophielee@techgadgetsco.com | V88: Fast Delivery | W88: positive | X88: =R88*Q88 -> 4589.04 | Y88: =S88*Q88 -> 1800 | Z88: =VLOOKUP(T88,Taxrate!A:B,2,FALSE) -> 0.07 | AA88: =X88*Z88 -> 321.2328 | AB88: =VLOOKUP('Sales Dataset'!O88,'Discount Rate'!A:B,2,) -> 0.1 | AC88: =Y88*AB88 -> 180 | AD88: =Y88-AB88-Z88 -> 1799.83
A89: ORD-00088 | B89: CUST-475 | C89: REP-23 | D89: Noah Kim | E89: Noah | F89: Kim | G89: 46257 | H89: =YEAR(G89) -> 2026 | I89: =TEXT(G89,"mmmm") -> August | J89: =TEXT(G89,"dddd") -> Sunday | K89: 0.46320602 | L89: =HOUR(K89) -> 11 | M89: =MINUTE(K89) -> 7 | N89: =SECOND(K89) -> 1 | O89: Smartphone | P89: Mobile Devices | Q89: 7 | R89: 515.33 | S89: =VLOOKUP(O89,'Product-cost'!A:B,2,) -> 300 | T89: Asia | U89: noahkim@sales.techg.com | V89: Battery Life Amazing | W89: positive | X89: =R89*Q89 -> 3607.31 | Y89: =S89*Q89 -> 2100 | Z89: =VLOOKUP(T89,Taxrate!A:B,2,FALSE) -> 0.1 | AA89: =X89*Z89 -> 360.731 | AB89: =VLOOKUP('Sales Dataset'!O89,'Discount Rate'!A:B,2,) -> 0.1 | AC89: =Y89*AB89 -> 210 | AD89: =Y89-AB89-Z89 -> 2099.8
A90: ORD-00089 | B90: CUST-276 | C90: REP-28 | D90: Maria Garcia | E90: Maria | F90: Garcia | G90: 46323 | H90: =YEAR(G90) -> 2026 | I90: =TEXT(G90,"mmmm") -> October | J90: =TEXT(G90,"dddd") -> Wednesday | K90: 0.76579861 | L90: =HOUR(K90) -> 18 | M90: =MINUTE(K90) -> 22 | N90: =SECOND(K90) -> 45 | O90: Laptop | P90: Computers | Q90: 5 | R90: 1225.68 | S90: =VLOOKUP(O90,'Product-cost'!A:B,2,) -> 600 | T90: Europe | U90: mariagarcia@sales.techg.com | V90: Packaging Was Damaged | W90: negative | X90: =R90*Q90 -> 6128.4 | Y90: =S90*Q90 -> 3000 | Z90: =VLOOKUP(T90,Taxrate!A:B,2,FALSE) -> 0.2 | AA90: =X90*Z90 -> 1225.68 | AB90: =VLOOKUP('Sales Dataset'!O90,'Discount Rate'!A:B,2,) -> 0.05 | AC90: =Y90*AB90 -> 150 | AD90: =Y90-AB90-Z90 -> 2999.75
A91: ORD-00090 | B91: CUST-469 | C91: REP-33 | D91: Ahmed Khan | E91: Ahmed | F91: Khan | G91: 45884 | H91: =YEAR(G91) -> 2025 | I91: =TEXT(G91,"mmmm") -> August | J91: =TEXT(G91,"dddd") -> Friday | K91: 0.74728009 | L91: =HOUR(K91) -> 17 | M91: =MINUTE(K91) -> 56 | N91: =SECOND(K91) -> 5 | O91: Laptop | P91: Computers | Q91: 12 | R91: 1062.85 | S91: =VLOOKUP(O91,'Product-cost'!A:B,2,) -> 600 | T91: South America | U91: ahmedkhan@tg.inc | V91: Would Buy Again | W91: positive | X91: =R91*Q91 -> 12754.2 | Y91: =S91*Q91 -> 7200 | Z91: =VLOOKUP(T91,Taxrate!A:B,2,FALSE) -> 0.15 | AA91: =X91*Z91 -> 1913.13 | AB91: =VLOOKUP('Sales Dataset'!O91,'Discount Rate'!A:B,2,) -> 0.05 | AC91: =Y91*AB91 -> 360 | AD91: =Y91-AB91-Z91 -> 7199.8
A92: ORD-00091 | B92: CUST-999 | C92: REP-33 | D92: Ahmed Khan | E92: Ahmed | F92: Khan | G92: 45191 | H92: =YEAR(G92) -> 2023 | I92: =TEXT(G92,"mmmm") -> September | J92: =TEXT(G92,"dddd") -> Friday | K92: 0.70758102 | L92: =HOUR(K92) -> 16 | M92: =MINUTE(K92) -> 58 | N92: =SECOND(K92) -> 55 | O92: Laptop | P92: Computers | Q92: 9 | R92: 882.33 | S92: =VLOOKUP(O92,'Product-cost'!A:B,2,) -> 600 | T92: Asia | U92: ahmedkhan@sales.techg.com | V92: Love The Design | W92: positive | X92: =R92*Q92 -> 7940.97 | Y92: =S92*Q92 -> 5400 | Z92: =VLOOKUP(T92,Taxrate!A:B,2,FALSE) -> 0.1 | AA92: =X92*Z92 -> 794.097 | AB92: =VLOOKUP('Sales Dataset'!O92,'Discount Rate'!A:B,2,) -> 0.05 | AC92: =Y92*AB92 -> 270 | AD92: =Y92-AB92-Z92 -> 5399.85
A93: ORD-00092 | B93: CUST-750 | C93: REP-33 | D93: Ahmed Khan | E93: Ahmed | F93: Khan | G93: 45183 | H93: =YEAR(G93) -> 2023 | I93: =TEXT(G93,"mmmm") -> September | J93: =TEXT(G93,"dddd") -> Thursday | K93: 0.73200231 | L93: =HOUR(K93) -> 17 | M93: =MINUTE(K93) -> 34 | N93: =SECOND(K93) -> 5 | O93: Smartwatch | P93: Wearables | Q93: 10 | R93: 192.96 | S93: =VLOOKUP(O93,'Product-cost'!A:B,2,) -> 150 | T93: Africa | U93: ahmedkhan@tg.inc | V93: Quick Shipping | W93: positive | X93: =R93*Q93 -> 1929.6 | Y93: =S93*Q93 -> 1500 | Z93: =VLOOKUP(T93,Taxrate!A:B,2,FALSE) -> 0.12 | AA93: =X93*Z93 -> 231.552 | AB93: =VLOOKUP('Sales Dataset'!O93,'Discount Rate'!A:B,2,) -> 0.07 | AC93: =Y93*AB93 -> 105 | AD93: =Y93-AB93-Z93 -> 1499.81
A94: ORD-00093 | B94: CUST-756 | C94: REP-34 | D94: Fatima Adebayo | E94: Fatima | F94: Adebayo | G94: 46260 | H94: =YEAR(G94) -> 2026 | I94: =TEXT(G94,"mmmm") -> August | J94: =TEXT(G94,"dddd") -> Wednesday | K94: 0.85863426 | L94: =HOUR(K94) -> 20 | M94: =MINUTE(K94) -> 36 | N94: =SECOND(K94) -> 26 | O94: Smartwatch | P94: Wearables | Q94: 8 | R94: 236.01 | S94: =VLOOKUP(O94,'Product-cost'!A:B,2,) -> 150 | T94: Asia | U94: fatimaadebayo@sales.techg.com | W94: neutral | X94: =R94*Q94 -> 1888.08 | Y94: =S94*Q94 -> 1200 | Z94: =VLOOKUP(T94,Taxrate!A:B,2,FALSE) -> 0.1 | AA94: =X94*Z94 -> 188.808 | AB94: =VLOOKUP('Sales Dataset'!O94,'Discount Rate'!A:B,2,) -> 0.07 | AC94: =Y94*AB94 -> 84 | AD94: =Y94-AB94-Z94 -> 1199.83
A95: ORD-00094 | B95: CUST-525 | C95: REP-29 | D95: Sophie Lee | E95: Sophie | F95: Lee | G95: 45344 | H95: =YEAR(G95) -> 2024 | I95: =TEXT(G95,"mmmm") -> February | J95: =TEXT(G95,"dddd") -> Thursday | K95: 0.71481481 | L95: =HOUR(K95) -> 17 | M95: =MINUTE(K95) -> 9 | N95: =SECOND(K95) -> 20 | O95: Tablet | P95: Tablets | Q95: 14 | R95: 399.74 | S95: =VLOOKUP(O95,'Product-cost'!A:B,2,) -> 200 | T95: Asia | U95: sophielee@techgadgetsco.com | V95: Good Value For Money | W95: positive | X95: =R95*Q95 -> 5596.36 | Y95: =S95*Q95 -> 2800 | Z95: =VLOOKUP(T95,Taxrate!A:B,2,FALSE) -> 0.1 | AA95: =X95*Z95 -> 559.636 | AB95: =VLOOKUP('Sales Dataset'!O95,'Discount Rate'!A:B,2,) -> 0.08 | AC95: =Y95*AB95 -> 224 | AD95: =Y95-AB95-Z95 -> 2799.82
A96: ORD-00095 | B96: CUST-397 | C96: REP-23 | D96: Noah Kim | E96: Noah | F96: Kim | G96: 45435 | H96: =YEAR(G96) -> 2024 | I96: =TEXT(G96,"mmmm") -> May | J96: =TEXT(G96,"dddd") -> Thursday | K96: 0.88957176 | L96: =HOUR(K96) -> 21 | M96: =MINUTE(K96) -> 20 | N96: =SECOND(K96) -> 59 | O96: Smartwatch | P96: Wearables | Q96: 4 | R96: 230.81 | S96: =VLOOKUP(O96,'Product-cost'!A:B,2,) -> 150 | T96: Africa | U96: noahkim@sales.techg.com | V96: Would Buy Again | W96: positive | X96: =R96*Q96 -> 923.24 | Y96: =S96*Q96 -> 600 | Z96: =VLOOKUP(T96,Taxrate!A:B,2,FALSE) -> 0.12 | AA96: =X96*Z96 -> 110.7888 | AB96: =VLOOKUP('Sales Dataset'!O96,'Discount Rate'!A:B,2,) -> 0.07 | AC96: =Y96*AB96 -> 42 | AD96: =Y96-AB96-Z96 -> 599.81
A97: ORD-00096 | B97: CUST-320 | C97: REP-34 | D97: Fatima Adebayo | E97: Fatima | F97: Adebayo | G97: 45203 | H97: =YEAR(G97) -> 2023 | I97: =TEXT(G97,"mmmm") -> October | J97: =TEXT(G97,"dddd") -> Wednesday | K97: 0.52196759 | L97: =HOUR(K97) -> 12 | M97: =MINUTE(K97) -> 31 | N97: =SECOND(K97) -> 38 | O97: Headphones | P97: Audio | Q97: 1 | R97: 152.32 | S97: =VLOOKUP(O97,'Product-cost'!A:B,2,) -> 50 | T97: Asia | U97: fatimaadebayo@sales.techg.com | W97: neutral | X97: =R97*Q97 -> 152.32 | Y97: =S97*Q97 -> 50 | Z97: =VLOOKUP(T97,Taxrate!A:B,2,FALSE) -> 0.1 | AA97: =X97*Z97 -> 15.232 | AB97: =VLOOKUP('Sales Dataset'!O97,'Discount Rate'!A:B,2,) -> 0.03 | AC97: =Y97*AB97 -> 1.5 | AD97: =Y97-AB97-Z97 -> 49.87
A98: ORD-00097 | B98: CUST-395 | C98: REP-12 | D98: Olivia Patel | E98: Olivia | F98: Patel | G98: 45959 | H98: =YEAR(G98) -> 2025 | I98: =TEXT(G98,"mmmm") -> October | J98: =TEXT(G98,"dddd") -> Wednesday | K98: 0.85783565 | L98: =HOUR(K98) -> 20 | M98: =MINUTE(K98) -> 35 | N98: =SECOND(K98) -> 17 | O98: Smartwatch | P98: Wearables | Q98: 2 | R98: 186.63 | S98: =VLOOKUP(O98,'Product-cost'!A:B,2,) -> 150 | T98: Asia | U98: oliviapatel@tg.inc | V98: A Bit Expensive But Worth It | W98: neutral | X98: =R98*Q98 -> 373.26 | Y98: =S98*Q98 -> 300 | Z98: =VLOOKUP(T98,Taxrate!A:B,2,FALSE) -> 0.1 | AA98: =X98*Z98 -> 37.326 | AB98: =VLOOKUP('Sales Dataset'!O98,'Discount Rate'!A:B,2,) -> 0.07 | AC98: =Y98*AB98 -> 21 | AD98: =Y98-AB98-Z98 -> 299.83
A99: ORD-00098 | B99: CUST-146 | C99: REP-11 | D99: Emma Dubois | E99: Emma | F99: Dubois | G99: 45609 | H99: =YEAR(G99) -> 2024 | I99: =TEXT(G99,"mmmm") -> November | J99: =TEXT(G99,"dddd") -> Wednesday | K99: 0.68690972 | L99: =HOUR(K99) -> 16 | M99: =MINUTE(K99) -> 29 | N99: =SECOND(K99) -> 9 | O99: Smartwatch | P99: Wearables | Q99: 3 | R99: 243.44 | S99: =VLOOKUP(O99,'Product-cost'!A:B,2,) -> 150 | T99: Europe | U99: emmadubois@tg.inc | V99: Great Product | W99: positive | X99: =R99*Q99 -> 730.32 | Y99: =S99*Q99 -> 450 | Z99: =VLOOKUP(T99,Taxrate!A:B,2,FALSE) -> 0.2 | AA99: =X99*Z99 -> 146.064 | AB99: =VLOOKUP('Sales Dataset'!O99,'Discount Rate'!A:B,2,) -> 0.07 | AC99: =Y99*AB99 -> 31.5 | AD99: =Y99-AB99-Z99 -> 449.73
A100: ORD-00099 | B100: CUST-676 | C100: REP-20 | D100: Sophie Lee | E100: Sophie | F100: Lee | G100: 45018 | H100: =YEAR(G100) -> 2023 | I100: =TEXT(G100,"mmmm") -> April | J100: =TEXT(G100,"dddd") -> Sunday | K100: 0.5716088 | L100: =HOUR(K100) -> 13 | M100: =MINUTE(K100) -> 43 | N100: =SECOND(K100) -> 7 | O100: Headphones | P100: Audio | Q100: 13 | R100: 185.41 | S100: =VLOOKUP(O100,'Product-cost'!A:B,2,) -> 50 | T100: North America | U100: sophielee@sales.techg.com | V100: Very Satisfied | W100: positive | X100: =R100*Q100 -> 2410.33 | Y100: =S100*Q100 -> 650 | Z100: =VLOOKUP(T100,Taxrate!A:B,2,FALSE) -> 0.07 | AA100: =X100*Z100 -> 168.7231 | AB100: =VLOOKUP('Sales Dataset'!O100,'Discount Rate'!A:B,2,) -> 0.03 | AC100: =Y100*AB100 -> 19.5 | AD100: =Y100-AB100-Z100 -> 649.9
...

Sheet Product-cost
A1: Product | B1: Cost
A2: Laptop | B2: 600
A3: Smartphone | B3: 300
A4: Tablet | B4: 200
A5: Headphones | B5: 50
A6: Smartwatch | B6: 150

Sheet Taxrate
A1: Region | B1: TaxRate
A2: North America | B2: 0.07
A3: Europe | B3: 0.2
A4: Asia | B4: 0.1
A5: South America | B5: 0.15
A6: Africa | B6: 0.12

Sheet Discount Rate
A1: Product | B1: DiscountRate
A2: Laptop | B2: 0.05
A3: Smartphone | B3: 0.1
A4: Tablet | B4: 0.08
A5: Headphones | B5: 0.03
A6: Smartwatch | B6: 0.07
